Workbook

Sheet DADOS
B1: STATEMENTS (mi) | D1: 2015 | E1: 2016 | F1: 2017 | G1: 2018 | H1: 2019 | I1: 2020 | J1: 2021 | K1: 2022 | L1: 2023 | M1: 2024
D2: 12/31/2015 | E2: 12/31/2016 | F2: 12/31/2017 | G2: 12/31/2018 | H2: 12/31/2019 | I2: 12/31/2020 | J2: 12/31/2021 | K2: 12/31/2022 | L2: 12/31/2023 | M2: 12/31/2024
B4: BALANÇO PATRIMONIAL
A6: (+) | B6: ACOp | D6: =SUM('Bal patrim - Padronizado'!C10,'Bal patrim - Padronizado'!C13,'Bal patrim - Padronizado'!C18,) -> 31.74 | E6: =SUM('Bal patrim - Padronizado'!D10,'Bal patrim - Padronizado'!D13,'Bal patrim - Padronizado'!D18,) -> 33.107 | F6: =SUM('Bal patrim - Padronizado'!E10,'Bal patrim - Padronizado'!E13,'Bal patrim - Padronizado'!E18,) -> 34.141 | G6: =SUM('Bal patrim - Padronizado'!F10,'Bal patrim - Padronizado'!F13,'Bal patrim - Padronizado'!F18,) -> 21.139 | H6: =SUM('Bal patrim - Padronizado'!G10,'Bal patrim - Padronizado'!G13,'Bal patrim - Padronizado'!G18,) -> 23.61 | I6: =SUM('Bal patrim - Padronizado'!H10,'Bal patrim - Padronizado'!H13,'Bal patrim - Padronizado'!H18,) -> 23.888 | J6: =SUM('Bal patrim - Padronizado'!I10,'Bal patrim - Padronizado'!I13,'Bal patrim - Padronizado'!I18,) -> 43.215 | K6: =SUM('Bal patrim - Padronizado'!J10,'Bal patrim - Padronizado'!J13,'Bal patrim - Padronizado'!J18,) -> 47.297 | ... M6: =SUM('Bal patrim - Padronizado'!L10,'Bal patrim - Padronizado'!L13,'Bal patrim - Padronizado'!L18,) -> 63.12
A7: (-) | B7: PCOp | D7: =-SUM('Bal patrim - Padronizado'!C38,'Bal patrim - Padronizado'!C47,) -> -6.455 | E7: =-SUM('Bal patrim - Padronizado'!D38,'Bal patrim - Padronizado'!D47,) -> -3.225 | F7: =-SUM('Bal patrim - Padronizado'!E38,'Bal patrim - Padronizado'!E47,) -> -1.726 | G7: =-SUM('Bal patrim - Padronizado'!F38,'Bal patrim - Padronizado'!F47,) -> -1.925 | H7: =-SUM('Bal patrim - Padronizado'!G38,'Bal patrim - Padronizado'!G47,) -> -3.655 | I7: =-SUM('Bal patrim - Padronizado'!H38,'Bal patrim - Padronizado'!H47,) -> -6.761 | J7: =-SUM('Bal patrim - Padronizado'!I38,'Bal patrim - Padronizado'!I47,) -> -10.185 | K7: =-SUM('Bal patrim - Padronizado'!J38,'Bal patrim - Padronizado'!J47,) -> -20.362 | ... M7: =-SUM('Bal patrim - Padronizado'!L38,'Bal patrim - Padronizado'!L47,) -> -17.905
A8: (=) | B8: IOG | D8: =SUM(D6:D7) -> 25.285 | E8: =SUM(E6:E7) -> 29.882 | F8: =SUM(F6:F7) -> 32.415 | G8: =SUM(G6:G7) -> 19.214 | H8: =SUM(H6:H7) -> 19.955 | I8: =SUM(I6:I7) -> 17.127 | J8: =SUM(J6:J7) -> 33.03 | K8: =SUM(K6:K7) -> 26.935 | ... M8: =SUM(M6:M7) -> 45.215
A9: (+) | B9: AñC | D9: ='Bal patrim - Padronizado'!C34 -> 15.37 | E9: ='Bal patrim - Padronizado'!D34 -> 18.735 | F9: ='Bal patrim - Padronizado'!E34 -> 1.705 | G9: ='Bal patrim - Padronizado'!F34 -> 153.849 | H9: ='Bal patrim - Padronizado'!G34 -> 150.299 | I9: ='Bal patrim - Padronizado'!H34 -> 152.686 | J9: ='Bal patrim - Padronizado'!I34 -> 215.111 | K9: ='Bal patrim - Padronizado'!J34 -> 232.091 | ... M9: ='Bal patrim - Padronizado'!L34 -> 272.316
B10: Capital Investido | D10: =SUM(D8:D9) -> 40.655 | E10: =SUM(E8:E9) -> 48.617 | F10: =SUM(F8:F9) -> 34.12 | G10: =SUM(G8:G9) -> 173.063 | H10: =SUM(H8:H9) -> 170.254 | I10: =SUM(I8:I9) -> 169.813 | J10: =SUM(J8:J9) -> 248.141 | K10: =SUM(K8:K9) -> 259.026 | ... M10: =SUM(M8:M9) -> 317.531
B12: Variação dos dois métodos | D12: =D10-D19 -> 0 | E12: =E10-E19 -> 0 | F12: =F10-F19 -> 0 | G12: =G10-G19 -> 0 | H12: =H10-H19 -> 0 | I12: =I10-I19 -> 0 | J12: =J10-J19 -> 0 | K12: =K10-K19 -> 0 | ... M12: =M10-M19 -> 0
A14: (+) | B14: PCFin | D14: ='Bal patrim - Padronizado'!C43 -> 0.61 | E14: ='Bal patrim - Padronizado'!D43 -> 0.735 | F14: ='Bal patrim - Padronizado'!E43 -> 0.733 | G14: ='Bal patrim - Padronizado'!F43 -> 0.731 | H14: ='Bal patrim - Padronizado'!G43 -> 0.511 | I14: ='Bal patrim - Padronizado'!H43 -> 0.203 | J14: ='Bal patrim - Padronizado'!I43 -> 0.202 | K14: ='Bal patrim - Padronizado'!J43 -> 0.202 | ... M14: ='Bal patrim - Padronizado'!L43 -> 0.088
A15: (-) | B15: ACFin | D15: =-'Bal patrim - Padronizado'!C7 -> -42.264 | E15: =-'Bal patrim - Padronizado'!D7 -> -35.774 | F15: =-'Bal patrim - Padronizado'!E7 -> -18.945 | G15: =-'Bal patrim - Padronizado'!F7 -> -31.212 | H15: =-'Bal patrim - Padronizado'!G7 -> -51.746 | I15: =-'Bal patrim - Padronizado'!H7 -> -31.209 | J15: =-'Bal patrim - Padronizado'!I7 -> -17.619 | K15: =-'Bal patrim - Padronizado'!J7 -> -21.331 | ... M15: =-'Bal patrim - Padronizado'!L7 -> -7.321
A16: (=) | B16: Tesouraria | D16: =SUM(D14:D15) -> -41.654 | E16: =SUM(E14:E15) -> -35.039 | F16: =SUM(F14:F15) -> -18.212 | G16: =SUM(G14:G15) -> -30.481 | H16: =SUM(H14:H15) -> -51.235 | I16: =SUM(I14:I15) -> -31.006 | J16: =SUM(J14:J15) -> -17.417 | K16: =SUM(K14:K15) -> -21.129 | ... M16: =SUM(M14:M15) -> -7.233
A17: (+) | B17: PñC | D17: ='Bal patrim - Padronizado'!C62 -> 3.891 | E17: ='Bal patrim - Padronizado'!D62 -> 7.45 | F17: ='Bal patrim - Padronizado'!E62 -> 7.397 | G17: ='Bal patrim - Padronizado'!F62 -> 7.79 | H17: ='Bal patrim - Padronizado'!G62 -> 7.143 | I17: ='Bal patrim - Padronizado'!H62 -> 13.36 | J17: ='Bal patrim - Padronizado'!I62 -> 18.04 | K17: ='Bal patrim - Padronizado'!J62 -> 19.423 | ... M17: ='Bal patrim - Padronizado'!L62 -> 71.852
A18: (+) | B18: PL | D18: ='Bal patrim - Padronizado'!C72 -> 78.418 | E18: ='Bal patrim - Padronizado'!D72 -> 76.206 | F18: ='Bal patrim - Padronizado'!E72 -> 44.935 | G18: ='Bal patrim - Padronizado'!F72 -> 195.754 | H18: ='Bal patrim - Padronizado'!G72 -> 214.346 | I18: ='Bal patrim - Padronizado'!H72 -> 187.459 | J18: ='Bal patrim - Padronizado'!I72 -> 247.518 | K18: ='Bal patrim - Padronizado'!J72 -> 260.732 | ... M18: ='Bal patrim - Padronizado'!L72 -> 252.912
B19: Capital Investido | D19: =SUM(D16:D18) -> 40.655 | E19: =SUM(E16:E18) -> 48.617 | F19: =SUM(F16:F18) -> 34.12 | G19: =SUM(G16:G18) -> 173.063 | H19: =SUM(H16:H18) -> 170.254 | I19: =SUM(I16:I18) -> 169.813 | J19: =SUM(J16:J18) -> 248.141 | K19: =SUM(K16:K18) -> 259.026 | ... M19: =SUM(M16:M18) -> 317.531
A21: (=) | B21: Investimento Líquido | D21: 0 | E21: =-(E19-D19) -> -7.962 | F21: =-(F19-E19) -> 14.497 | G21: =-(G19-F19) -> -138.943 | H21: =-(H19-G19) -> 2.809 | I21: =-(I19-H19) -> 0.441 | J21: =-(J19-I19) -> -78.328 | K21: =-(K19-J19) -> -10.885 | L21: =-(L19-K19) -> -11.238 | M21: =-(M19-L19) -> -47.267
B24: D.R.E
A26: (+) | B26: Lucro Operacional (LAJIR) | E26: ='DRE - Ajustado 3º TRI 2025'!C20 -> 16.399 | F26: ='DRE - Ajustado 3º TRI 2025'!D20 -> 12.666 | G26: ='DRE - Ajustado 3º TRI 2025'!E20 -> 22.903 | H26: ='DRE - Ajustado 3º TRI 2025'!F20 -> 24.961 | I26: ='DRE - Ajustado 3º TRI 2025'!G20 -> 19.171 | J26: ='DRE - Ajustado 3º TRI 2025'!H20 -> 103.23 | K26: ='DRE - Ajustado 3º TRI 2025'!I20 -> 38.323 | L26: ='DRE - Ajustado 3º TRI 2025'!J20 -> 30.123 | M26: ='DRE - Ajustado 3º TRI 2025'!K20 -> 43.628
A27: (-) | B27: Alíquota IR (do LAIR) | E27: ='DRE - Ajustado 3º TRI 2025'!C31/'DRE - Ajustado 3º TRI 2025'!C30 -> 0.32721194 | F27: ='DRE - Ajustado 3º TRI 2025'!D31/'DRE - Ajustado 3º TRI 2025'!D30 -> 0.16240632 | G27: ='DRE - Ajustado 3º TRI 2025'!E31/'DRE - Ajustado 3º TRI 2025'!E30 -> 0.069491874 | H27: ='DRE - Ajustado 3º TRI 2025'!F31/'DRE - Ajustado 3º TRI 2025'!F30 -> 0.076661549 | I27: ='DRE - Ajustado 3º TRI 2025'!G31/'DRE - Ajustado 3º TRI 2025'!G30 -> 0.084462931 | J27: ='DRE - Ajustado 3º TRI 2025'!H31/'DRE - Ajustado 3º TRI 2025'!H30 -> 0.041818671 | K27: ='DRE - Ajustado 3º TRI 2025'!I31/'DRE - Ajustado 3º TRI 2025'!I30 -> 0.088876467 | L27: ='DRE - Ajustado 3º TRI 2025'!J31/'DRE - Ajustado 3º TRI 2025'!J30 -> 0.098042911 | M27: ='DRE - Ajustado 3º TRI 2025'!K31/'DRE - Ajustado 3º TRI 2025'!K30 -> 0.23857152
A28: (=) | B28: NOPAT | D28: =D26*(1-D27) -> 0 | E28: =E26*(1-E27) -> 11.033051 | F28: =F26*(1-F27) -> 10.608962 | G28: =G26*(1-G27) -> 21.311428 | H28: =H26*(1-H27) -> 23.047451 | I28: =I26*(1-I27) -> 17.551761 | J28: =J26*(1-J27) -> 98.913059 | K28: =K26*(1-K27) -> 34.916987 | ... M28: =M26*(1-M27) -> 33.219602
A30: (=) | B30: FLUXO DE CAIXA LIVRE (FCLE) | D30: =SUM(D28,D21) -> 0 | E30: =SUM(E28,E21) -> 3.0710514 | F30: =SUM(F28,F21) -> 25.105962 | G30: =SUM(G28,G21) -> -117.63157 | H30: =SUM(H28,H21) -> 25.856451 | I30: =SUM(I28,I21) -> 17.992761 | J30: =SUM(J28,J21) -> 20.585059 | K30: =SUM(K28,K21) -> 24.031987 | ... M30: =SUM(M28,M21) -> -14.047398
B34: ROIC | C34: =EXP(C35)-1 -> 0.24223623 | E34: =E28/D19 -> 0.2713824 | F34: =F28/E19 -> 0.21821506 | G34: =G28/F19 -> 0.62460222 | H34: =H28/G19 -> 0.13317376 | I34: =I28/H19 -> 0.10309162 | J34: =J28/I19 -> 0.58248225 | K34: =K28/J19 -> 0.1407143 | L34: =L28/K19 -> 0.10489161 | M34: =M28/L19 -> 0.12291538
B35: ln(1+ROIC) | C35: =AVERAGE(E35:M35) -> 0.21691317 | E35: =LN(1+E34) -> 0.24010481 | F35: =LN(1+F34) -> 0.19738672 | G35: =LN(1+G34) -> 0.485263 | H35: =LN(1+H34) -> 0.12502234 | I35: =LN(1+I34) -> 0.098116804 | J35: =LN(1+J34) -> 0.45899466 | K35: =LN(1+K34) -> 0.13165465 | L35: =LN(1+L34) -> 0.099747237 | M35: =LN(1+M34) -> 0.11592832
B36: b (taxa de retenção) | C36: =C38/C34 -> 1.059162 | E36: =E38/E34 -> 0.72164986 | F36: =F38/F34 -> -1.3664862 | G36: =G38/G34 -> 6.5196477 | H36: =H38/H34 -> -0.12187899 | I36: =I38/I34 -> -0.025125684 | J36: =J38/J34 -> 0.79188735 | K36: =K38/K34 -> 0.31173938 | L36: =L38/L34 -> 0.41362324 | M36: =M38/M34 -> 1.4228647
B37: g (=ROIC * b) | C37: =C34*C36 -> 0.25656742 | E37: =E34*E36 -> 0.19584307 | F37: =F34*F36 -> -0.29818788 | G37: =G34*G36 -> 4.0721864 | H37: =H34*H36 -> -0.016231083 | I37: =I34*I36 -> -0.0025902475 | J37: =J34*J36 -> 0.46126033 | K37: =K34*K36 -> 0.043866189 | L37: =L34*L36 -> 0.043385606 | M37: =M34*M36 -> 0.17489196
B38: g (CapInvest) | C38: =EXP(C39)-1 -> 0.25656742 | E38: =E19/D19-1 -> 0.19584307 | F38: =F19/E19-1 -> -0.29818788 | G38: =G19/F19-1 -> 4.0721864 | H38: =H19/G19-1 -> -0.016231083 | I38: =I19/H19-1 -> -0.0025902475 | J38: =J19/I19-1 -> 0.46126033 | K38: =K19/J19-1 -> 0.043866189 | L38: =L19/K19-1 -> 0.043385606 | M38: =M19/L19-1 -> 0.17489196
B39: ln[1+g(CapInvest)] | C39: =AVERAGE(E39:M39) -> 0.22838374 | E39: =LN(1+E38) -> 0.17885143 | F39: =LN(1+F38) -> -0.35408954 | G39: =LN(1+G38) -> 1.623772 | H39: =LN(1+H38) -> -0.01636425 | I39: =LN(1+I38) -> -0.002593608 | J39: =LN(1+J38) -> 0.3792993 | K39: =LN(1+K38) -> 0.04293131 | L39: =LN(1+L38) -> 0.042470816 | M39: =LN(1+M38) -> 0.16117619
B41: Receita | E41: ='DRE - Ajustado 3º TRI 2025'!C6 -> 31.353 | F41: ='DRE - Ajustado 3º TRI 2025'!D6 -> 23.646 | G41: ='DRE - Ajustado 3º TRI 2025'!E6 -> 33.684 | H41: ='DRE - Ajustado 3º TRI 2025'!F6 -> 38.621 | I41: ='DRE - Ajustado 3º TRI 2025'!G6 -> 35.93 | J41: ='DRE - Ajustado 3º TRI 2025'!H6 -> 120.319 | K41: ='DRE - Ajustado 3º TRI 2025'!I6 -> 72.058 | L41: ='DRE - Ajustado 3º TRI 2025'!J6 -> 67.307 | M41: ='DRE - Ajustado 3º TRI 2025'!K6 -> 85.999
B42: g(Receita) | C42: =EXP(C43)-1 -> 0.13442761 | D42: n/a | E42: n/a | F42: =F41/E41-1 -> -0.2458138 | G42: =G41/F41-1 -> 0.42451155 | H42: =H41/G41-1 -> 0.1465681 | I42: =I41/H41-1 -> -0.069677119 | J42: =J41/I41-1 -> 2.3487058 | K42: =K41/J41-1 -> -0.40110872 | L42: =L41/K41-1 -> -0.065932998 | M42: =M41/L41-1 -> 0.27771257
B43: ln[1+g(Rec)] | C43: =AVERAGE(F43:M43) -> 0.12612821 | D43: n/a | E43: n/a | F43: =LN(1+F42) -> -0.28211599 | G43: =LN(1+G42) -> 0.35382898 | H43: =LN(1+H42) -> 0.13677322 | I43: =LN(1+I42) -> -0.072223569 | J43: =LN(1+J42) -> 1.2085739 | K43: =LN(1+K42) -> -0.5126752 | L43: =LN(1+L42) -> -0.068207107 | M43: =LN(1+M42) -> 0.24507143
B45: WACC 2024 | C45: 0.151
B47: n/a -> não aplicável

Sheet ESTRUTURA DE CAPITAL
B1: STATEMENTS (mi) | D1: 2017 | E1: 2018 | F1: 2019 | G1: 2020 | H1: 2021 | I1: 2022 | J1: 2023 | K1: 2024 | L1: 3º tri. 2025 (mi.) | O1: 3º tri. (Milhares) | P1: 3º tri.
D2: 12/31/2017 | E2: 12/31/2018 | F2: 12/31/2019 | G2: 12/31/2020 | H2: 12/31/2021 | I2: 12/31/2022 | J2: 12/31/2023 | K2: 12/31/2024 | L2: 09/30/2025 | O2: 09/30/2025 | P2: 09/30/2025
B4: BALANÇO PATRIMONIAL
B6: Dívida Financeira CP | D6: ='Bal patrim - Padronizado'!E43 -> 0.733 | E6: ='Bal patrim - Padronizado'!F43 -> 0.731 | F6: ='Bal patrim - Padronizado'!G43 -> 0.511 | G6: ='Bal patrim - Padronizado'!H43 -> 0.203 | H6: ='Bal patrim - Padronizado'!I43 -> 0.202 | I6: ='Bal patrim - Padronizado'!J43 -> 0.202 | J6: ='Bal patrim - Padronizado'!K43 -> 0.134 | K6: ='Bal patrim - Padronizado'!L43 -> 0.088 | L6: =O6/1000 -> 1.049 | O6: 1049 | P6: =TRIM('Bal patrim B3 - 3º TRI 2025'!C24) -> 1.049
B7: Dívida Financeira LP | D7: ='Bal patrim - Padronizado'!E52 -> 1.972 | E7: ='Bal patrim - Padronizado'!F52 -> 1.245 | F7: ='Bal patrim - Padronizado'!G52 -> 0.737 | G7: ='Bal patrim - Padronizado'!H52 -> 0.536 | H7: ='Bal patrim - Padronizado'!I52 -> 0.335 | I7: ='Bal patrim - Padronizado'!J52 -> 0.134 | J7: ='Bal patrim - Padronizado'!K52 -> 0 | K7: ='Bal patrim - Padronizado'!L52 -> 30.706 | L7: =O7/1000 -> 26.373 | O7: 26373 | P7: =TRIM('Bal patrim B3 - 3º TRI 2025'!C58) -> 26.373
A8: (=) | B8: Dívida Bruta Total | D8: =SUM(D6:D7) -> 2.705 | E8: =SUM(E6:E7) -> 1.976 | F8: =SUM(F6:F7) -> 1.248 | G8: =SUM(G6:G7) -> 0.739 | H8: =SUM(H6:H7) -> 0.537 | I8: =SUM(I6:I7) -> 0.336 | J8: =SUM(J6:J7) -> 0.134 | K8: =SUM(K6:K7) -> 30.794 | L8: =SUM(L6:L7) -> 27.422 | O8: =SUM(O6:O7) -> 27422 | P8: =SUM(P6:P7) -> 0
B9: Capitalização de mercado | D9: 313.5325 | E9: 350.1218 | F9: 698.9818 | G9: 622.0181 | H9: 559.564 | I9: 584.798 | J9: 541.9002 | K9: 451.0578 | L9: 455.47153
B10: Peso da Dívida (Wd) | D10: =D8/(D8+D9) -> 0.0085536978 | E10: =E8/(E8+E9) -> 0.0056120771 | F10: =F8/(F8+F9) -> 0.001782272 | G10: =G8/(G8+G9) -> 0.0011866585 | H10: =H8/(H8+H9) -> 0.00095875565 | I10: =I8/(I8+I9) -> 0.00057422744 | J10: =J8/(J8+J9) -> 0.00024721687 | K10: =K8/(K8+K9) -> 0.063907616 | L10: =L8/(L8+L9) -> 0.056786844
B11: Peso do Capital Próprio (Wpl) | D11: =D9/(D8+D9) -> 0.9914463 | E11: =E9/(E8+E9) -> 0.99438792 | F11: =F9/(F8+F9) -> 0.99821773 | G11: =G9/(G8+G9) -> 0.99881334 | H11: =H9/(H8+H9) -> 0.99904124 | I11: =I9/(I8+I9) -> 0.99942577 | J11: =J9/(J8+J9) -> 0.99975278 | K11: =K9/(K8+K9) -> 0.93609238 | L11: =L9/(L8+L9) -> 0.94321316
B13: DRE
B15: "Despesa com juros" | D15: =('DRE - Ajustado 3º TRI 2025'!D23) -> 0.157 | E15: =('DRE - Ajustado 3º TRI 2025'!E23) -> 0.121 | F15: =('DRE - Ajustado 3º TRI 2025'!F23) -> 0.086 | G15: =('DRE - Ajustado 3º TRI 2025'!G23) -> 0.053 | H15: =('DRE - Ajustado 3º TRI 2025'!H23) -> 0.037 | I15: =('DRE - Ajustado 3º TRI 2025'!I23) -> 0.025 | J15: =('DRE - Ajustado 3º TRI 2025'!J23) -> 0.014 | K15: =('DRE - Ajustado 3º TRI 2025'!K23) -> 0.105 | L15: =('DRE - Ajustado 3º TRI 2025'!L23) -> 1.313
B16: Despesa de Juros acumulada | D16: =D15 -> 0.157 | E16: =E15 -> 0.121 | F16: =F15 -> 0.086 | G16: =G15 -> 0.053 | H16: =H15 -> 0.037 | I16: =I15 -> 0.025 | J16: =J15 -> 0.014 | K16: =K15 -> 0.105 | L16: =L15 -> 1.313
B17: Despesa de Juros da dívida | D17: =D16/D8 -> 0.058040665 | E17: =E16/E8 -> 0.061234818 | F17: =F16/F8 -> 0.068910256 | G17: =G16/G8 -> 0.071718539 | H17: =H16/H8 -> 0.068901304 | I17: =I16/I8 -> 0.074404762 | J17: =J16/J8 -> 0.10447761 | K17: =K16/K8 -> 0.0034097551 | L17: =L16/L8 -> 0.047881263
B20: Custo de Cap. Próprio (Kpl) Brasil | C20: =C26+(C27*(C28-C26)) -> 0.15149278
B21: Modelo CAPM
B23: 𝐾𝑒 = 𝑅𝑓 + β ∗ (𝑅𝑚 − 𝑅𝑓)
B25: Dados do dia 30/10/2025
B26: RF -> Taxa livre de risco - SELIC | C26: 0.151633
B27: β -> Beta ajustado da AFLT3 | C27: 0.077
B28: RM -> Retorno esperado do merc. | C28: 0.149812
B30: Alíquota IR (sob o LAIR) | D30: =DADOS!F27 -> 0.16240632 | E30: =DADOS!G27 -> 0.069491874 | F30: =DADOS!H27 -> 0.076661549 | G30: =DADOS!I27 -> 0.084462931 | H30: =DADOS!J27 -> 0.041818671 | I30: =DADOS!K27 -> 0.088876467 | J30: =DADOS!L27 -> 0.098042911 | K30: =DADOS!M27 -> 0.23857152 | L30: ='DRE - Ajustado 3º TRI 2025'!L31/'DRE - Ajustado 3º TRI 2025'!L30 -> 0.29344521
B31: WACC | K31: 0.151 | L31: =(L11*C20)+(L10*(L17*(1-L30))) -> 0.14481113
B32: 𝑊𝐴𝐶𝐶=𝑤_𝑃𝐿 (𝑘_𝑃𝐿 )+𝑤_𝐷 [𝑘_𝐷 (1−𝑖𝑟)]

Sheet Aval. Fluxo de Caixa Descontado
A1: VALORES EM MILHÕES (mi.) | C1: 2019 | D1: 2020 | E1: 2021 | F1: 2022 | G1: 2023 | H1: 2024 | I1: 2025 | J1: =I1+1 -> 2026 | K1: =J1+1 -> 2027 | L1: =K1+1 -> 2028 | M1: =L1+1 -> 2029 | N1: =M1+1 -> 2030 | O1: =N1+1 -> 2031 | P1: =O1+1 -> 2032 | Q1: =P1+1 -> 2033 | R1: =Q1+1 -> 2034
B3: RECEITA | C3: ='DRE - Ajustado 3º TRI 2025'!F6 -> 38.621 | D3: ='DRE - Ajustado 3º TRI 2025'!G6 -> 35.93 | E3: ='DRE - Ajustado 3º TRI 2025'!H6 -> 120.319 | F3: ='DRE - Ajustado 3º TRI 2025'!I6 -> 72.058 | G3: ='DRE - Ajustado 3º TRI 2025'!J6 -> 67.307 | H3: ='DRE - Ajustado 3º TRI 2025'!K6 -> 85.999 | I3: ='Projeção DRE'!K3 -> 81.447 | J3: ='Projeção DRE'!L3 -> 86.813486 | K3: ='Projeção DRE'!M3 -> 92.03559 | L3: ='Projeção DRE'!N3 -> 97.043889 | M3: ='Projeção DRE'!O3 -> 101.76806 | N3: ='Projeção DRE'!P3 -> 106.13846 | O3: ='Projeção DRE'!Q3 -> 110.08771 | P3: ='Projeção DRE'!R3 -> 113.55243 | ... R3: ='Projeção DRE'!T3 -> 118.80433
B4: EBIT(LAJIR) | C4: ='Projeção DRE'!E13 -> 24.961 | D4: ='Projeção DRE'!F13 -> 19.171 | E4: ='Projeção DRE'!G13 -> 103.23 | F4: ='Projeção DRE'!H13 -> 38.323 | G4: ='Projeção DRE'!I13 -> 30.123 | H4: ='Projeção DRE'!J13 -> 43.628 | I4: ='Projeção DRE'!K13 -> 38.793514 | J4: ='Projeção DRE'!L13 -> 40.082095 | ... R4: ='Projeção DRE'!T13 -> 39.526854
B5: IR + CSLL (sob o LAIR) | I5: ='Projeção DRE'!K20 -> 9.6824168 | J5: ='Projeção DRE'!L20 -> 8.4566592 | K5: ='Projeção DRE'!M20 -> 7.4555791 | L5: ='Projeção DRE'!N20 -> 6.6379938 | M5: ='Projeção DRE'!O20 -> 5.9702692 | N5: ='Projeção DRE'!P20 -> 5.4249365 | O5: ='Projeção DRE'!Q20 -> 4.9795616 | P5: ='Projeção DRE'!R20 -> 4.6158225 | ... R5: ='Projeção DRE'!T20 -> 4.0761401
B6: Alíquota IR + CSLL (sob o LAIR) | I6: ='Projeção DRE'!K20/'Projeção DRE'!K19 -> 0.1542555 | J6: ='Projeção DRE'!L20/'Projeção DRE'!L19 -> 0.13896139 | K6: ='Projeção DRE'!M20/'Projeção DRE'!M19 -> 0.12760117 | L6: ='Projeção DRE'!N20/'Projeção DRE'!N19 -> 0.11759072 | M6: ='Projeção DRE'!O20/'Projeção DRE'!O19 -> 0.10909681 | N6: ='Projeção DRE'!P20/'Projeção DRE'!P19 -> 0.10221818 | O6: ='Projeção DRE'!Q20/'Projeção DRE'!Q19 -> 0.096964679 | P6: ='Projeção DRE'!R20/'Projeção DRE'!R19 -> 0.093351637 | ... R6: ='Projeção DRE'!T20/'Projeção DRE'!T19 -> 0.091240859
B7: WACC | H7: 0.151 | I7: ='ESTRUTURA DE CAPITAL'!L31 -> 0.14481113 | J7: =I7 -> 0.14481113 | K7: =J7 -> 0.14481113 | L7: =K7 -> 0.14481113 | M7: =L7 -> 0.14481113 | N7: =M7 -> 0.14481113 | O7: =N7 -> 0.14481113 | P7: =O7 -> 0.14481113 | Q7: =P7 -> 0.14481113 | R7: =Q7 -> 0.14481113
B8: ROIC | C8: =DADOS!H34 -> 0.13317376 | D8: =DADOS!I34 -> 0.10309162 | E8: =DADOS!J34 -> 0.58248225 | F8: =DADOS!K34 -> 0.1407143 | G8: =DADOS!L34 -> 0.10489161 | H8: =DADOS!M34 -> 0.12291538 | I8: =I14/H12 -> 0.10332661 | J8: =J14/I12 -> 0.10868933 | K8: =K14/J12 -> 0.11326599 | L8: =L14/K12 -> 0.11717198 | M8: =M14/L12 -> 0.12014197 | N8: =N14/M12 -> 0.12189803 | O8: =O14/N12 -> 0.12224451 | P8: =P14/O12 -> 0.12098799 | ... R8: =R14/Q12 -> 0.11312404
B9: b | C9: =DADOS!H36 -> -0.12187899 | D9: =DADOS!I36 -> -0.025125684 | E9: =DADOS!J36 -> 0.79188735 | F9: =DADOS!K36 -> 0.31173938 | G9: =DADOS!L36 -> 0.41362324 | H9: =DADOS!M36 -> 1.4228647 | I9: 0 | J9: 0 | K9: 0 | L9: 0 | M9: 0 | N9: 0 | O9: 0 | P9: 0 | Q9: 0 | R9: 0 | XFA9: \
B10: g | C10: =C8*C9 -> -0.016231083 | D10: =D8*D9 -> -0.0025902475 | E10: =E8*E9 -> 0.46126033 | F10: =F8*F9 -> 0.043866189 | G10: =G8*G9 -> 0.043385606 | H10: =H8*H9 -> 0.17489196 | I10: =I8*I9 -> 0 | J10: =J8*J9 -> 0 | ... R10: =R8*R9 -> 0
B12: Capital Investido | C12: =DADOS!H19 -> 170.254 | D12: =DADOS!I19 -> 169.813 | E12: =DADOS!J19 -> 248.141 | F12: =DADOS!K19 -> 259.026 | G12: =DADOS!L19 -> 270.264 | H12: =DADOS!M19 -> 317.531 | I12: =H12-I16 -> 317.531 | J12: =I12-J16 -> 317.531 | K12: =J12-K16 -> 317.531 | L12: =K12-L16 -> 317.531 | M12: =L12-M16 -> 317.531 | N12: =M12-N16 -> 317.531 | O12: =N12-O16 -> 317.531 | P12: =O12-P16 -> 317.531 | ... R12: =Q12-R16 -> 317.531
A14: (+) | B14: NOPAT [(LAJIR *(1 - IR)] | C14: =DADOS!H28 -> 23.047451 | D14: =DADOS!I28 -> 17.551761 | E14: =DADOS!J28 -> 98.913059 | F14: =DADOS!K28 -> 34.916987 | G14: =DADOS!L28 -> 27.169653 | H14: =DADOS!M28 -> 33.219602 | I14: =I4*(1-I6) -> 32.809401 | J14: =J4*(1-J6) -> 34.512232 | K14: =K4*(1-K6) -> 35.965463 | L14: =L4*(1-L6) -> 37.205737 | M14: =M4*(1-M6) -> 38.148801 | N14: =N4*(1-N6) -> 38.706403 | O14: =O4*(1-O6) -> 38.81642 | P14: =P4*(1-P6) -> 38.417439 | ... R14: =R4*(1-R6) -> 35.92039
A15: (+) | B15: NOPAT (CAP. INV. * ROIC) | C15: =DADOS!H28 -> 23.047451 | D15: =DADOS!I28 -> 17.551761 | E15: =DADOS!J28 -> 98.913059 | F15: =DADOS!K28 -> 34.916987 | G15: =DADOS!L28 -> 27.169653 | H15: =DADOS!M28 -> 33.219602 | I15: =I8*H12 -> 32.809401 | J15: =J8*I12 -> 34.512232 | K15: =K8*J12 -> 35.965463 | L15: =L8*K12 -> 37.205737 | M15: =M8*L12 -> 38.148801 | N15: =N8*M12 -> 38.706403 | O15: =O8*N12 -> 38.81642 | P15: =P8*O12 -> 38.417439 | ... R15: =R8*Q12 -> 35.92039
A16: (-) | B16: Invest.Líquido | C16: =DADOS!H21 -> 2.809 | D16: =DADOS!I21 -> 0.441 | E16: =DADOS!J21 -> -78.328 | F16: =DADOS!K21 -> -10.885 | G16: =DADOS!L21 -> -11.238 | H16: =DADOS!M21 -> -47.267 | I16: =-(I15*I9) -> 0 | J16: =-(J15*J9) -> 0 | K16: =-(K15*K9) -> 0 | L16: =-(L15*L9) -> 0 | M16: =-(M15*M9) -> 0 | N16: =-(N15*N9) -> 0 | O16: =-(O15*O9) -> 0 | P16: =-(P15*P9) -> 0 | ... R16: =-(R15*R9) -> 0
A17: (=) | B17: Fluxo de Caixa Livre (FCLE) | C17: =SUM(C15:C16) -> 25.856451 | D17: =SUM(D15:D16) -> 17.992761 | E17: =SUM(E15:E16) -> 20.585059 | F17: =SUM(F15:F16) -> 24.031987 | G17: =SUM(G15:G16) -> 15.931653 | H17: =SUM(H15:H16) -> -14.047398 | I17: =SUM(I15:I16) -> 32.809401 | J17: =SUM(J15:J16) -> 34.512232 | ... R17: =SUM(R15:R16) -> 35.92039
A19: Valor da Empresa (histórico) | C19: =#REF! -> #REF! | D19: 591.5481 | E19: 542.482 | F19: 563.803 | G19: 539.0982 | H19: 474.5308
R20: Perpetuidade:
A21: Valor Residual | R21: =R17*(1+R10)/(R7-R10) -> 248.04993
A22: Fluxo Caixa | E22: =E17+E21 -> 20.585059 | F22: =F17+F21 -> 24.031987 | G22: =G17+G21 -> 15.931653 | H22: =H17+H21 -> -14.047398 | I22: =I17+I21 -> 32.809401 | J22: =J17+J21 -> 34.512232 | K22: =K17+K21 -> 35.965463 | L22: =L17+L21 -> 37.205737 | ... R22: =R17+R21 -> 283.97032
A24: Fator de Desconto (Taxa "r") | H24: 1 | I24: =(1+I7)^(-(I1-$H$1)) -> 0.87350653 | J24: =(1+J7)^(-(J1-$H$1)) -> 0.76301367 | K24: =(1+K7)^(-(K1-$H$1)) -> 0.66649742 | L24: =(1+L7)^(-(L1-$H$1)) -> 0.58218985 | M24: =(1+M7)^(-(M1-$H$1)) -> 0.50854664 | N24: =(1+N7)^(-(N1-$H$1)) -> 0.44421882 | O24: =(1+O7)^(-(O1-$H$1)) -> 0.38802804 | P24: =(1+P7)^(-(P1-$H$1)) -> 0.33894503 | ... R24: =(1+R7)^(-(R1-$H$1)) -> 0.25861969
A26: Fluxos de Caixa à Valor Presente | H26: =SUMPRODUCT(I22:$R22,I24:$R24)/H24 -> 249.83571 | I26: =SUMPRODUCT(J22:$R22,J24:$R24)/I24 -> 253.2053 | J26: =SUMPRODUCT(K22:$R22,K24:$R24)/J24 -> 255.36001 | K26: =SUMPRODUCT(L22:$R22,L24:$R24)/K24 -> 256.37352 | L26: =SUMPRODUCT(M22:$R22,M24:$R24)/L24 -> 256.29352 | M26: =SUMPRODUCT(N22:$R22,N24:$R24)/M24 -> 255.25887 | N26: =SUMPRODUCT(O22:$R22,O24:$R24)/N24 -> 253.51679 | O26: =SUMPRODUCT(P22:$R22,P24:$R24)/O24 -> 251.41242 | ... Q26: =SUMPRODUCT(R22:$R22,R24:$R24)/Q24 -> 248.04993 | R26: =R21 -> 248.04993
A27: Crescimento do Valor da Empresa | I27: =I26/H26-1 -> 0.01348722 | J27: =J26/I26-1 -> 0.0085097451 | K27: =K26/J26-1 -> 0.0039689379 | L27: =L26/K26-1 -> -0.00031204246 | M27: =M26/L26-1 -> -0.0040369634 | N27: =N26/M26-1 -> -0.0068247534 | O27: =O26/N26-1 -> -0.0083007048 | P27: =P26/O26-1 -> -0.0079953183 | ... R27: =R26/Q26-1 -> 0
A30: Lucro Econômico | I30: =H12*(I8-I7) -> -13.172621 | J30: =I12*(J8-J7) -> -11.46979 | K30: =J12*(K8-K7) -> -10.016559 | L30: =K12*(L8-L7) -> -8.7762846 | M30: =L12*(M8-M7) -> -7.8332213 | N30: =M12*(N8-N7) -> -7.2756184 | O30: =N12*(O8-O7) -> -7.1656016 | P30: =O12*(P8-P7) -> -7.5645832 | ... R30: =Q12*(R8-R7) -> -10.061632
A31: Valor Residual(LE) | R31: =R30*(1+R10)/(R7-R10) -> -69.481068
A33: VP(LE) | H33: =(SUMPRODUCT(I30:$R30,I24:$R24)+$R$31*$R$24)/H24 -> -67.695293 | I33: =(SUMPRODUCT(J30:$R30,J24:$R24)+$R$31*$R$24)/I24 -> -64.325703 | J33: =(SUMPRODUCT(K30:$R30,K24:$R24)+$R$31*$R$24)/J24 -> -62.170991 | K33: =(SUMPRODUCT(L30:$R30,L24:$R24)+$R$31*$R$24)/K24 -> -61.157483 | L33: =(SUMPRODUCT(M30:$R30,M24:$R24)+$R$31*$R$24)/L24 -> -61.237482 | M33: =(SUMPRODUCT(N30:$R30,N24:$R24)+$R$31*$R$24)/M24 -> -62.27213 | N33: =(SUMPRODUCT(O30:$R30,O24:$R24)+$R$31*$R$24)/N24 -> -64.014209 | O33: =(SUMPRODUCT(P30:$R30,P24:$R24)+$R$31*$R$24)/O24 -> -66.118577 | ... Q33: =(SUMPRODUCT(R30:$R30,R24:$R24)+$R$31*$R$24)/Q24 -> -69.481068 | R33: =(SUMPRODUCT($R30:$R30,$R24:$R24)+$R$31*$R$24)/R24 -> -79.5427
A34: Capital Investido | H34: =H12 -> 317.531 | I34: =I12 -> 317.531 | J34: =J12 -> 317.531 | K34: =K12 -> 317.531 | L34: =L12 -> 317.531 | M34: =M12 -> 317.531 | N34: =N12 -> 317.531 | O34: =O12 -> 317.531 | ... R34: =R12 -> 317.531
A35: Valor Econômico da Empresa Projetado | H35: =SUM(H33:H34) -> 249.83571 | I35: =SUM(I33:I34) -> 253.2053 | J35: =SUM(J33:J34) -> 255.36001 | K35: =SUM(K33:K34) -> 256.37352 | L35: =SUM(L33:L34) -> 256.29352 | M35: =SUM(M33:M34) -> 255.25887 | N35: =SUM(N33:N34) -> 253.51679 | O35: =SUM(O33:O34) -> 251.41242 | ... R35: =SUM(R33:R34) -> 237.9883
A37: Valor Total da Empresa Projetado | H37: =I35*(10^6) -> 2.532053e+08
A38: Dívida Total da Empresa | H38: =SUM(DADOS!M16:M17)*(10^6) -> 64619000
A39: PL / Market Captalization | H39: =H37-H38 -> 1.885863e+08
A40: QTD de ações ordinárias da empresa | H40: 63084700
A41: Valor por ação | H41: =H39/H40 -> 2.9894142

Sheet Aval. Valor Patrimonial da Ação
B1: Baseado no Valor Patrimonial por Ação da Afluente T em 30 de setembro de 2025
B3: CÁLCULO DO VALOR PATRIMONIAL
B4: Patrimônio Líquido Total | C4: 255393000
B5: QTD de ações ordinárias | C5: ='Aval. Fluxo de Caixa Descontado'!H40 -> 63084700
B6: Valor patrimonial por ação | C6: =C4/C5 -> 4.0484143
B9: CÁLCULO DO PREÇO POR VALOR PATRIMONIAL (P/VPA)
B10: Preço da ação no dia 30/10/2025 | C10: 7.22
B11: Valor patrimonial por ação | C11: =C4/C5 -> 4.0484143
B12: Preço/Valor Patrimonial | C12: =C10/C11 -> 1.7834143
B14: *O mercado estava pagando 1,78x o valor patrimonial da ação no dia 30/10/2025, apresentando assim uma boa expectativa em relação ao título.

Sheet Aval. VWAP
O1: Price Buckets | P1: Trades | Q1: Volume | R1: Bid | S1: Mid | T1: Ask | V1: PERÍODO
O2: 7.98 | P2: 4 | Q2: 700 | R2: 0 | S2: 0 | T2: 700 | V2: 04/11/24 até 30/10/25
B3: CÁLCULO DO PREÇO MÉDIO POR VOLUME NEGOCIADO (VWAP) | O3: 7.8 | P3: 36 | Q3: 3600 | R3: 0 | S3: 0 | T3: 3600
B4: Período: 04/11/24 até 30/10/25 | O4: 7.79 | P4: 5 | Q4: 800 | R4: 200 | S4: 100 | T4: 500
B5: Preço médio por volume negoc. | C5: =(SUMPRODUCT(O2:O95,Q2:Q95))/Q96 -> 7.2103614 | O5: 7.77 | P5: 2 | Q5: 200 | R5: 0 | S5: 0 | T5: 200
O6: 7.75 | P6: 5 | Q6: 700 | R6: 200 | S6: 400 | T6: 100
O7: 7.74 | P7: 2 | Q7: 100 | R7: 0 | S7: 0 | T7: 100
O8: 7.73 | P8: 2 | Q8: 100 | R8: 0 | S8: 0 | T8: 100
O9: 7.7 | P9: 1 | Q9: 100 | R9: 0 | S9: 0 | T9: 100
O10: 7.69 | P10: 3 | Q10: 200 | R10: 0 | S10: 100 | T10: 100
O11: 7.68 | P11: 3 | Q11: 400 | R11: 100 | S11: 200 | T11: 100
O12: 7.67 | P12: 3 | Q12: 300 | R12: 0 | S12: 0 | T12: 300
O13: 7.66 | P13: 3 | Q13: 300 | R13: 0 | S13: 100 | T13: 200
O14: 7.65 | P14: 1 | Q14: 100 | R14: 0 | S14: 0 | T14: 100
O15: 7.63 | P15: 3 | Q15: 400 | R15: 0 | S15: 400 | T15: 0
O16: 7.6 | P16: 5 | Q16: 600 | R16: 0 | S16: 100 | T16: 500
O17: 7.59 | P17: 6 | Q17: 900 | R17: 0 | S17: 0 | T17: 900
... O95: 6.53 | P95: 4 | Q95: 200 | R95: 200 | S95: 0 | T95: 0
O96: Totals | P96: 480 | Q96: 66400 | R96: 28300 | S96: 15000 | T96: 23100

Sheet Projeção DRE
A1: Em Milhões de BRL exceto Por ação
A2: Ano | B2: 2016 | C2: 2017 | D2: 2018 | E2: 2019 | F2: 2020 | G2: 2021 | H2: 2022 | I2: 2023 | J2: 2024 | K2: 2025 | L2: 2026 | M2: 2027 | N2: 2028 | O2: 2029 | P2: 2030 | Q2: 2031 | R2: 2032 | S2: 2033 | T2: 2034
A3: Receita | B3: 31.353 | C3: 23.646 | D3: 33.684 | E3: 38.621 | F3: 35.93 | G3: 120.319 | H3: 72.058 | I3: 67.307 | J3: 85.999 | K3: ='Proj. Receita e MG Operacional'!H55 -> 81.447 | L3: ='Proj. Receita e MG Operacional'!I55 -> 86.813486 | M3: ='Proj. Receita e MG Operacional'!J55 -> 92.03559 | N3: ='Proj. Receita e MG Operacional'!K55 -> 97.043889 | O3: ='Proj. Receita e MG Operacional'!L55 -> 101.76806 | P3: ='Proj. Receita e MG Operacional'!M55 -> 106.13846 | Q3: ='Proj. Receita e MG Operacional'!N55 -> 110.08771 | R3: ='Proj. Receita e MG Operacional'!O55 -> 113.55243 | ... T3: ='Proj. Receita e MG Operacional'!Q55 -> 118.80433
A4: Custo de bens e serviços | B4: 14.175 | C4: 10.425 | D4: 10.028 | E4: 13.006 | F4: 12.631 | G4: 13.665 | H4: 27.45 | I4: 32.273 | J4: 38.034 | K4: ='Proj. Custos da receita'!B25 -> 35.449917 | L4: ='Proj. Custos da receita'!C25 -> 38.724633 | M4: ='Proj. Custos da receita'!D25 -> 41.99935 | N4: ='Proj. Custos da receita'!E25 -> 45.274067 | O4: ='Proj. Custos da receita'!F25 -> 48.548783 | P4: ='Proj. Custos da receita'!G25 -> 51.8235 | Q4: ='Proj. Custos da receita'!H25 -> 55.098217 | R4: ='Proj. Custos da receita'!I25 -> 58.372933 | ... T4: ='Proj. Custos da receita'!K25 -> 64.922367
A5: Depreciação e amortização: | B5: 0 | C5: 0 | D5: 0 | E5: 0 | F5: 0 | G5: 0 | H5: 0.06 | I5: 0.045 | J5: 0.057 | K5: ='Proj. Custos da receita'!B26 -> 0.057954961 | L5: ='Proj. Custos da receita'!C26 -> 0.065945953 | M5: ='Proj. Custos da receita'!D26 -> 0.073936945 | N5: ='Proj. Custos da receita'!E26 -> 0.081927937 | O5: ='Proj. Custos da receita'!F26 -> 0.089918929 | P5: ='Proj. Custos da receita'!G26 -> 0.097909922 | Q5: ='Proj. Custos da receita'!H26 -> 0.10590091 | R5: ='Proj. Custos da receita'!I26 -> 0.11389191 | ... T5: ='Proj. Custos da receita'!K26 -> 0.12987389
A6: Lucro bruto | B6: 17.178 | C6: 13.221 | D6: 23.656 | E6: 25.615 | F6: 23.299 | G6: 106.654 | H6: 44.548 | I6: 34.989 | J6: =J3-SUM(J4:J5) -> 47.908 | K6: =K3-SUM(K4:K5) -> 45.939128 | L6: =L3-SUM(L4:L5) -> 48.022907 | M6: =M3-SUM(M4:M5) -> 49.962303 | N6: =N3-SUM(N4:N5) -> 51.687894 | O6: =O3-SUM(O4:O5) -> 53.129362 | P6: =P3-SUM(P4:P5) -> 54.217049 | Q6: =Q3-SUM(Q4:Q5) -> 54.883593 | ... T6: =T3-SUM(T4:T5) -> 53.752086
A7: Outros lucros operacionais | B7: 0 | C7: 0 | D7: 0 | E7: 0 | F7: 0 | G7: 0.005 | H7: 0 | I7: 0 | J7: 0.109 | K7: =AVERAGE(B7:J7) -> 0.012666667 | L7: =AVERAGE(C7:K7) -> 0.014074074 | M7: =AVERAGE(D7:L7) -> 0.01563786 | N7: =AVERAGE(E7:M7) -> 0.0173754 | O7: =AVERAGE(F7:N7) -> 0.019306 | P7: =AVERAGE(G7:O7) -> 0.021451111 | Q7: =AVERAGE(H7:P7) -> 0.023279012 | R7: =AVERAGE(I7:Q7) -> 0.025865569 | ... T7: =AVERAGE(K7:S7) -> 0.019821691
A8: Despesas operacionais | B8: 0.779 | C8: 0.555 | D8: 0.753 | E8: 0.654 | F8: 4.128 | G8: 3.429 | H8: 6.225 | I8: 4.866 | J8: =SUM(J9:J12) -> 4.993 | K8: =SUM(K9:K12) -> 7.1582811 | L8: =SUM(L9:L12) -> 7.9548855 | M8: =SUM(M9:M12) -> 8.7520001 | N8: =SUM(N9:N12) -> 9.5414595 | O8: =SUM(O9:O12) -> 10.328302 | P8: =SUM(P9:P12) -> 11.125126 | Q8: =SUM(Q9:Q12) -> 11.922484 | ... T8: =SUM(T9:T12) -> 14.245054
A9: Venda e marketing | B9: 0 | C9: 0 | D9: 0.074 | E9: 0.095 | F9: 0 | G9: 0 | H9: 0.018 | I9: 0.185 | J9: 0 | K9: ='Proj. Despesas Operacionais'!B23 -> 0.041333333 | L9: ='Proj. Despesas Operacionais'!C23 -> 0.045925926 | M9: ='Proj. Despesas Operacionais'!D23 -> 0.051028807 | N9: ='Proj. Despesas Operacionais'!E23 -> 0.048476452 | O9: ='Proj. Despesas Operacionais'!F23 -> 0.043307169 | P9: ='Proj. Despesas Operacionais'!G23 -> 0.048119076 | Q9: ='Proj. Despesas Operacionais'!H23 -> 0.05346564 | R9: ='Proj. Despesas Operacionais'!I23 -> 0.057406267 | S9: ='Proj. Despesas Operacionais'!J23 -> 0.043229186 | T9: ='Proj. Despesas Operacionais'!K24 -> 12.625078
A10: Geral e administrativas | B10: 0 | C10: 0.555 | D10: 0.679 | E10: 0.559 | F10: 4.202 | G10: 3.365 | H10: 6.094 | I10: 4.528 | J10: 4.253 | K10: ='Proj. Despesas Operacionais'!B24 -> 6.2400278 | L10: ='Proj. Despesas Operacionais'!C24 -> 6.9494778 | M10: ='Proj. Despesas Operacionais'!D24 -> 7.6589278 | N10: ='Proj. Despesas Operacionais'!E24 -> 8.3683778 | O10: ='Proj. Despesas Operacionais'!F24 -> 9.0778278 | P10: ='Proj. Despesas Operacionais'!G24 -> 9.7872778 | Q10: ='Proj. Despesas Operacionais'!H24 -> 10.496728 | R10: ='Proj. Despesas Operacionais'!I24 -> 11.206178 | S10: ='Proj. Despesas Operacionais'!J24 -> 11.915628 | T10: ='Proj. Despesas Operacionais'!K25 -> 1.3011
A11: Pesquisa e desenvolvimento (Outras desp operacionais) | B11: 0 | C11: 0.334 | D11: 0.355 | E11: 0.393 | F11: 0.38 | G11: 0.449 | H11: 0.539 | I11: 0.657 | J11: 0.604 | K11: ='Proj. Despesas Operacionais'!B25 -> 0.72975 | L11: ='Proj. Despesas Operacionais'!C25 -> 0.79323333 | M11: ='Proj. Despesas Operacionais'!D25 -> 0.85671667 | N11: ='Proj. Despesas Operacionais'!E25 -> 0.9202 | O11: ='Proj. Despesas Operacionais'!F25 -> 0.98368333 | P11: ='Proj. Despesas Operacionais'!G25 -> 1.0471667 | Q11: ='Proj. Despesas Operacionais'!H25 -> 1.11065 | R11: ='Proj. Despesas Operacionais'!I25 -> 1.1741333 | S11: ='Proj. Despesas Operacionais'!J25 -> 1.2376167 | T11: ='Proj. Despesas Operacionais'!K26 -> 0.31887595
A12: Depreciação e amortização | B12: 0 | C12: 0 | D12: 0 | E12: 0 | F12: 0 | G12: 0.064 | H12: 0.113 | I12: 0.153 | J12: 0.136 | K12: ='Proj. Despesas Operacionais'!B26 -> 0.14716998 | L12: ='Proj. Despesas Operacionais'!C26 -> 0.16624842 | M12: ='Proj. Despesas Operacionais'!D26 -> 0.18532686 | N12: ='Proj. Despesas Operacionais'!E26 -> 0.2044053 | O12: ='Proj. Despesas Operacionais'!F26 -> 0.22348375 | P12: ='Proj. Despesas Operacionais'!G26 -> 0.24256219 | Q12: ='Proj. Despesas Operacionais'!H26 -> 0.26164063 | R12: ='Proj. Despesas Operacionais'!I26 -> 0.28071907 | S12: ='Proj. Despesas Operacionais'!J26 -> 0.29979751 | T12: ='Proj. Despesas Operacionais'!K27 -> 0
A13: Lucro (Prejuízo) operacional (EBIT/LAJIR) | B13: 16.399 | C13: 12.666 | D13: 22.903 | E13: 24.961 | F13: 19.171 | G13: 103.23 | H13: 38.323 | I13: 30.123 | J13: 43.628 | K13: =K6+K7-K8 -> 38.793514 | L13: =L6+L7-L8 -> 40.082095 | M13: =M6+M7-M8 -> 41.225941 | N13: =N6+N7-N8 -> 42.16381 | O13: =O6+O7-O8 -> 42.820366 | P13: =P6+P7-P8 -> 43.113374 | Q13: =Q6+Q7-Q8 -> 42.984388 | R13: =R6+R7-R8 -> 42.37303 | ... T13: =T6+T7-T8 -> 39.526854
A14: Perdas (lucros) não operacionais | B14: =B17+(SUM(B16,B18)) -> -5.26 | C14: =C17+(SUM(C16,C18)) -> -2.278 | D14: =D17+(SUM(D16,D18)) -> -1.402 | E14: =E17+(SUM(E16,E18)) -> -2.393 | F14: =F17+(SUM(F16,F18)) -> -1.264 | G14: =G17+(SUM(G16,G18)) -> -0.934 | H14: =H17+(SUM(H16,H18)) -> -2.824 | I14: =I17+(SUM(I16,I18)) -> -1.71 | ... T14: =T17+(SUM(T16,T18)) -> -5.1499341
A15: Despesa de juros, líq | B15: -5.26 | C15: -2.429 | D15: -1.491 | E15: -2.349 | F15: -1.403 | G15: -0.938 | H15: -2.908 | I15: -1.434 | J15: -1.64 | K15: ='Proj. Despesa não operacional'!B57 -> -23.979668 | L15: ='Proj. Despesa não operacional'!C57 -> -20.778716 | M15: ='Proj. Despesa não operacional'!D57 -> -17.207592 | N15: ='Proj. Despesa não operacional'!E57 -> -14.291044 | O15: ='Proj. Despesa não operacional'!F57 -> -11.90909 | P15: ='Proj. Despesa não operacional'!G57 -> -9.9637409 | Q15: ='Proj. Despesa não operacional'!H57 -> -8.3749679 | R15: ='Proj. Despesa não operacional'!I57 -> -7.0774119 | ... T15: ='Proj. Despesa não operacional'!K57 -> -5.1522188
A16: Despesa com juros | B16: 0.192 | C16: 0.157 | D16: 0.121 | E16: 0.086 | F16: 0.053 | G16: 0.037 | H16: 0.025 | I16: 0.014 | J16: 0.105 | K16: ='Proj. Despesa não operacional'!B58 -> 1.3984489 | L16: ='Proj. Despesa não operacional'!C58 -> 1.2057688 | M16: ='Proj. Despesa não operacional'!D58 -> 0.99080637 | N16: ='Proj. Despesa não operacional'!E58 -> 0.81524585 | O16: ='Proj. Despesa não operacional'!F58 -> 0.67186502 | P16: ='Proj. Despesa não operacional'!G58 -> 0.55476545 | Q16: ='Proj. Despesa não operacional'!H58 -> 0.45912986 | R16: ='Proj. Despesa não operacional'!I58 -> 0.38102396 | ... T16: ='Proj. Despesa não operacional'!K58 -> 0.26513769
A17: Lucro com juros | B17: =B15-B16 -> -5.452 | C17: =C15-C16 -> -2.586 | D17: =D15-D16 -> -1.612 | E17: =E15-E16 -> -2.435 | F17: =F15-F16 -> -1.456 | G17: =G15-G16 -> -0.975 | H17: =H15-H16 -> -2.933 | I17: =I15-I16 -> -1.448 | ... T17: =T15-T16 -> -5.4173565
A18: Outros Prejuízos (Lucros) não op | B18: 0 | C18: 0.151 | D18: 0.089 | E18: -0.044 | F18: 0.139 | G18: 0.004 | H18: 0.084 | I18: -0.276 | J18: -0.129 | K18: =K13*'Proj. Despesa não operacional'!B59 -> 0.0022423708 | L18: =L13*'Proj. Despesa não operacional'!C59 -> 0.0023168544 | M18: =M13*'Proj. Despesa não operacional'!D59 -> 0.0023829718 | N18: =N13*'Proj. Despesa não operacional'!E59 -> 0.0024371831 | O18: =O13*'Proj. Despesa não operacional'!F59 -> 0.0024751339 | P18: =P13*'Proj. Despesa não operacional'!G59 -> 0.0024920705 | Q18: =Q13*'Proj. Despesa não operacional'!H59 -> 0.0024846148 | R18: =R13*'Proj. Despesa não operacional'!I59 -> 0.0024492767 | ... T18: =T13*'Proj. Despesa não operacional'!K59 -> 0.0022847599
A19: Lucro (Prejuízo) antes de impostos (LAIR) | B19: 21.237 | C19: 14.944 | D19: 24.305 | E19: 27.354 | F19: 20.435 | G19: 104.164 | H19: 41.147 | I19: 31.833 | J19: =J13-J14-J18 -> 45.526 | K19: =K13-K14-K18 -> 62.768697 | L19: =L13-L14-L18 -> 60.856178 | M19: =M13-M14-M18 -> 58.428767 | N19: =N13-N14-N18 -> 56.44998 | O19: =O13-O14-O18 -> 54.724506 | P19: =P13-P14-P18 -> 53.072131 | Q19: =Q13-Q14-Q18 -> 51.354386 | ... T19: =T13-T14-T18 -> 44.674504
A20: Desp c/imposto renda (Benefício) | B20: 6.949 | C20: 2.427 | D20: 1.689 | E20: 2.097 | F20: 1.726 | G20: 4.356 | H20: 3.657 | I20: 3.121 | J20: 10.662 | K20: ='Proj. Imposto de Renda'!B28 -> 9.6824168 | L20: ='Proj. Imposto de Renda'!C28 -> 8.4566592 | M20: ='Proj. Imposto de Renda'!D28 -> 7.4555791 | N20: ='Proj. Imposto de Renda'!E28 -> 6.6379938 | O20: ='Proj. Imposto de Renda'!F28 -> 5.9702692 | P20: ='Proj. Imposto de Renda'!G28 -> 5.4249365 | Q20: ='Proj. Imposto de Renda'!H28 -> 4.9795616 | R20: ='Proj. Imposto de Renda'!I28 -> 4.6158225 | ... T20: ='Proj. Imposto de Renda'!K28 -> 4.0761401
A21: Lucro líquido, GAAP | B21: =B19-B20 -> 14.288 | C21: =C19-C20 -> 12.517 | D21: =D19-D20 -> 22.616 | E21: =E19-E20 -> 25.257 | F21: =F19-F20 -> 18.709 | G21: =G19-G20 -> 99.808 | H21: =H19-H20 -> 37.49 | I21: =I19-I20 -> 28.712 | ... T21: =T19-T20 -> 40.598363
A23: EBITDA/LAJIDA | B23: =B13+B12+B5 -> 16.399 | C23: =C13+C12+C5 -> 12.666 | D23: =D13+D12+D5 -> 22.903 | E23: =E13+E12+E5 -> 24.961 | F23: =F13+F12+F5 -> 19.171 | G23: =G13+G12+G5 -> 103.294 | H23: =H13+H12+H5 -> 38.496 | I23: =I13+I12+I5 -> 30.321 | ... T23: =T13+T12+T5 -> 39.656728
A24: Mg EBITDA/LAJIDA | B24: =B23/B3 -> 0.52304405 | C24: =C23/C3 -> 0.53565085 | D24: =D23/D3 -> 0.67993706 | E24: =E23/E3 -> 0.64630641 | F24: =F23/F3 -> 0.53356527 | G24: =G23/G3 -> 0.85850115 | H24: =H23/H3 -> 0.53423631 | I24: =I23/I3 -> 0.45048806 | ... T24: =T23/T3 -> 0.33379869
A25: EBIT/LAJIR | B25: =B13 -> 16.399 | C25: =C13 -> 12.666 | D25: =D13 -> 22.903 | E25: =E13 -> 24.961 | F25: =F13 -> 19.171 | G25: =G13 -> 103.23 | H25: =H13 -> 38.323 | I25: =I13 -> 30.123 | ... T25: =T13 -> 39.526854
A26: Mg EBIT/LAJIR | B26: =B25/B3 -> 0.52304405 | C26: =C25/C3 -> 0.53565085 | D26: =D25/D3 -> 0.67993706 | E26: =E25/E3 -> 0.64630641 | F26: =F25/F3 -> 0.53356527 | G26: =G25/G3 -> 0.85796923 | H26: =H25/H3 -> 0.53183547 | I26: =I25/I3 -> 0.44754632 | ... T26: =T25/T3 -> 0.33270551
A27: Margem bruta | B27: =B6/B3 -> 0.54789015 | C27: =C6/C3 -> 0.55912205 | D27: =D6/D3 -> 0.70229189 | E27: =E6/E3 -> 0.66324021 | F27: =F6/F3 -> 0.64845533 | G27: =G6/G3 -> 0.88642692 | H27: =H6/H3 -> 0.61822421 | I27: =I6/I3 -> 0.51984192 | ... T27: =T6/T3 -> 0.45244216
A28: Margem operacional | B28: =B13/B3 -> 0.52304405 | C28: =C13/C3 -> 0.53565085 | D28: =D13/D3 -> 0.67993706 | E28: =E13/E3 -> 0.64630641 | F28: =F13/F3 -> 0.53356527 | G28: =G13/G3 -> 0.85796923 | H28: =H13/H3 -> 0.53183547 | I28: =I13/I3 -> 0.44754632 | ... T28: =T13/T3 -> 0.33270551
A29: Margem de lucro líquido (sob a receita) | B29: =B21/B3 -> 0.45571397 | C29: =C21/C3 -> 0.52934957 | D29: =D21/D3 -> 0.6714167 | E29: =E21/E3 -> 0.65397064 | F29: =F21/F3 -> 0.52070693 | G29: =G21/G3 -> 0.82952817 | H29: =H21/H3 -> 0.52027533 | I29: =I21/I3 -> 0.42658267 | ... T29: =T21/T3 -> 0.34172462
A30: Dívida Bruta | B30: ='Bal patrim - Padronizado'!D44+'Bal patrim - Padronizado'!D53 -> 3.434 | C30: ='Bal patrim - Padronizado'!E44+'Bal patrim - Padronizado'!E53 -> 2.705 | D30: ='Bal patrim - Padronizado'!F44+'Bal patrim - Padronizado'!F53 -> 1.976 | E30: ='Bal patrim - Padronizado'!G44+'Bal patrim - Padronizado'!G53 -> 1.248 | F30: ='Bal patrim - Padronizado'!H44+'Bal patrim - Padronizado'!H53 -> 0.739 | G30: ='Bal patrim - Padronizado'!I44+'Bal patrim - Padronizado'!I53 -> 0.537 | H30: ='Bal patrim - Padronizado'!J44+'Bal patrim - Padronizado'!J53 -> 0.336 | I30: ='Bal patrim - Padronizado'!K44+'Bal patrim - Padronizado'!K53 -> 0.134 | J30: ='Bal patrim - Padronizado'!L44+'Bal patrim - Padronizado'!L53 -> 30.794 | K30: ='Bal patrim B3 - 3º TRI 2025'!K58+'Bal patrim B3 - 3º TRI 2025'!K59 -> 27.422 | L30: ='Proj. Despesa não operacional'!L7+'Proj. Despesa não operacional'!L10 -> 22.391244 | M30: ='Proj. Despesa não operacional'!M7+'Proj. Despesa não operacional'!M10 -> 18.283433 | N30: ='Proj. Despesa não operacional'!N7+'Proj. Despesa não operacional'!N10 -> 14.929239 | O30: ='Proj. Despesa não operacional'!O7+'Proj. Despesa não operacional'!O10 -> 12.190402 | P30: ='Proj. Despesa não operacional'!P7+'Proj. Despesa não operacional'!P10 -> 9.9540261 | Q30: ='Proj. Despesa não operacional'!Q7+'Proj. Despesa não operacional'!Q10 -> 8.1279299 | R30: ='Proj. Despesa não operacional'!R7+'Proj. Despesa não operacional'!R10 -> 6.6368428 | S30: ='Proj. Despesa não operacional'!S7+'Proj. Despesa não operacional'!S10 -> 5.4193041 | T30: ='Proj. Despesa não operacional'!T7+'Proj. Despesa não operacional'!T10 -> 4.4251288
A31: CAIXA E EQUIVALENTES | B31: ='Bal patrim - Padronizado'!D7 -> 35.774 | C31: ='Bal patrim - Padronizado'!E7 -> 18.945 | D31: ='Bal patrim - Padronizado'!F7 -> 31.212 | E31: ='Bal patrim - Padronizado'!G7 -> 51.746 | F31: ='Bal patrim - Padronizado'!H7 -> 31.209 | G31: ='Bal patrim - Padronizado'!I7 -> 17.619 | H31: ='Bal patrim - Padronizado'!J7 -> 21.331 | I31: ='Bal patrim - Padronizado'!K7 -> 2.936 | J31: ='Bal patrim - Padronizado'!L7 -> 7.321 | K31: ='Bal patrim B3 - 3º TRI 2025 Atv'!E7 -> 38.09 | L31: - | M31: - | N31: - | O31: - | P31: - | Q31: - | R31: - | S31: - | T31: -
A32: Dívida Líquida | B32: =B30-B31 -> -32.34 | C32: =C30-C31 -> -16.24 | D32: =D30-D31 -> -29.236 | E32: =E30-E31 -> -50.498 | F32: =F30-F31 -> -30.47 | G32: =G30-G31 -> -17.082 | H32: =H30-H31 -> -20.995 | I32: =I30-I31 -> -2.802 | ... K32: =K30-K31 -> -10.668 | L32: - | M32: - | N32: - | O32: - | P32: - | Q32: - | R32: - | S32: - | T32: -
A33: Dívida Líquida/EBITDA | B33: =B32/B23 -> -1.9720715 | C33: =C32/C23 -> -1.2821727 | D33: =D32/D23 -> -1.276514 | E33: =E32/E23 -> -2.023076 | F33: =F32/F23 -> -1.5893798 | G33: =G32/G23 -> -0.16537263 | H33: =H32/H23 -> -0.54538134 | I33: =I32/I23 -> -0.0924112 | ... K33: =K32/K23 -> -0.27354801

Sheet Proj. Receita e MG Operacional
B1: ANO | C1: 2016 | D1: 2017 | E1: 2018 | F1: 2019 | G1: 2020 | H1: 2021 | I1: 2022 | J1: 2023 | K1: 2024 | L1: Últ 12M | T1: LAJIR (Lucro antes de Juros e Imposto de Renda)
B2: Receita | C2: 31.353 | D2: 23.646 | E2: 33.684 | F2: 38.621 | G2: 35.93 | H2: 120.319 | I2: 72.058 | J2: 67.307 | K2: 85.999 | L2: 81.447 | T2: "Causas X": RECEITA E ANO
B3: Lucro Bruto | C3: ='DRE - Ajustado 3º TRI 2025'!C11 -> 17.178 | D3: ='DRE - Ajustado 3º TRI 2025'!D11 -> 13.221 | E3: ='DRE - Ajustado 3º TRI 2025'!E11 -> 23.656 | F3: ='DRE - Ajustado 3º TRI 2025'!F11 -> 25.615 | G3: ='DRE - Ajustado 3º TRI 2025'!G11 -> 23.299 | H3: ='DRE - Ajustado 3º TRI 2025'!H11 -> 106.654 | I3: ='DRE - Ajustado 3º TRI 2025'!I11 -> 44.548 | J3: ='DRE - Ajustado 3º TRI 2025'!J11 -> 34.989 | ... L3: ='DRE - Ajustado 3º TRI 2025'!L11 -> 55.133 | T3: RESUMO DOS RESULTADOS - LAJIR: ANO;RECEITA
B4: LAJIR | C4: ='DRE - Ajustado 3º TRI 2025'!C20 -> 16.399 | D4: ='DRE - Ajustado 3º TRI 2025'!D20 -> 12.666 | E4: ='DRE - Ajustado 3º TRI 2025'!E20 -> 22.903 | F4: ='DRE - Ajustado 3º TRI 2025'!F20 -> 24.961 | G4: ='DRE - Ajustado 3º TRI 2025'!G20 -> 19.171 | H4: ='DRE - Ajustado 3º TRI 2025'!H20 -> 103.23 | I4: ='DRE - Ajustado 3º TRI 2025'!I20 -> 38.323 | J4: ='DRE - Ajustado 3º TRI 2025'!J20 -> 30.123 | ... L4: ='DRE - Ajustado 3º TRI 2025'!L20 -> 50.097
B5: IRPJ+CSLL | C5: ='DRE - Ajustado 3º TRI 2025'!C31/'DRE - Ajustado 3º TRI 2025'!C30 -> 0.32721194 | D5: ='DRE - Ajustado 3º TRI 2025'!D31/'DRE - Ajustado 3º TRI 2025'!D30 -> 0.16240632 | E5: ='DRE - Ajustado 3º TRI 2025'!E31/'DRE - Ajustado 3º TRI 2025'!E30 -> 0.069491874 | F5: ='DRE - Ajustado 3º TRI 2025'!F31/'DRE - Ajustado 3º TRI 2025'!F30 -> 0.076661549 | G5: ='DRE - Ajustado 3º TRI 2025'!G31/'DRE - Ajustado 3º TRI 2025'!G30 -> 0.084462931 | H5: ='DRE - Ajustado 3º TRI 2025'!H31/'DRE - Ajustado 3º TRI 2025'!H30 -> 0.041818671 | I5: ='DRE - Ajustado 3º TRI 2025'!I31/'DRE - Ajustado 3º TRI 2025'!I30 -> 0.088876467 | J5: ='DRE - Ajustado 3º TRI 2025'!J31/'DRE - Ajustado 3º TRI 2025'!J30 -> 0.098042911 | ... L5: ='DRE - Ajustado 3º TRI 2025'!L31/'DRE - Ajustado 3º TRI 2025'!L30 -> 0.29344521 | T5: Estatística de regressão
B6: NOPAT | C6: =C4*(1-C5) -> 11.033051 | D6: =D4*(1-D5) -> 10.608962 | E6: =E4*(1-E5) -> 21.311428 | F6: =F4*(1-F5) -> 23.047451 | G6: =G4*(1-G5) -> 17.551761 | H6: =H4*(1-H5) -> 98.913059 | I6: =I4*(1-I5) -> 34.916987 | J6: =J4*(1-J5) -> 27.169653 | ... L6: =L4*(1-L5) -> 35.396275 | T6: R múltiplo | U6: 0.97957378
T7: R-Quadrado | U7: 0.95956479
T8: R-quadrado ajustado | U8: 0.94801187
T9: Erro padrão | U9: 5.9409812
B10: A empresa tem apenas uma linha de negócio até a data do presente trabalho | T10: Observações | U10: 10
B11: ANO | C11: Receita | D11: Lucro Bruto | E11: LAJIR | F11: LAJIR ESPERADO | G11: MG operacional | H11: IRPJ+CSLL | I11: NOPAT
B12: 2016 | C12: 31.353 | D12: 17.178 | E12: 16.399 | F12: =$U$19+($U$20*B12)+($U$21*C12) -> 25.183041 | G12: =E12/C12 -> 0.52304405 | H12: ='DRE - Ajustado 3º TRI 2025'!C31/'DRE - Ajustado 3º TRI 2025'!C30 -> 0.32721194 | I12: =E12*(1-H12) -> 11.033051 | T12: ANOVA
B13: 2017 | C13: 23.646 | D13: 13.221 | E13: 12.666 | F13: =$U$19+($U$20*B13)+($U$21*C13) -> 12.695883 | G13: =E13/C13 -> 0.53565085 | H13: ='DRE - Ajustado 3º TRI 2025'!D31/'DRE - Ajustado 3º TRI 2025'!D30 -> 0.16240632 | I13: =E13*(1-H13) -> 10.608962 | U13: gl | V13: SQ | W13: MQ | X13: F | Y13: F de significação
B14: 2018 | C14: 33.684 | D14: 23.656 | E14: 22.903 | F14: =$U$19+($U$20*B14)+($U$21*C14) -> 19.113271 | G14: =E14/C14 -> 0.67993706 | H14: ='DRE - Ajustado 3º TRI 2025'!E31/'DRE - Ajustado 3º TRI 2025'!E30 -> 0.069491874 | I14: =E14*(1-H14) -> 21.311428 | T14: Regressão | U14: 2 | V14: 5863.1224 | W14: 2931.5612 | X14: 83.058219 | Y14: 1.3294104e-05
B15: 2019 | C15: 38.621 | D15: 25.615 | E15: 24.961 | F15: =$U$19+($U$20*B15)+($U$21*C15) -> 20.096335 | G15: =E15/C15 -> 0.64630641 | H15: ='DRE - Ajustado 3º TRI 2025'!F31/'DRE - Ajustado 3º TRI 2025'!F30 -> 0.076661549 | I15: =E15*(1-H15) -> 23.047451 | T15: Resíduo | U15: 7 | V15: 247.0668 | W15: 35.295257
B16: 2020 | C16: 35.93 | D16: 23.299 | E16: 19.171 | F16: =$U$19+($U$20*B16)+($U$21*C16) -> 12.952947 | G16: =E16/C16 -> 0.53356527 | H16: ='DRE - Ajustado 3º TRI 2025'!G31/'DRE - Ajustado 3º TRI 2025'!G30 -> 0.084462931 | I16: =E16*(1-H16) -> 17.551761 | T16: Total | U16: 9 | V16: 6110.1892
B17: 2021 | C17: 120.319 | D17: 106.654 | E17: 103.23 | F17: =$U$19+($U$20*B17)+($U$21*C17) -> 98.579798 | G17: =E17/C17 -> 0.85796923 | H17: ='DRE - Ajustado 3º TRI 2025'!H31/'DRE - Ajustado 3º TRI 2025'!H30 -> 0.041818671 | I17: =E17*(1-H17) -> 98.913059
B18: 2022 | C18: 72.058 | D18: 44.548 | E18: 38.323 | F18: =$U$19+($U$20*B18)+($U$21*C18) -> 42.888641 | G18: =E18/C18 -> 0.53183547 | H18: ='DRE - Ajustado 3º TRI 2025'!I31/'DRE - Ajustado 3º TRI 2025'!I30 -> 0.088876467 | I18: =E18*(1-H18) -> 34.916987 | U18: Coeficientes | V18: Erro padrão | W18: Stat t | X18: valor-P | Y18: 95% inferiores | Z18: 95% superiores | AA18: Inferior 99,0% | AB18: Superior 99,0%
B19: 2023 | C19: 67.307 | D19: 34.989 | E19: 30.123 | F19: =$U$19+($U$20*B19)+($U$21*C19) -> 33.550643 | G19: =E19/C19 -> 0.44754632 | H19: ='DRE - Ajustado 3º TRI 2025'!J31/'DRE - Ajustado 3º TRI 2025'!J30 -> 0.098042911 | I19: =E19*(1-H19) -> 27.169653 | T19: Interseção | U19: 8613.2945 | V19: 1860.7223 | W19: 4.6290059 | X19: 0.002400499 | Y19: 4213.3854 | Z19: 13013.204 | AA19: 2101.7279 | AB19: 15124.861
B20: 2024 | C20: 85.999 | D20: 47.908 | E20: 43.628 | F20: =$U$19+($U$20*B20)+($U$21*C20) -> 49.187526 | G20: =E20/C20 -> 0.50730822 | H20: ='DRE - Ajustado 3º TRI 2025'!K31/'DRE - Ajustado 3º TRI 2025'!K30 -> 0.23857152 | I20: =E20*(1-H20) -> 33.219602 | T20: ANO | U20: -4.2765443 | V20: 0.92276318 | W20: -4.6344982 | X20: 0.0023850071 | Y20: -6.4585325 | Z20: -2.0945561 | AA20: -7.5057386 | AB20: -1.0473499
B21: 2025 | C21: 75.76 | D21: 41.201 | E21: 36.847 | F21: =$U$19+($U$20*B21)+($U$21*C21) -> 34.002915 | G21: =E21/C21 -> 0.48636484 | H21: ='DRE - Ajustado 3º TRI 2025'!L31/'DRE - Ajustado 3º TRI 2025'!L30 -> 0.29344521 | I21: =E21*(1-H21) -> 26.034424 | T21: Receita | U21: 1.0653449 | V21: 0.090330597 | W21: 11.793844 | X21: 7.1418976e-06 | Y21: 0.85174702 | Z21: 1.2789429 | AA21: 0.74923453 | AB21: 1.3814554
A24: Crescimento da receita nos últimos 6 anos
A25: Anos | D25: 2018 | E25: 2019 | F25: 2020 | G25: 2021 | H25: 2022 | I25: 2023 | J25: 2024 | K25: 2025
A26: Receita | D26: 33.684 | E26: 38.621 | F26: 35.93 | G26: 120.319 | H26: 72.058 | I26: 67.307 | J26: 85.999 | K26: 81.447
A27: g(Receita) | D27: 0 | E27: =E26/D26-1 -> 0.1465681 | F27: =F26/E26-1 -> -0.069677119 | G27: =G26/F26-1 -> 2.3487058 | H27: =H26/G26-1 -> -0.40110872 | I27: =I26/H26-1 -> -0.065932998 | J27: =J26/I26-1 -> 0.27771257 | K27: =K26/J26-1 -> -0.052930848
A30: MÉDIA GEOMÉTRICA DE CRESCIMENTO DA RECEITA DOS ANOS MAIS ESTÁVEIS
A31: g(Receita) | C31: =EXP(C32)-1 -> 0.065889304
A32: ln[1+g(Rec)] | C32: =AVERAGE(E32:K32) -> 0.063809478 | E32: =LN(E27+1) -> 0.13677322 | F32: =LN(F27+1) -> -0.072223569 | J32: =LN(J27+1) -> 0.24507143 | K32: =LN(K27+1) -> -0.054383166
A33: Desvio-padrão (σ) | C33: =_xlfn.STDEV.S(E32:F32,J32:K32) -> 0.15346454
A34: Z score (modelo) | C34: =(C40-C32)/C33 -> -0.089984816
A40: g(Receita) - Cenário | C40: 0.05
A42: Otimista | C42: =EXP(C32+C34*C33)-1 -> 0.051271096
A43: Base | C43: =EXP(C32+0*C33)-1 -> 0.065889304
A44: Pessimista | C44: =EXP(C32-C34*C33)-1 -> 0.080710782
A45: E(g)=m+Zs
A47: Crescimento por Fadeout
A48: taxa inicial | B48: =C31 -> 0.065889304
A49: taxa final | B49: 0.02
A50: n períodos | B50: 8
A51: δ decresc. | B51: =(B48-B49)/B50 -> 0.005736163 | C51: ao ano
A53: Ano | B53: Crescimento (%) | C53: Receita (R$ mi) | G53: {=TRANSPOSE(A53:C63)} -> Ano | H53: 2025 | I53: 2026 | J53: 2027 | K53: 2028 | L53: 2029 | M53: 2030 | N53: 2031 | O53: 2032 | P53: 2033 | Q53: 2034
A54: 2025 | B54: 0 | C54: =L2*(1+B54) -> 81.447 | G54: Crescimento (%) | H54: 0 | I54: 0.065889304 | J54: 0.060153141 | K54: 0.054416978 | L54: 0.048680815 | M54: 0.042944652 | N54: 0.037208489 | O54: 0.031472326 | P54: 0.025736163 | Q54: 0.02
A55: 2026 | B55: =B48 -> 0.065889304 | C55: =C54*(1+B55) -> 86.813486 | G55: Receita (R$ mi) | H55: 81.447 | I55: 86.813486 | J55: 92.03559 | K55: 97.043889 | L55: 101.76806 | M55: 106.13846 | N55: 110.08771 | O55: 113.55243 | P55: 116.47483 | Q55: 118.80433
A56: 2027 | B56: =B55-$B$51 -> 0.060153141 | C56: =C55*(1+B56) -> 92.03559 | G56: LAJIR ESPERADO | H56: =$U$19+($U$20*H53)+($U$21*H55) -> 40.061532 | I56: =$U$19+($U$20*I53)+($U$21*I55) -> 41.502146 | J56: =$U$19+($U$20*J53)+($U$21*J55) -> 42.788944 | K56: =$U$19+($U$20*K53)+($U$21*K55) -> 43.847966 | L56: =$U$19+($U$20*L53)+($U$21*L55) -> 44.604298 | M56: =$U$19+($U$20*M53)+($U$21*M55) -> 44.983731 | N56: =$U$19+($U$20*N53)+($U$21*N55) -> 44.914502 | O56: =$U$19+($U$20*O53)+($U$21*O55) -> 44.329076 | ... Q56: =$U$19+($U$20*Q53)+($U$21*Q55) -> 41.371073
A57: 2028 | B57: =B56-$B$51 -> 0.054416978 | C57: =C56*(1+B57) -> 97.043889 | G57: MG oper. | H57: =H56/H55 -> 0.49187241 | I57: =I56/I55 -> 0.47806105 | J57: =J56/J55 -> 0.46491737 | K57: =K56/K55 -> 0.45183644 | L57: =L56/L55 -> 0.43829366 | M57: =M56/M55 -> 0.42382122 | N57: =N56/N55 -> 0.40798834 | O57: =O56/O55 -> 0.39038422 | ... Q57: =Q56/Q55 -> 0.34822867
A58: 2029 | B58: =B57-$B$51 -> 0.048680815 | C58: =C57*(1+B58) -> 101.76806
A59: 2030 | B59: =B58-$B$51 -> 0.042944652 | C59: =C58*(1+B59) -> 106.13846
A60: 2031 | B60: =B59-$B$51 -> 0.037208489 | C60: =C59*(1+B60) -> 110.08771
A61: 2032 | B61: =B60-$B$51 -> 0.031472326 | C61: =C60*(1+B61) -> 113.55243
A62: 2033 | B62: =B61-$B$51 -> 0.025736163 | C62: =C61*(1+B62) -> 116.47483
A63: 2034 | B63: 0.02 | C63: =C62*(1+B63) -> 118.80433

Sheet Proj. Custos da receita
A1: Ano | B1: 2016 | C1: 2017 | D1: 2018 | E1: 2019 | F1: 2020 | G1: 2021 | H1: 2022 | I1: 2023 | J1: 2024 | P1: CUSTO DE BENS E SERVIÇOS | AM1: DEPRECIAÇÃO E AMORTIZAÇÃO
A2: Receita | B2: 31.353 | C2: 23.646 | D2: 33.684 | E2: 38.621 | F2: 35.93 | G2: 120.319 | H2: 72.058 | I2: 67.307 | J2: 85.999 | P2: "Causas X": RECEITA E ANO | Z2: "Causas X": ANO | AM2: "Causas X": RECEITA, ANO E CUSTO | AW2: "Causas X": Custo de bens e serviços
A3: Custo de bens e serviços | B3: 0 | C3: 10.425 | D3: 10.028 | E3: 13.006 | F3: 12.631 | G3: 13.665 | H3: 27.45 | I3: 32.273 | J3: 38.034 | P3: RESUMO DOS RESULTADOS | Z3: RESUMO DOS RESULTADOS | AC3: MODELO A SER UTILIZADO PARA A PROJEÇÃO | AM3: RESUMO DOS RESULTADOS | AW3: RESUMO DOS RESULTADOS
A4: Depreciação e amortização | B4: 0 | C4: 0 | D4: 0 | E4: 0 | F4: 0 | G4: 0 | H4: 0.06 | I4: 0.045 | J4: 0.057 | AZ4: MODELO A SER UTILIZADO PARA A PROJEÇÃO
A5: Lucro bruto | B5: 17.178 | C5: 13.221 | D5: 23.656 | E5: 25.615 | F5: 23.299 | G5: 106.654 | H5: 44.548 | I5: 34.989 | J5: 47.908 | P5: Estatística de regressão | Z5: Estatística de regressão | AM5: Estatística de regressão | AW5: Estatística de regressão
P6: R múltiplo | Q6: 0.86629102 | Z6: R múltiplo | AA6: 0.84927412 | AM6: R múltiplo | AN6: 0.94556716 | AW6: R múltiplo | AX6: 0.94423086
A7: Ano | B7: Receita | C7: Custo de bens e serviços | D7: Depreciação e amortização | E7: Lucro bruto | P7: R-Quadrado | Q7: 0.75046013 | Z7: R-Quadrado | AA7: 0.72126654 | AM7: R-Quadrado | AN7: 0.89409725 | AW7: R-Quadrado | AX7: 0.89157191
A8: 2016 | B8: 31.353 | C8: 14.175 | D8: 0 | E8: 17.178 | P8: R-quadrado ajustado | Q8: 0.66728018 | Z8: R-quadrado ajustado | AA8: 0.68144747 | AM8: R-quadrado ajustado | AN8: 0.83055561 | AW8: R-quadrado ajustado | AX8: 0.87608218
A9: 2017 | B9: 23.646 | C9: 10.425 | D9: 0 | E9: 13.221 | P9: Erro padrão | Q9: 6.0911011 | Z9: Erro padrão | AA9: 5.9600101 | AM9: Erro padrão | AN9: 0.011233597 | AW9: Erro padrão | AX9: 0.0096066537
A10: 2018 | B10: 33.684 | C10: 10.028 | D10: 0 | E10: 23.656 | P10: Observações | Q10: 9 | Z10: Observações | AA10: 9 | AM10: Observações | AN10: 9 | AW10: Observações | AX10: 9
A11: 2019 | B11: 38.621 | C11: 13.006 | D11: 0 | E11: 25.615
A12: 2020 | B12: 35.93 | C12: 12.631 | D12: 0 | E12: 23.299 | P12: ANOVA | Z12: ANOVA | AM12: ANOVA | AW12: ANOVA
A13: 2021 | B13: 120.319 | C13: 13.665 | D13: 0 | E13: 106.654 | Q13: gl | R13: SQ | S13: MQ | T13: F | U13: F de significação | AA13: gl | AB13: SQ | AC13: MQ | AD13: F | AE13: F de significação | AN13: gl | AO13: SQ | AP13: MQ | AQ13: F | AR13: F de significação | AX13: gl | AY13: SQ | AZ13: MQ | BA13: F | BB13: F de significação
A14: 2022 | B14: 72.058 | C14: 27.45 | D14: 0.06 | E14: 44.548 | P14: Regressão | Q14: 2 | R14: 669.46912 | S14: 334.73456 | T14: 9.0221271 | U14: 0.015538884 | Z14: Regressão | AA14: 1 | AB14: 643.42615 | AC14: 643.42615 | AD14: 18.113598 | AE14: 0.0037650974 | AM14: Regressão | AN14: 3 | AO14: 0.0053270314 | AP14: 0.0017756771 | AQ14: 14.071043 | AR14: 0.0071480164 | AW14: Regressão | AX14: 1 | AY14: 0.0053119854 | AZ14: 0.0053119854 | BA14: 57.558915 | BB14: 0.00012768217
A15: 2023 | B15: 67.307 | C15: 32.273 | D15: 0.045 | E15: 34.989 | P15: Resíduo | Q15: 6 | R15: 222.60908 | S15: 37.101513 | Z15: Resíduo | AA15: 7 | AB15: 248.65205 | AC15: 35.521721 | AM15: Resíduo | AN15: 5 | AO15: 0.00063096855 | AP15: 0.00012619371 | AW15: Resíduo | AX15: 7 | AY15: 0.00064601457 | AZ15: 9.2287796e-05
A16: 2024 | B16: 85.999 | C16: 38.034 | D16: 0.057 | E16: 47.908 | P16: Total | Q16: 8 | R16: 892.0782 | Z16: Total | AA16: 8 | AB16: 892.0782 | AM16: Total | AN16: 8 | AO16: 0.005958 | AW16: Total | AX16: 8 | AY16: 0.005958
Q18: Coeficientes | R18: Erro padrão | S18: Stat t | T18: valor-P | U18: 95% inferiores | V18: 95% superiores | W18: Inferior 99,0% | X18: Superior 99,0% | AA18: Coeficientes | AB18: Erro padrão | AC18: Stat t | AD18: valor-P | AE18: 95% inferiores | AF18: 95% superiores | AG18: Inferior 99,0% | AH18: Superior 99,0% | AN18: Coeficientes | AO18: Erro padrão | AP18: Stat t | AQ18: valor-P | AR18: 95% inferiores | AS18: 95% superiores | AT18: Inferior 99,0% | AU18: Superior 99,0% | AX18: Coeficientes | AY18: Erro padrão | AZ18: Stat t | BA18: valor-P | BB18: 95% inferiores | BC18: 95% superiores | BD18: Inferior 99,0% | BE18: Superior 99,0%
P19: Interseção | Q19: -7975.5207 | R19: 2287.9933 | S19: -3.4858146 | T19: 0.013049706 | U19: -13574.039 | V19: -2377.0026 | W19: -16458.091 | X19: 507.04999 | Z19: Interseção | AA19: -6595.8513 | AB19: 1554.2579 | AC19: -4.2437302 | AD19: 0.0038226352 | AE19: -10271.087 | AF19: -2920.6153 | AG19: -12034.951 | AH19: -1156.7516 | AM19: Interseção | AN19: -2.0766143 | AO19: 7.3392436 | AP19: -0.28294664 | AQ19: 0.78855787 | AR19: -20.942741 | AS19: 16.789512 | AT19: -31.669494 | AU19: 27.516265 | AW19: Interseção | AX19: -0.028550235 | AY19: 0.0069210741 | AZ19: -4.1251162 | BA19: 0.004431035 | BB19: -0.044915975 | BC19: -0.012184495 | BD19: -0.052770418 | BE19: -0.0043300516
P20: Ano | Q20: 3.9599869 | R20: 1.1346174 | S20: 3.4901518 | T20: 0.012980959 | U20: 1.1836782 | V20: 6.7362957 | W20: -0.2465254 | X20: 8.1664993 | Z20: Ano | AA20: 3.2747167 | AB20: 0.769434 | AC20: 4.2560072 | AD20: 0.0037650974 | AE20: 1.4552944 | AF20: 5.094139 | AG20: 0.58209524 | AH20: 5.9673381 | AM20: Ano | AN20: 0.0010168821 | AO20: 0.0036425678 | AP20: 0.27916628 | AQ20: 0.79129613 | AR20: -0.0083466366 | AS20: 0.010380401 | AT20: -0.013670472 | AU20: 0.015704236 | AW20: Custo de bens e serviços | AX20: 0.0024402087 | AY20: 0.00032164046 | AZ20: 7.5867592 | BA20: 0.00012768217 | BB20: 0.0016796499 | BC20: 0.0032007675 | BD20: 0.0013146333 | BE20: 0.0035657841
P21: Receita | Q21: -0.080935361 | R21: 0.096602611 | S21: -0.83781753 | T21: 0.43423173 | U21: -0.31731343 | V21: 0.15544271 | W21: -0.43908259 | X21: 0.27721187 | AM21: Receita | AN21: -6.3377122e-05 | AO21: 0.00018829401 | AP21: -0.33658598 | AQ21: 0.75009618 | AR21: -0.00054740228 | AS21: 0.00042064803 | AT21: -0.00082260548 | AU21: 0.00069585124
AM22: Custo de bens e serviços | AN22: 0.0023115663 | AO22: 0.00075291755 | AP22: 3.0701453 | AQ22: 0.027779212 | AR22: 0.00037613008 | AS22: 0.0042470025 | AT22: -0.00072430496 | AU22: 0.0053474375
A23: PROJEÇÃO (ESPERADO)
A24: Ano | B24: 2025 | C24: 2026 | D24: 2027 | E24: 2028 | F24: 2029 | G24: 2030 | H24: 2031 | I24: 2032 | J24: 2033 | K24: 2034 | AM24: "Causas X": RECEITA E CUSTO
A25: Custo de bens e serviços | B25: =$AA$19+($AA$20*B24) -> 35.449917 | C25: =$AA$19+($AA$20*C24) -> 38.724633 | D25: =$AA$19+($AA$20*D24) -> 41.99935 | E25: =$AA$19+($AA$20*E24) -> 45.274067 | F25: =$AA$19+($AA$20*F24) -> 48.548783 | G25: =$AA$19+($AA$20*G24) -> 51.8235 | H25: =$AA$19+($AA$20*H24) -> 55.098217 | I25: =$AA$19+($AA$20*I24) -> 58.372933 | ... K25: =$AA$19+($AA$20*K24) -> 64.922367 | AM25: RESUMO DOS RESULTADOS
A26: Depreciação e amortização | B26: =$AX$19+($AX$20*B25) -> 0.057954961 | C26: =$AX$19+($AX$20*C25) -> 0.065945953 | D26: =$AX$19+($AX$20*D25) -> 0.073936945 | E26: =$AX$19+($AX$20*E25) -> 0.081927937 | F26: =$AX$19+($AX$20*F25) -> 0.089918929 | G26: =$AX$19+($AX$20*G25) -> 0.097909922 | H26: =$AX$19+($AX$20*H25) -> 0.10590091 | I26: =$AX$19+($AX$20*I25) -> 0.11389191 | ... K26: =$AX$19+($AX$20*K25) -> 0.12987389
AM27: Estatística de regressão
AM28: R múltiplo | AN28: 0.9446939
AM29: R-Quadrado | AN29: 0.89244657
AM30: R-quadrado ajustado | AN30: 0.85659543
AM31: Erro padrão | AN31: 0.010334435
AM32: Observações | AN32: 9
AM34: ANOVA
AN35: gl | AO35: SQ | AP35: MQ | AQ35: F | AR35: F de significação
AM36: Regressão | AN36: 2 | AO36: 0.0053171967 | AP36: 0.0026585983 | AQ36: 24.893114 | AR36: 0.00124415
AM37: Resíduo | AN37: 6 | AO37: 0.00064080331 | AP37: 0.00010680055
AM38: Total | AN38: 8 | AO38: 0.005958
AN40: Coeficientes | AO40: Erro padrão | AP40: Stat t | AQ40: valor-P | AR40: 95% inferiores | AS40: 95% superiores | AT40: Inferior 99,0% | AU40: Superior 99,0%
AM41: Interseção | AN41: -0.027746532 | AO41: 0.0082868556 | AP41: -3.3482582 | AQ41: 0.015452687 | AR41: -0.048023737 | AS41: -0.0074693271 | AT41: -0.058469453 | AU41: 0.0029763884
AM42: Receita | AN42: -2.8855599e-05 | AO42: 0.00013063075 | AP42: -0.22089438 | AQ42: 0.8324998 | AR42: -0.00034849753 | AS42: 0.00029078633 | AT42: -0.0005131597 | AU42: 0.0004554485
AM43: Custo de bens e serviços | AN43: 0.002483612 | AO43: 0.00039790569 | AP43: 6.2417102 | AQ43: 0.00078322756 | AR43: 0.0015099718 | AS43: 0.0034572522 | AT43: 0.0010084053 | AU43: 0.0039588187

Sheet Proj. Despesas Operacionais
A1: Ano | B1: 2016 | C1: 2017 | D1: 2018 | E1: 2019 | F1: 2020 | G1: 2021 | H1: 2022 | I1: 2023 | J1: 2024 | P1: Venda e marketing | AN1: Geral e administrativas | BJ1: Pesquisa e desenvolvimento | CG1: Depreciação e amortização:
A2: Receita | B2: 31.353 | C2: 23.646 | D2: 33.684 | E2: 38.621 | F2: 35.93 | G2: 120.319 | H2: 72.058 | I2: 67.307 | J2: 85.999 | P2: "Causas X": RECEITA E ANO | Z2: "Causas X": RECEITA E CUSTO DE VENDA | AN2: "Causas X": RECEITA E ANO | AX2: "Causas X": RECEITA(t-1) E ANO | BJ2: "Causas X": RECEITA(t-1) | BS2: "Causas X": RECEITA(t-1) e ANO | CG2: "Causas X": RECEITA, CUSTO DE BENS E ANO | CP2: "Causas X": CUSTO DE BENS E SERVIÇOS
A3: Custo de bens e serviços | B3: 14.175 | C3: 10.425 | D3: 10.028 | E3: 13.006 | F3: 12.631 | G3: 13.665 | H3: 27.45 | I3: 32.273 | J3: 38.034 | P3: RESUMO DOS RESULTADOS | Z3: RESUMO DOS RESULTADOS | AN3: RESUMO DOS RESULTADOS | AX3: RESUMO DOS RESULTADOS | BJ3: RESUMO DOS RESULTADOS | BM3: Bom modelo, mas apenas a causa "ANO" foi melhor | BS3: RESUMO DOS RESULTADOS | CG3: RESUMO DOS RESULTADOS | CP3: RESUMO DOS RESULTADOS | CS3: MODELO A SER UTILIZADO PARA A PROJEÇÃO
A4: Venda e marketing | B4: 0 | C4: 0 | D4: 0.074 | E4: 0.095 | F4: 0 | G4: 0 | H4: 0.018 | I4: 0.185 | J4: 0
A5: Geral e administrativas | B5: 0 | C5: 0.555 | D5: 0.679 | E5: 0.559 | F5: 4.202 | G5: 3.365 | H5: 6.094 | I5: 4.528 | J5: 4.253 | P5: Estatística de regressão | Z5: Estatística de regressão | AN5: Estatística de regressão | AX5: Estatística de regressão | BJ5: Estatística de regressão | BS5: Estatística de regressão | CG5: Estatística de regressão | CP5: Estatística de regressão
A6: Pesquisa e desenvolvimento | B6: 0 | C6: 0.334 | D6: 0.355 | E6: 0.393 | F6: 0.38 | G6: 0.449 | H6: 0.539 | I6: 0.657 | J6: 0.604 | P6: R múltiplo | Q6: 0.42865792 | Z6: R múltiplo | AA6: 0.32764706 | AN6: R múltiplo | AO6: 0.86341318 | AX6: R múltiplo | AY6: 0.91760327 | BJ6: R múltiplo | BK6: 0.77032233 | BS6: R múltiplo | BT6: 0.91341231 | CG6: R múltiplo | CH6: 0.96843062 | CP6: R múltiplo | CQ6: 0.93491455
A7: Depreciação e amortização: | B7: 0 | C7: 0 | D7: 0 | E7: 0 | F7: 0 | G7: 0.064 | H7: 0.113 | I7: 0.153 | J7: 0.136 | P7: R-Quadrado | Q7: 0.18374761 | Z7: R-Quadrado | AA7: 0.1073526 | AN7: R-Quadrado | AO7: 0.74548232 | AX7: R-Quadrado | AY7: 0.84199576 | BJ7: R-Quadrado | BK7: 0.5933965 | BS7: R-Quadrado | BT7: 0.83432204 | CG7: R-Quadrado | CH7: 0.93785786 | CP7: R-Quadrado | CQ7: 0.87406522
P8: R-quadrado ajustado | Q8: -0.088336519 | Z8: R-quadrado ajustado | AA8: -0.19019654 | AN8: R-quadrado ajustado | AO8: 0.6606431 | AX8: R-quadrado ajustado | AY8: 0.78932769 | BJ8: R-quadrado ajustado | BK8: 0.53531028 | BS8: R-quadrado ajustado | BT8: 0.77909606 | CG8: R-quadrado ajustado | CH8: 0.90057258 | CP8: R-quadrado ajustado | CQ8: 0.85607454
A9: Ano | B9: Receita | C9: Geral e administrativas (t-1) | D9: Ano | E9: Geral e administrativas | F9: Custo de bens e serviços | G9: Venda e marketing | H9: Pesquisa e desenvolvimento | I9: Depreciação e amortização: | J9: Ano | K9: Receita (t-1) | P9: Erro padrão | Q9: 0.06768368 | Z9: Erro padrão | AA9: 0.070780186 | AN9: Erro padrão | AO9: 1.3112039 | AX9: Erro padrão | AY9: 1.0331078 | BJ9: Erro padrão | BK9: 0.13086865 | BS9: Erro padrão | BT9: 0.090231013 | CG9: Erro padrão | CH9: 0.02074946 | CP9: Erro padrão | CQ9: 0.024964479
A10: 2016 | B10: 31.353 | C10: 0 | D10: 2016 | E10: 0 | F10: 14.175 | G10: 0 | H10: 0 | I10: 0 | J10: 2016 | K10: 0 | P10: Observações | Q10: 9 | Z10: Observações | AA10: 9 | AN10: Observações | AO10: 9 | AX10: Observações | AY10: 9 | BJ10: Observações | BK10: 9 | BS10: Observações | BT10: 9 | CG10: Observações | CH10: 9 | CP10: Observações | CQ10: 9
A11: 2017 | B11: 23.646 | C11: 0 | D11: 2017 | E11: 0.555 | F11: 10.425 | G11: 0 | H11: 0.334 | I11: 0 | J11: 2017 | K11: 31.353
A12: 2018 | B12: 33.684 | C12: 0.555 | D12: 2018 | E12: 0.679 | F12: 10.028 | G12: 0.074 | H12: 0.355 | I12: 0 | J12: 2018 | K12: 23.646 | P12: ANOVA | Z12: ANOVA | AN12: ANOVA | AX12: ANOVA | BJ12: ANOVA | BS12: ANOVA | CG12: ANOVA | CP12: ANOVA
A13: 2019 | B13: 38.621 | C13: 0.679 | D13: 2019 | E13: 0.559 | F13: 13.006 | G13: 0.095 | H13: 0.393 | I13: 0 | J13: 2019 | K13: 33.684 | Q13: gl | R13: SQ | S13: MQ | T13: F | U13: F de significação | AA13: gl | AB13: SQ | AC13: MQ | AD13: F | AE13: F de significação | AO13: gl | AP13: SQ | AQ13: MQ | AR13: F | AS13: F de significação | AY13: gl | AZ13: SQ | BA13: MQ | BB13: F | BC13: F de significação | BK13: gl | BL13: SQ | BM13: MQ | BN13: F | BO13: F de significação | BT13: gl | BU13: SQ | BV13: MQ | BW13: F | BX13: F de significação | CH13: gl | CI13: SQ | CJ13: MQ | CK13: F | CL13: F de significação | CQ13: gl | CR13: SQ | CS13: MQ | CT13: F | CU13: F de significação
A14: 2020 | B14: 35.93 | C14: 0.559 | D14: 2020 | E14: 4.202 | F14: 12.631 | G14: 0 | H14: 0.38 | I14: 0 | J14: 2020 | K14: 38.621 | P14: Regressão | Q14: 2 | R14: 0.0061875171 | S14: 0.0030937585 | T14: 0.67533381 | U14: 0.54384282 | Z14: Regressão | AA14: 2 | AB14: 0.0036149914 | AC14: 0.0018074957 | AD14: 0.36078948 | AE14: 0.71127875 | AN14: Regressão | AO14: 2 | AP14: 30.214201 | AQ14: 15.107101 | AR14: 8.7870005 | AS14: 0.016487464 | AX14: Regressão | AY14: 2 | AZ14: 34.125866 | BA14: 17.062933 | BB14: 15.986833 | BC14: 0.0039446292 | BJ14: Regressão | BK14: 1 | BL14: 0.17496177 | BM14: 0.17496177 | BN14: 10.215789 | BO14: 0.015145252 | BS14: Regressão | BT14: 2 | BU14: 0.24599819 | BV14: 0.12299909 | BW14: 15.107418 | BX14: 0.0045477251 | CG14: Regressão | CH14: 3 | CI14: 0.032488855 | CJ14: 0.010829618 | CK14: 25.153567 | CL14: 0.0019170181 | CP14: Regressão | CQ14: 1 | CR14: 0.030278979 | CS14: 0.030278979 | CT14: 48.584327 | CU14: 0.00021723229
A15: 2021 | B15: 120.319 | C15: 4.202 | D15: 2021 | E15: 3.365 | F15: 13.665 | G15: 0 | H15: 0.449 | I15: 0.064 | J15: 2021 | K15: 35.93 | P15: Resíduo | Q15: 6 | R15: 0.027486483 | S15: 0.0045810805 | Z15: Resíduo | AA15: 6 | AB15: 0.030059009 | AC15: 0.0050098348 | AN15: Resíduo | AO15: 6 | AP15: 10.315534 | AQ15: 1.7192557 | AX15: Resíduo | AY15: 6 | AZ15: 6.4038699 | BA15: 1.0673116 | BJ15: Resíduo | BK15: 7 | BL15: 0.11988623 | BM15: 0.017126604 | BS15: Resíduo | BT15: 6 | BU15: 0.048849815 | BV15: 0.0081416358 | CG15: Resíduo | CH15: 5 | CI15: 0.0021527004 | CJ15: 0.00043054007 | CP15: Resíduo | CQ15: 7 | CR15: 0.0043625767 | CS15: 0.00062322524
A16: 2022 | B16: 72.058 | C16: 3.365 | D16: 2022 | E16: 6.094 | F16: 27.45 | G16: 0.018 | H16: 0.539 | I16: 0.113 | J16: 2022 | K16: 120.319 | P16: Total | Q16: 8 | R16: 0.033674 | Z16: Total | AA16: 8 | AB16: 0.033674 | AN16: Total | AO16: 8 | AP16: 40.529736 | AX16: Total | AY16: 8 | AZ16: 40.529736 | BJ16: Total | BK16: 8 | BL16: 0.294848 | BS16: Total | BT16: 8 | BU16: 0.294848 | CG16: Total | CH16: 8 | CI16: 0.034641556 | CP16: Total | CQ16: 8 | CR16: 0.034641556
A17: 2023 | B17: 67.307 | C17: 6.094 | D17: 2023 | E17: 4.528 | F17: 32.273 | G17: 0.185 | H17: 0.657 | I17: 0.153 | J17: 2023 | K17: 72.058
A18: 2024 | B18: 85.999 | C18: 4.528 | D18: 2024 | E18: 4.253 | F18: 38.034 | G18: 0 | H18: 0.604 | I18: 0.136 | J18: 2024 | K18: 67.307 | Q18: Coeficientes | R18: Erro padrão | S18: Stat t | T18: valor-P | U18: 95% inferiores | V18: 95% superiores | W18: Inferior 99,0% | X18: Superior 99,0% | AA18: Coeficientes | AB18: Erro padrão | AC18: Stat t | AD18: valor-P | AE18: 95% inferiores | AF18: 95% superiores | AG18: Inferior 99,0% | AH18: Superior 99,0% | AO18: Coeficientes | AP18: Erro padrão | AQ18: Stat t | AR18: valor-P | AS18: 95% inferiores | AT18: 95% superiores | AU18: Inferior 99,0% | AV18: Superior 99,0% | AY18: Coeficientes | AZ18: Erro padrão | BA18: Stat t | BB18: valor-P | BC18: 95% inferiores | BD18: 95% superiores | BE18: Inferior 99,0% | BF18: Superior 99,0% | BK18: Coeficientes | BL18: Erro padrão | BM18: Stat t | BN18: valor-P | BO18: 95% inferiores | BP18: 95% superiores | BQ18: Inferior 99,0% | BR18: Superior 99,0% | BT18: Coeficientes | BU18: Erro padrão | BV18: Stat t | BW18: valor-P | BX18: 95% inferiores | BY18: 95% superiores | BZ18: Inferior 99,0% | CA18: Superior 99,0% | CH18: Coeficientes | CI18: Erro padrão | CJ18: Stat t | CK18: valor-P | CL18: 95% inferiores | CM18: 95% superiores | CN18: Inferior 99,0% | CO18: Superior 99,0% | CQ18: Coeficientes | CR18: Erro padrão | CS18: Stat t | CT18: valor-P | CU18: 95% inferiores | CV18: 95% superiores | CW18: Inferior 99,0% | CX18: Superior 99,0%
A19: 2025 | C19: 4.253 | J19: 2025 | K19: 85.999 | P19: Interseção | Q19: -29.130951 | R19: 25.423943 | S19: -1.1458077 | T19: 0.29550972 | U19: -91.341099 | V19: 33.079197 | W19: -123.38839 | X19: 65.126489 | Z19: Interseção | AA19: 0.026567923 | AB19: 0.056756384 | AC19: 0.46810457 | AD19: 0.65623066 | AE19: -0.11230995 | AF19: 0.16544579 | AG19: -0.18385229 | AH19: 0.23698813 | AN19: Interseção | AO19: -1463.5551 | AP19: 492.52603 | AQ19: -2.9715284 | AR19: 0.024908185 | AS19: -2668.7229 | AT19: -258.38732 | AU19: -3289.5599 | AV19: 362.4497 | AX19: Interseção | AY19: -816.0967 | AZ19: 418.51531 | BA19: -1.9499805 | BB19: 0.099061638 | BC19: -1840.1668 | BD19: 207.97336 | BE19: -2367.7121 | BF19: 735.51867 | BJ19: Interseção | BK19: 0.21363278 | BL19: 0.075945699 | BM19: 2.8129674 | BN19: 0.026034756 | BO19: 0.034049736 | BP19: 0.39321582 | BQ19: -0.052137928 | BR19: 0.47940348 | BS19: Interseção | BT19: -107.75704 | BU19: 36.552876 | BV19: -2.947977 | BW19: 0.025680292 | BX19: -197.1987 | BY19: -18.315371 | BZ19: -243.27419 | CA19: 27.760121 | CG19: Interseção | CH19: -5.1058885 | CI19: 13.55624 | CJ19: -0.3766449 | CK19: 0.72189212 | CL19: -39.953312 | CM19: 29.741535 | CN19: -59.766585 | CO19: 49.554808 | CP19: Interseção | CQ19: -0.0593606 | CR19: 0.017985556 | CS19: -3.3004594 | CT19: 0.013112426 | CU19: -0.10188968 | CV19: -0.016831517 | CW19: -0.12230075 | CX19: 0.0035795548
P20: Ano | Q20: 0.014470391 | R20: 0.01260775 | S20: 1.1477378 | T20: 0.29477138 | U20: -0.016379662 | V20: 0.045320444 | W20: -0.032271935 | X20: 0.061212717 | Z20: Receita | AA20: -0.00050316598 | AB20: 0.00089468544 | AC20: -0.56239429 | AD20: 0.59421984 | AE20: -0.0026923824 | AF20: 0.0016860504 | AG20: -0.0038201479 | AH20: 0.0028138159 | AN20: Ano | AO20: 0.72591974 | AP20: 0.24424398 | AQ20: 2.972109 | AR20: 0.024889471 | AS20: 0.12827625 | AT20: 1.3235632 | AU20: -0.17959723 | AV20: 1.6314367 | AX20: Ano | AY20: 0.40461641 | AZ20: 0.20747508 | BA20: 1.9501928 | BB20: 0.099032488 | BC20: -0.10305682 | BD20: 0.91228965 | BE20: -0.36458252 | BF20: 1.1738153 | BJ20: Receita (t-1) | BK20: 0.0042284911 | BL20: 0.0013229684 | BM20: 3.1962147 | BN20: 0.015145252 | BO20: 0.0011001679 | BP20: 0.0073568143 | BQ20: -0.00040121471 | BR20: 0.0088581969 | BS20: Ano | BT20: 0.053525513 | BU20: 0.018120749 | BV20: 2.9538245 | BW20: 0.025486199 | BX20: 0.0091856365 | BY20: 0.097865389 | BZ20: -0.013655861 | CA20: 0.12070689 | CG20: Ano | CH20: 0.00249656 | CI20: 0.0067281487 | CJ20: 0.37106195 | CK20: 0.72579429 | CL20: -0.014798697 | CM20: 0.019791817 | CN20: -0.024632298 | CO20: 0.029625418 | CP20: Custo de bens e serviços | CQ20: 0.0058259821 | CR20: 0.00083583596 | CS20: 6.9702459 | CT20: 0.00021723229 | CU20: 0.0038495442 | CV20: 0.0078024201 | CW20: 0.0029009882 | CX20: 0.0087509761
A21: PROJEÇÃO (ESPERADO) | P21: Receita | Q21: -0.0010240357 | R21: 0.0010734381 | S21: -0.95397739 | T21: 0.37693141 | U21: -0.0036506442 | V21: 0.0016025728 | W21: -0.0050037303 | X21: 0.0029556589 | Z21: Custo de bens e serviços | AA21: 0.0022655088 | AB21: 0.0027252422 | AC21: 0.8313055 | AD21: 0.43762568 | AE21: -0.0044029186 | AF21: 0.0089339363 | AG21: -0.0078381305 | AH21: 0.012369148 | AN21: Receita | AO21: -0.0019451949 | AP21: 0.020795209 | AQ21: -0.093540528 | AR21: 0.92851953 | AS21: -0.052829239 | AT21: 0.048938849 | AU21: -0.079041936 | AV21: 0.075151546 | AX21: Receita (t-1) | AY21: 0.031161909 | AZ21: 0.016246335 | BA21: 1.9180885 | BB21: 0.10354018 | BC21: -0.0085914406 | BD21: 0.070915259 | BE21: -0.029070209 | BF21: 0.091394027 | BS21: Receita (t-1) | BT21: 0.0010179479 | BU21: 0.0014189452 | BV21: 0.7173976 | BW21: 0.50009216 | BX21: -0.0024540859 | BY21: 0.0044899816 | BZ21: -0.0042426892 | CA21: 0.006278585 | CG21: Receita | CH21: 0.00050143541 | CI21: 0.00034779588 | CJ21: 1.441752 | CK21: 0.20894396 | CL21: -0.00039260235 | CM21: 0.0013954732 | CN21: -0.0009009273 | CO21: 0.0019037981
A22: Ano | B22: 2025 | C22: 2026 | D22: 2027 | E22: 2028 | F22: 2029 | G22: 2030 | H22: 2031 | I22: 2032 | J22: 2033 | K22: 2034 | AN22: "Causas X": ANO | BJ22: "Causas X": RECEITA | BS22: "Causas X": RECEITA e ANO | CG22: Custo de bens e serviços | CH22: 0.0045218705 | CI22: 0.0013907061 | CJ22: 3.2514926 | CK22: 0.022658339 | CL22: 0.00094694673 | CM22: 0.0080967944 | CN22: -0.0010856553 | CO22: 0.010129396
A23: Venda e marketing | B23: =AVERAGE('Projeção DRE'!B9:J9) -> 0.041333333 | C23: =AVERAGE('Projeção DRE'!C9:K9) -> 0.045925926 | D23: =AVERAGE('Projeção DRE'!D9:L9) -> 0.051028807 | E23: =AVERAGE('Projeção DRE'!E9:M9) -> 0.048476452 | F23: =AVERAGE('Projeção DRE'!F9:N9) -> 0.043307169 | G23: =AVERAGE('Projeção DRE'!G9:O9) -> 0.048119076 | H23: =AVERAGE('Projeção DRE'!H9:P9) -> 0.05346564 | I23: =AVERAGE('Projeção DRE'!I9:Q9) -> 0.057406267 | ... K23: =AVERAGE('Projeção DRE'!K9:S9) -> 0.048032428 | AN23: RESUMO DOS RESULTADOS | AQ23: MODELO A SER UTILIZADO PARA A PROJEÇÃO | BJ23: RESUMO DOS RESULTADOS | BS23: RESUMO DOS RESULTADOS | CG23: "Causas X": CUSTO DE BENS E ANO
A24: Geral e administrativas | B24: =$AO$39+($AO$40*B22) -> 6.2400278 | C24: =$AO$39+($AO$40*C22) -> 6.9494778 | D24: =$AO$39+($AO$40*D22) -> 7.6589278 | E24: =$AO$39+($AO$40*E22) -> 8.3683778 | F24: =$AO$39+($AO$40*F22) -> 9.0778278 | G24: =$AO$39+($AO$40*G22) -> 9.7872778 | H24: =$AO$39+($AO$40*H22) -> 10.496728 | I24: =$AO$39+($AO$40*I22) -> 11.206178 | ... K24: =$AO$39+($AO$40*K22) -> 12.625078 | P24: "Causas X": CUSTO DE VENDA | Z24: "Causas X": RECEITA | CG24: RESUMO DOS RESULTADOS
A25: Pesquisa e desenvolvimento | B25: =$BK$59+($BK$60*B22) -> 0.72975 | C25: =$BK$59+($BK$60*C22) -> 0.79323333 | D25: =$BK$59+($BK$60*D22) -> 0.85671667 | E25: =$BK$59+($BK$60*E22) -> 0.9202 | F25: =$BK$59+($BK$60*F22) -> 0.98368333 | G25: =$BK$59+($BK$60*G22) -> 1.0471667 | H25: =$BK$59+($BK$60*H22) -> 1.11065 | I25: =$BK$59+($BK$60*I22) -> 1.1741333 | ... K25: =$BK$59+($BK$60*K22) -> 1.3011 | P25: RESUMO DOS RESULTADOS | Z25: RESUMO DOS RESULTADOS | AN25: Estatística de regressão | BJ25: Estatística de regressão | BS25: Estatística de regressão
A26: Depreciação e amortização: | B26: =$CQ$19+($CQ$20*'Proj. Custos da receita'!B25) -> 0.14716998 | C26: =$CQ$19+($CQ$20*'Proj. Custos da receita'!C25) -> 0.16624842 | D26: =$CQ$19+($CQ$20*'Proj. Custos da receita'!D25) -> 0.18532686 | E26: =$CQ$19+($CQ$20*'Proj. Custos da receita'!E25) -> 0.2044053 | F26: =$CQ$19+($CQ$20*'Proj. Custos da receita'!F25) -> 0.22348375 | G26: =$CQ$19+($CQ$20*'Proj. Custos da receita'!G25) -> 0.24256219 | H26: =$CQ$19+($CQ$20*'Proj. Custos da receita'!H25) -> 0.26164063 | I26: =$CQ$19+($CQ$20*'Proj. Custos da receita'!I25) -> 0.28071907 | ... K26: =$CQ$19+($CQ$20*'Proj. Custos da receita'!K25) -> 0.31887595 | AN26: R múltiplo | AO26: 0.86319821 | BJ26: R múltiplo | BK26: 0.56416289 | BS26: R múltiplo | BT26: 0.91459162 | CG26: Estatística de regressão
P27: Estatística de regressão | Z27: Estatística de regressão | AN27: R-Quadrado | AO27: 0.74511116 | BJ27: R-Quadrado | BK27: 0.31827976 | BS27: R-Quadrado | BT27: 0.83647784 | CG27: R múltiplo | CH27: 0.95499923
P28: R múltiplo | Q28: 0.24555465 | Z28: R múltiplo | AA28: 0.067373072 | AN28: R-quadrado ajustado | AO28: 0.70869847 | BJ28: R-quadrado ajustado | BK28: 0.22089116 | BS28: R-quadrado ajustado | BT28: 0.78197045 | CG28: R-Quadrado | CH28: 0.91202352
P29: R-Quadrado | Q29: 0.060297087 | Z29: R-Quadrado | AA29: 0.0045391308 | AN29: Erro padrão | AO29: 1.2148238 | BJ29: Erro padrão | BK29: 0.16945452 | BS29: Erro padrão | BT29: 0.08964205 | CG29: R-quadrado ajustado | CH29: 0.88269803
P30: R-quadrado ajustado | Q30: -0.073946187 | Z30: R-quadrado ajustado | AA30: -0.13766956 | AN30: Observações | AO30: 9 | BJ30: Observações | BK30: 9 | BS30: Observações | BT30: 9 | CG30: Erro padrão | CH30: 0.022537532
P31: Erro padrão | Q31: 0.067234723 | Z31: Erro padrão | AA31: 0.069200691 | CG31: Observações | CH31: 9
P32: Observações | Q32: 9 | Z32: Observações | AA32: 9 | AN32: ANOVA | BJ32: ANOVA | BS32: ANOVA
AO33: gl | AP33: SQ | AQ33: MQ | AR33: F | AS33: F de significação | BK33: gl | BL33: SQ | BM33: MQ | BN33: F | BO33: F de significação | BT33: gl | BU33: SQ | BV33: MQ | BW33: F | BX33: F de significação | CG33: ANOVA
P34: ANOVA | Z34: ANOVA | AN34: Regressão | AO34: 1 | AP34: 30.199158 | AQ34: 30.199158 | AR34: 20.462952 | AS34: 0.0027204257 | BJ34: Regressão | BK34: 1 | BL34: 0.093844151 | BM34: 0.093844151 | BN34: 3.2681417 | BO34: 0.11358008 | BS34: Regressão | BT34: 2 | BU34: 0.24663382 | BV34: 0.12331691 | BW34: 15.346137 | BX34: 0.0043725006 | CH34: gl | CI34: SQ | CJ34: MQ | CK34: F | CL34: F de significação
Q35: gl | R35: SQ | S35: MQ | T35: F | U35: F de significação | AA35: gl | AB35: SQ | AC35: MQ | AD35: F | AE35: F de significação | AN35: Resíduo | AO35: 7 | AP35: 10.330577 | AQ35: 1.4757968 | BJ35: Resíduo | BK35: 7 | BL35: 0.20100385 | BM35: 0.028714836 | BS35: Resíduo | BT35: 6 | BU35: 0.048214183 | BV35: 0.0080356972 | CG35: Regressão | CH35: 2 | CI35: 0.031593914 | CJ35: 0.015796957 | CK35: 31.100024 | CL35: 0.00068092566
P36: Regressão | Q36: 1 | R36: 0.0020304441 | S36: 0.0020304441 | T36: 0.44916282 | U36: 0.52421891 | Z36: Regressão | AA36: 1 | AB36: 0.00015285069 | AC36: 0.00015285069 | AD36: 0.031918799 | AE36: 0.86326681 | AN36: Total | AO36: 8 | AP36: 40.529736 | BJ36: Total | BK36: 8 | BL36: 0.294848 | BS36: Total | BT36: 8 | BU36: 0.294848 | CG36: Resíduo | CH36: 6 | CI36: 0.003047642 | CJ36: 0.00050794034
P37: Resíduo | Q37: 7 | R37: 0.031643556 | S37: 0.004520508 | Z37: Resíduo | AA37: 7 | AB37: 0.033521149 | AC37: 0.0047887356 | CG37: Total | CH37: 8 | CI37: 0.034641556
P38: Total | Q38: 8 | R38: 0.033674 | Z38: Total | AA38: 8 | AB38: 0.033674 | AO38: Coeficientes | AP38: Erro padrão | AQ38: Stat t | AR38: valor-P | AS38: 95% inferiores | AT38: 95% superiores | AU38: Inferior 99,0% | AV38: Superior 99,0% | BK38: Coeficientes | BL38: Erro padrão | BM38: Stat t | BN38: valor-P | BO38: 95% inferiores | BP38: 95% superiores | BQ38: Inferior 99,0% | BR38: Superior 99,0% | BT38: Coeficientes | BU38: Erro padrão | BV38: Stat t | BW38: valor-P | BX38: 95% inferiores | BY38: 95% superiores | BZ38: Inferior 99,0% | CA38: Superior 99,0%
AN39: Interseção | AO39: -1430.3962 | AP39: 316.80307 | AQ39: -4.5150959 | AR39: 0.0027482177 | AS39: -2179.5164 | AT39: -681.27601 | AU39: -2539.0433 | AV39: -321.74918 | BJ39: Interseção | BK39: 0.22193118 | BL39: 0.11951309 | BM39: 1.8569612 | BN39: 0.10568185 | BO39: -0.060672378 | BP39: 0.50453474 | BQ39: -0.19630289 | BR39: 0.64016525 | BS39: Interseção | BT39: -146.60482 | BU39: 33.672141 | BV39: -4.3538905 | BW39: 0.0048022364 | BX39: -228.99758 | BY39: -64.212054 | BZ39: -271.44185 | CA39: -21.767776 | CH39: Coeficientes | CI39: Erro padrão | CJ39: Stat t | CK39: valor-P | CL39: 95% inferiores | CM39: 95% superiores | CN39: Inferior 99,0% | CO39: Superior 99,0%
Q40: Coeficientes | R40: Erro padrão | S40: Stat t | T40: valor-P | U40: 95% inferiores | V40: 95% superiores | W40: Inferior 99,0% | X40: Superior 99,0% | AA40: Coeficientes | AB40: Erro padrão | AC40: Stat t | AD40: valor-P | AE40: 95% inferiores | AF40: 95% superiores | AG40: Inferior 99,0% | AH40: Superior 99,0% | AN40: Ano | AO40: 0.70945 | AP40: 0.15683307 | AQ40: 4.5235994 | AR40: 0.0027204257 | AS40: 0.33859871 | AT40: 1.0803013 | AU40: 0.16061528 | AV40: 1.2582847 | BJ40: Receita | BK40: 0.0033671883 | BL40: 0.0018625887 | BM40: 1.8078002 | BN40: 0.11358008 | BO40: -0.0010371341 | BP40: 0.0077715108 | BQ40: -0.0031509098 | BR40: 0.0098852864 | BS40: Ano | BT40: 0.072811608 | BU40: 0.016698037 | BV40: 4.3604891 | BW40: 0.0047679576 | BX40: 0.031952984 | BY40: 0.11367023 | BZ40: 0.010904839 | CA40: 0.13471838 | CG40: Interseção | CH40: -17.933659 | CI40: 11.109224 | CJ40: -1.6143034 | CK40: 0.15758868 | CL40: -45.116951 | CM40: 9.2496335 | CN40: -59.120307 | CO40: 23.25299
P41: Interseção | Q41: 0.012553455 | R41: 0.048438979 | S41: 0.25916018 | T41: 0.8029677 | U41: -0.10198653 | V41: 0.12709344 | W41: -0.15695794 | X41: 0.18206485 | Z41: Interseção | AA41: 0.049017592 | AB41: 0.048805948 | AC41: 1.0043364 | AD41: 0.34866366 | AE41: -0.066390136 | AF41: 0.16442532 | AG41: -0.12177801 | AH41: 0.21981319 | BS41: Receita | BT41: -0.0011017365 | BU41: 0.0014216898 | BV41: -0.7749486 | BW41: 0.46780149 | BX41: -0.004580486 | BY41: 0.002377013 | BZ41: -0.006372549 | CA41: 0.004169076 | CG41: Ano | CH41: 0.008867106 | CI41: 0.0055110731 | CJ41: 1.6089618 | CK41: 0.15874974 | CL41: -0.004618004 | CM41: 0.022352216 | CN41: -0.011564801 | CO41: 0.029299013
P42: Custo de bens e serviços | Q42: 0.0015086693 | R42: 0.0022510864 | S42: 0.6701961 | T42: 0.52421891 | U42: -0.0038143041 | V42: 0.0068316427 | W42: -0.0063689698 | X42: 0.0093863084 | Z42: Receita | AA42: -0.00013589313 | AB42: 0.00076063137 | AC42: -0.17865833 | AD42: 0.86326681 | AE42: -0.0019345005 | AF42: 0.0016627142 | AG42: -0.0027977099 | AH42: 0.0025259236 | BJ42: "Causas X": ANO | CG42: Custo de bens e serviços | CH42: 0.0038729744 | CI42: 0.001429257 | CJ42: 2.7097817 | CK42: 0.035116264 | CL42: 0.00037570851 | CM42: 0.0073702404 | CN42: -0.0014258931 | CO42: 0.009171842
BJ43: RESUMO DOS RESULTADOS | BM43: MODELO A SER UTILIZADO PARA A PROJEÇÃO
BJ45: Estatística de regressão
BJ46: R múltiplo | BK46: 0.90559967
BJ47: R-Quadrado | BK47: 0.82011076
BJ48: R-quadrado ajustado | BK48: 0.79441229
BJ49: Erro padrão | BK49: 0.087046772
BJ50: Observações | BK50: 9
BJ52: ANOVA
BK53: gl | BL53: SQ | BM53: MQ | BN53: F | BO53: F de significação
BJ54: Regressão | BK54: 1 | BL54: 0.24180802 | BM54: 0.24180802 | BN54: 31.912833 | BO54: 0.00077517031
BJ55: Resíduo | BK55: 7 | BL55: 0.053039983 | BM55: 0.0075771405
BJ56: Total | BK56: 8 | BL56: 0.294848
BK58: Coeficientes | BL58: Erro padrão | BM58: Stat t | BN58: valor-P | BO58: 95% inferiores | BP58: 95% superiores | BQ58: Inferior 99,0% | BR58: Superior 99,0%
BJ59: Interseção | BK59: -127.824 | BL59: 22.700152 | BM59: -5.6309755 | BN59: 0.00078997588 | BO59: -181.50133 | BP59: -74.14667 | BQ59: -207.2628 | BR59: -48.385197
BJ60: Ano | BK60: 0.063483333 | BL60: 0.01123769 | BM60: 5.6491444 | BN60: 0.00077517031 | BO60: 0.036910419 | BP60: 0.090056247 | BQ60: 0.024157225 | BR60: 0.10280944

Sheet Proj. Despesa não operacional
A1: Ano | B1: 2016 | C1: 2017 | D1: 2018 | E1: 2019 | F1: 2020 | G1: 2021 | H1: 2022 | I1: 2023 | J1: 2024 | K1: 2025 | L1: 2026 | M1: 2027 | N1: 2028 | O1: 2029 | P1: 2030 | Q1: 2031 | R1: 2032 | S1: 2033 | T1: 2034 | W1: Despesa de juros, líq | AV1: Despesa com juros | BT1: Outros Prejuízos (Lucros) não op
A2: Receita | B2: 31.353 | C2: 23.646 | D2: 33.684 | E2: 38.621 | F2: 35.93 | G2: 120.319 | H2: 72.058 | I2: 67.307 | J2: 85.999 | W2: "Causas X": CAPITAL INVESTIDO, DÍVIDA LP e CP | AF2: "Causas X": CAPITAL INVESTIDO | AV2: "Causas X": Dívida LP (t-1) | AX2: MODELO A SER UTILIZADO PARA A PROJEÇÃO | BE2: "Causas X": Dívida LP (t-1) e CP (t-1) | BT2: "Causas X": Dívida LP (t-1) | CC2: "Causas X": EBIT (LAJIR)
A3: Capital Investido (T-1) | B3: =DADOS!E19 -> 48.617 | C3: =DADOS!F19 -> 34.12 | D3: =DADOS!G19 -> 173.063 | E3: =DADOS!H19 -> 170.254 | F3: =DADOS!I19 -> 169.813 | G3: =DADOS!J19 -> 248.141 | H3: =DADOS!K19 -> 259.026 | I3: =DADOS!L19 -> 270.264 | ... K3: =DADOS!N19 -> 0 | W3: Estatística de regressão | AF3: Estatística de regressão | AV3: Estatística de regressão | BE3: Estatística de regressão | BT3: Estatística de regressão | CC3: Estatística de regressão
A4: Lucro (Prejuízo) operacional (EBIT/LAJIR) | B4: 16.399 | C4: 12.666 | D4: 22.903 | E4: 24.961 | F4: 19.171 | G4: 103.23 | H4: 38.323 | I4: 30.123 | J4: 43.628 | W4: RESUMO DOS RESULTADOS | AF4: RESUMO DOS RESULTADOS | AV4: RESUMO DOS RESULTADOS | BE4: RESUMO DOS RESULTADOS | BT4: RESUMO DOS RESULTADOS | CC4: RESUMO DOS RESULTADOS
A5: Capital Investido | B5: =DADOS!E19 -> 48.617 | C5: =DADOS!F19 -> 34.12 | D5: =DADOS!G19 -> 173.063 | E5: =DADOS!H19 -> 170.254 | F5: =DADOS!I19 -> 169.813 | G5: =DADOS!J19 -> 248.141 | H5: =DADOS!K19 -> 259.026 | I5: =DADOS!L19 -> 270.264 | ... K5: =DADOS!N19 -> 0
A6: Capital Investido (T-1) | B6: =DADOS!E17 -> 7.45 | C6: =DADOS!E19 -> 48.617 | D6: =DADOS!F19 -> 34.12 | E6: =DADOS!G19 -> 173.063 | F6: =DADOS!H19 -> 170.254 | G6: =DADOS!I19 -> 169.813 | H6: =DADOS!J19 -> 248.141 | I6: =DADOS!K19 -> 259.026 | J6: =DADOS!L19 -> 270.264 | K6: =DADOS!M19 -> 317.531 | W6: Estatística de regressão | AF6: Estatística de regressão | AV6: Estatística de regressão | BE6: Estatística de regressão | BT6: Estatística de regressão | CC6: Estatística de regressão
A7: Dívida LP | B7: 2.699 | C7: 1.972 | D7: 1.245 | E7: 0.737 | F7: 0.536 | G7: 0.335 | H7: 0.134 | I7: 0 | J7: 30.706 | K7: 26.373 | L7: =K7-(K7*$B$22) -> 21.538912 | M7: =L7-(L7*$B$22) -> 17.590898 | N7: =M7-(M7*$B$22) -> 14.366542 | O7: =N7-(N7*$B$22) -> 11.7332 | P7: =O7-(O7*$B$22) -> 9.5825416 | Q7: =P7-(P7*$B$22) -> 7.826092 | R7: =Q7-(Q7*$B$22) -> 6.391594 | S7: =R7-(R7*$B$22) -> 5.2200351 | T7: =S7-(S7*$B$22) -> 4.2632191 | W7: R múltiplo | X7: 0.61386848 | AF7: R múltiplo | AG7: 0.59056649 | AV7: R múltiplo | AW7: 0.87748227 | BE7: R múltiplo | BF7: 0.87984162 | BT7: R múltiplo | BU7: 0.4501963 | CC7: R múltiplo | CD7: 0.1778586
A8: Dívida LP (t-1) | B8: 3.426 | C8: =B7 -> 2.699 | D8: =C7 -> 1.972 | E8: =D7 -> 1.245 | F8: =E7 -> 0.737 | G8: =F7 -> 0.536 | H8: =G7 -> 0.335 | I8: =H7 -> 0.134 | J8: =I7 -> 0 | ... T8: =S7 -> 5.2200351 | W8: R-Quadrado | X8: 0.37683451 | AF8: R-Quadrado | AG8: 0.34876878 | AV8: R-Quadrado | AW8: 0.76997514 | AX8: Apesar do intercepto ter o "p-value" maior que 0,05, o modelo será considerado, uma vez que o "X causa" não será testado quando o valor for "0" | BE8: R-Quadrado | BF8: 0.77412128 | BT8: R-Quadrado | BU8: 0.20267671 | CC8: R-Quadrado | CD8: 0.031633681
A9: Dívida CP (t-1) | B9: 0.61 | C9: =B10 -> 0.735 | D9: =C10 -> 0.733 | E9: =D10 -> 0.731 | F9: =E10 -> 0.511 | G9: =F10 -> 0.203 | H9: =G10 -> 0.202 | I9: =H10 -> 0.202 | J9: =I10 -> 0.134 | ... T9: =S10 -> 0.19926907 | W9: R-quadrado ajustado | X9: 0.0029352113 | AF9: R-quadrado ajustado | AG9: 0.25573575 | AV9: R-quadrado ajustado | AW9: 0.73711444 | BE9: R-quadrado ajustado | BF9: 0.69882838 | BT9: R-quadrado ajustado | BU9: 0.088773381 | CC9: R-quadrado ajustado | CD9: -0.10670436
A10: Dívida CP | B10: 0.735 | C10: 0.733 | D10: 0.731 | E10: 0.511 | F10: 0.203 | G10: 0.202 | H10: 0.202 | I10: 0.134 | J10: 0.088 | K10: 1.049 | L10: =K10-(K10*$B$27) -> 0.8523315 | M10: =L10-(L10*$B$27) -> 0.69253478 | N10: =M10-(M10*$B$27) -> 0.56269705 | O10: =N10-(N10*$B$27) -> 0.45720154 | P10: =O10-(O10*$B$27) -> 0.37148453 | Q10: =P10-(P10*$B$27) -> 0.30183791 | R10: =Q10-(Q10*$B$27) -> 0.24524877 | S10: =R10-(R10*$B$27) -> 0.19926907 | T10: =S10-(S10*$B$27) -> 0.16190973 | W10: Erro padrão | X10: 1.3004934 | AF10: Erro padrão | AG10: 1.1235956 | AV10: Erro padrão | AW10: 0.031517681 | BE10: Erro padrão | BF10: 0.033734782 | BT10: Erro padrão | BU10: 0.1315073 | CC10: Erro padrão | CD10: 0.14492806
A11: Despesa de juros, líq | B11: -5.26 | C11: -2.429 | D11: -1.491 | E11: -2.349 | F11: -1.403 | G11: -0.938 | H11: -2.908 | I11: -1.434 | J11: -1.64 | K11: -1.101 | L11: =-(SUM(K8:K9)*B34) -> -40.364641 | W11: Observações | X11: 9 | AF11: Observações | AG11: 9 | AV11: Observações | AW11: 9 | BE11: Observações | BF11: 9 | BT11: Observações | BU11: 9 | CC11: Observações | CD11: 9
A12: Despesa com juros | B12: 0.192 | C12: 0.157 | D12: 0.121 | E12: 0.086 | F12: 0.053 | G12: 0.037 | H12: 0.025 | I12: 0.014 | J12: 0.105
A13: Despesa de juros, líq (t-1) | B13: 0 | C13: =B11 -> -5.26 | D13: =C11 -> -2.429 | E13: =D11 -> -1.491 | F13: =E11 -> -2.349 | G13: =F11 -> -1.403 | H13: =G11 -> -0.938 | I13: =H11 -> -2.908 | J13: =I11 -> -1.434 | K13: =J11 -> -1.64 | W13: ANOVA | AF13: ANOVA | AV13: ANOVA | BE13: ANOVA | BT13: ANOVA | CC13: ANOVA
A14: Despesa com juros (t-1) | B14: 0 | C14: =B12 -> 0.192 | D14: =C12 -> 0.157 | E14: =D12 -> 0.121 | F14: =E12 -> 0.086 | G14: =F12 -> 0.053 | H14: =G12 -> 0.037 | I14: =H12 -> 0.025 | J14: =I12 -> 0.014 | K14: =J12 -> 0.105 | X14: gl | Y14: SQ | Z14: MQ | AA14: F | AB14: F de significação | AG14: gl | AH14: SQ | AI14: MQ | AJ14: F | AK14: F de significação | AW14: gl | AX14: SQ | AY14: MQ | AZ14: F | BA14: F de significação | BF14: gl | BG14: SQ | BH14: MQ | BI14: F | BJ14: F de significação | BU14: gl | BV14: SQ | BW14: MQ | BX14: F | BY14: F de significação | CD14: gl | CE14: SQ | CF14: MQ | CG14: F | CH14: F de significação
A15: Outros Prejuízos (Lucros) não op | B15: 0 | C15: 0.151 | D15: 0.089 | E15: -0.044 | F15: 0.139 | G15: 0.004 | H15: 0.084 | I15: -0.276 | J15: -0.129 | W15: Regressão | X15: 3 | Y15: 5.1136803 | Z15: 1.7045601 | AA15: 1.0078503 | AB15: 0.46203057 | AF15: Regressão | AG15: 1 | AH15: 4.7328257 | AI15: 4.7328257 | AJ15: 3.7488704 | AK15: 0.094059834 | AV15: Regressão | AW15: 1 | AX15: 0.023276006 | AY15: 0.023276006 | AZ15: 23.431493 | BA15: 0.0018764443 | BE15: Regressão | BF15: 2 | BG15: 0.023401342 | BH15: 0.011700671 | BI15: 10.281464 | BJ15: 0.011524602 | BT15: Regressão | BU15: 1 | BV15: 0.03077281 | BW15: 0.03077281 | BX15: 1.7793748 | BY15: 0.22398904 | CC15: Regressão | CD15: 1 | CE15: 0.004803005 | CF15: 0.004803005 | CG15: 0.22866942 | CH15: 0.64708553
A16: Caixa e equivalentes de caixa (t) | B16: 35.774 | C16: 18.945 | D16: 31.212 | E16: 51.746 | F16: 31.209 | G16: 17.619 | H16: 21.331 | I16: 2.936 | J16: 7.321 | W16: Resíduo | X16: 5 | Y16: 8.4564153 | Z16: 1.6912831 | AF16: Resíduo | AG16: 7 | AH16: 8.8372699 | AI16: 1.2624671 | AW16: Resíduo | AX16: 7 | AY16: 0.0069535494 | AZ16: 0.0009933642 | BF16: Resíduo | BG16: 6 | BH16: 0.0068282132 | BI16: 0.0011380355 | BU16: Resíduo | BV16: 7 | BW16: 0.12105919 | BX16: 0.01729417 | CD16: Resíduo | CE16: 7 | CF16: 0.147029 | CG16: 0.021004142
A17: Caixa e equivalentes de caixa (t-1) | B17: 42.264 | C17: =B16 -> 35.774 | D17: =C16 -> 18.945 | E17: =D16 -> 31.212 | F17: =E16 -> 51.746 | G17: =F16 -> 31.209 | H17: =G16 -> 17.619 | I17: =H16 -> 21.331 | J17: =I16 -> 2.936 | K17: =J16 -> 7.321 | W17: Total | X17: 8 | Y17: 13.570096 | AF17: Total | AG17: 8 | AH17: 13.570096 | AW17: Total | AX17: 8 | AY17: 0.030229556 | BF17: Total | BG17: 8 | BH17: 0.030229556 | BU17: Total | BV17: 8 | BW17: 0.151832 | CD17: Total | CE17: 8 | CF17: 0.151832
A19: Dívida de Longo Prazo | X19: Coeficientes | Y19: Erro padrão | Z19: Stat t | AA19: valor-P | AB19: 95% inferiores | AC19: 95% superiores | AD19: Inferior 99,0% | AE19: Superior 99,0% | AG19: Coeficientes | AH19: Erro padrão | AI19: Stat t | AJ19: valor-P | AK19: 95% inferiores | AL19: 95% superiores | AM19: Inferior 99,0% | AN19: Superior 99,0% | AX19: Coeficientes | AY19: Erro padrão | AZ19: Stat t | BA19: valor-P | BB19: 95% inferiores | BC19: 95% superiores | BD19: Inferior 99,0% | BE19: Superior 99,0% | BG19: Coeficientes | BH19: Erro padrão | BI19: Stat t | BJ19: valor-P | BK19: 95% inferiores | BL19: 95% superiores | BM19: Inferior 99,0% | BN19: Superior 99,0% | BV19: Coeficientes | BW19: Erro padrão | BX19: Stat t | BY19: valor-P | BZ19: 95% inferiores | CA19: 95% superiores | CB19: Inferior 99,0% | CC19: Superior 99,0% | CE19: Coeficientes | CF19: Erro padrão | CG19: Stat t | CH19: valor-P | CI19: 95% inferiores | CJ19: 95% superiores | CK19: Inferior 99,0% | CL19: Superior 99,0%
A20: Montante amortizado (mi.) | B20: =B7-C7 -> 0.727 | C20: =C7-D7 -> 0.727 | D20: =D7-E7 -> 0.508 | E20: =E7-F7 -> 0.201 | F20: =F7-G7 -> 0.201 | G20: =G7-H7 -> 0.201 | H20: =H7-I7 -> 0.134 | J20: =J7-K7 -> 4.333 | W20: Interseção | X20: -3.6843812 | Y20: 3.0070654 | Z20: -1.2252414 | AA20: 0.27504818 | AB20: -11.414289 | AC20: 4.0455266 | AD20: -15.809299 | AE20: 8.4405366 | AF20: Interseção | AG20: -3.6865543 | AH20: 0.8515692 | AI20: -4.3291307 | AJ20: 0.0034415054 | AK20: -5.7001955 | AL20: -1.6729132 | AM20: -6.6666065 | AN20: -0.70650216 | AW20: Interseção | AX20: 0.033012902 | AY20: 0.015439304 | AZ20: 2.1382377 | BA20: 0.069815762 | BB20: -0.0034952516 | BC20: 0.069521055 | BD20: -0.021016686 | BE20: 0.087042489 | BF20: Interseção | BG20: 0.038891078 | BH20: 0.024224454 | BI20: 1.605447 | BJ20: 0.15951815 | BK20: -0.020384026 | BL20: 0.098166182 | BM20: -0.050919343 | BN20: 0.1287015 | BU20: Interseção | BV20: -0.060969675 | BW20: 0.064420388 | BX20: -0.94643446 | BY20: 0.37544357 | BZ20: -0.21329969 | CA20: 0.091360336 | CB20: -0.28640775 | CC20: 0.1644684 | CD20: Interseção | CE20: 0.032688266 | CF20: 0.080326025 | CG20: 0.4069449 | CH20: 0.69620403 | CI20: -0.1572526 | CJ20: 0.22262913 | CK20: -0.24841132 | CL20: 0.31378785
A21: Porcentagem em relação à dívida do periódo | B21: =B20/B7 -> 0.26935902 | C21: =C20/C7 -> 0.36866126 | D21: =D20/D7 -> 0.40803213 | E21: =E20/E7 -> 0.27272727 | F21: =F20/F7 -> 0.375 | G21: =G20/G7 -> 0.6 | H21: =H20/H7 -> 1 | J21: =J20/J7 -> 0.14111249 | W21: Capital Investido | X21: 0.0086453154 | Y21: 0.009803315 | Z21: 0.88187673 | AA21: 0.41821476 | AB21: -0.016554908 | AC21: 0.033845539 | AD21: -0.030883052 | AE21: 0.048173683 | AF21: Capital Investido | AG21: 0.007881926 | AH21: 0.0040708222 | AI21: 1.9362 | AJ21: 0.094059834 | AK21: -0.001744039 | AL21: 0.017507891 | AM21: -0.0063638484 | AN21: 0.0221277 | AW21: Dívida LP (t-1) | AX21: 0.044468052 | AY21: 0.0091864586 | AZ21: 4.8406087 | BA21: 0.0018764443 | BB21: 0.022745529 | BC21: 0.066190574 | BD21: 0.012320193 | BE21: 0.07661591 | BF21: Dívida LP (t-1) | BG21: 0.048626579 | BH21: 0.015928052 | BI21: 3.0528894 | BJ21: 0.02242861 | BK21: 0.0096520412 | BL21: 0.087601117 | BM21: -0.010425525 | BN21: 0.10767868 | BU21: Dívida LP (t-1) | BV21: 0.051130195 | BW21: 0.038330434 | BX21: 1.3339321 | BY21: 0.22398904 | BZ21: -0.039506878 | CA21: 0.14176727 | CB21: -0.083006517 | CC21: 0.18526691 | CD21: Lucro (Prejuízo) operacional (EBIT/LAJIR) | CE21: -0.00088693272 | CF21: 0.0018547554 | CG21: -0.47819391 | CH21: 0.64708553 | CI21: -0.0052727322 | CJ21: 0.0034988668 | CK21: -0.0073776181 | CL21: 0.0056037527
A22: Média ponderada da amortiz. em relação à dívida | B22: =SUM($B$20:$H$20,J20)/SUM($B$7:$H$7,J7) -> 0.18329684 | W22: Dívida LP | X22: -0.024007308 | Y22: 0.051106542 | Z22: -0.46975019 | AA22: 0.65830709 | AB22: -0.15538086 | AC22: 0.10736624 | AD22: -0.23007619 | AE22: 0.18206158 | BF22: Dívida CP (t-1) | BG22: -0.02437742 | BH22: 0.073456022 | BI22: -0.33186415 | BJ22: 0.75127783 | BK22: -0.20411783 | BL22: 0.15536299 | BM22: -0.29671034 | BN22: 0.2479555 | BU22: "Causas X": Receita e Capital Investido (t-1) | CD22: "Causas X": Ano
W23: Dívida CP | X23: -0.11000361 | Y23: 3.2767498 | Z23: -0.033570953 | AA23: 0.97451823 | AB23: -8.5331571 | AC23: 8.3131498 | AD23: -13.322327 | AE23: 13.10232 | AW23: "Causas X": Despesa de juros, líq | BF23: "Causas X": Dívida LP | BU23: RESUMO DOS RESULTADOS | CD23: RESUMO DOS RESULTADOS
A24: Dívida de Curto Prazo | W24: "Causas X": DÍVIDA LP | AF24: "Causas X": DÍVIDA CP | AW24: RESUMO DOS RESULTADOS | BF24: RESUMO DOS RESULTADOS
A25: Montante amortizado (mi.) | B25: =B10-C10 -> 0.002 | C25: =C10-D10 -> 0.002 | D25: =D10-E10 -> 0.22 | E25: =E10-F10 -> 0.308 | F25: =F10-G10 -> 0.001 | G25: =G10-H10 -> 0 | H25: =H10-I10 -> 0.068 | I25: =I10-J10 -> 0.046 | W25: RESUMO DOS RESULTADOS | AF25: RESUMO DOS RESULTADOS | BU25: Estatística de regressão | CD25: Estatística de regressão
A26: Porcentagem em relação à dívida do periódo | B26: =B25/B10 -> 0.0027210884 | C26: =C25/C10 -> 0.002728513 | D26: =D25/D10 -> 0.30095759 | E26: =E25/E10 -> 0.60273973 | F26: =F25/F10 -> 0.0049261084 | G26: =G25/G10 -> 0 | H26: =H25/H10 -> 0.33663366 | I26: =I25/I10 -> 0.34328358 | AW26: Estatística de regressão | BF26: Estatística de regressão | BU26: R múltiplo | BV26: 0.55178411 | CD26: R múltiplo | CE26: 0.58278526
A27: Média ponderada das taxas de Longo Prazo | B27: =SUM(B25:I25)/SUM(B10:I10) -> 0.18748189 | W27: Estatística de regressão | AF27: Estatística de regressão | AW27: R múltiplo | AX27: 0.63260822 | BF27: R múltiplo | BG27: 0.19252158 | BU27: R-Quadrado | BV27: 0.3044657 | CD27: R-Quadrado | CE27: 0.33963866
W28: R múltiplo | X28: 0.098658568 | AF28: R múltiplo | AG28: 0.52288762 | AW28: R-Quadrado | AX28: 0.40019316 | BF28: R-Quadrado | BG28: 0.037064558 | BU28: R-quadrado ajustado | BV28: 0.072620937 | CD28: R-quadrado ajustado | CE28: 0.24530132
A29: Despesa de juros, líq | B29: =B11 -> -5.26 | C29: =C11 -> -2.429 | D29: =D11 -> -1.491 | E29: =E11 -> -2.349 | F29: =F11 -> -1.403 | G29: =G11 -> -0.938 | H29: =H11 -> -2.908 | I29: =I11 -> -1.434 | J29: =J11 -> -1.64 | W29: R-Quadrado | X29: 0.0097335131 | AF29: R-Quadrado | AG29: 0.27341146 | AW29: R-quadrado ajustado | AX29: 0.31450647 | BF29: R-quadrado ajustado | BG29: -0.10049765 | BU29: Erro padrão | BV29: 0.13266773 | CD29: Erro padrão | CE29: 0.11968052
A30: Porcentagem em relação à dívida do periódo t-1 | B30: =-(B29/SUM(B8:B9)) -> 1.3032706 | C30: =-(C29/SUM(C8:C9)) -> 0.70733838 | D30: =-(D29/SUM(D8:D9)) -> 0.55120148 | E30: =-(E29/SUM(E8:E9)) -> 1.1887652 | F30: =-(F29/SUM(F8:F9)) -> 1.1241987 | G30: =-(G29/SUM(G8:G9)) -> 1.2692828 | H30: =-(H29/SUM(H8:H9)) -> 5.41527 | I30: =-(I29/SUM(I8:I9)) -> 4.2678571 | J30: =-(J29/SUM(J7,J10)) -> 0.053257128 | W30: R-quadrado ajustado | X30: -0.13173313 | AF30: R-quadrado ajustado | AG30: 0.1696131 | AW30: Erro padrão | AX30: 0.050894701 | BF30: Erro padrão | BG30: 0.064486001 | BU30: Observações | BV30: 9 | CD30: Observações | CE30: 9
A31: Porcentagem em relação à dívida do periódo t | B31: =-(B29/SUM(B7,B10)) -> 1.5317414 | C31: =-(C29/SUM(C7,C10)) -> 0.89796673 | D31: =-(D29/SUM(D7,D10)) -> 0.75455466 | E31: =-(E29/SUM(E7,E10)) -> 1.8822115 | F31: =-(F29/SUM(F7,F10)) -> 1.8985115 | G31: =-(G29/SUM(G7,G10)) -> 1.7467412 | H31: =-(H29/SUM(H7,H10)) -> 8.6547619 | I31: =-(I29/SUM(I7,I10)) -> 10.701493 | J31: =-(J29/SUM(J7,J10)) -> 0.053257128 | W31: Erro padrão | X31: 1.3855381 | AF31: Erro padrão | AG31: 1.1868251 | AW31: Observações | AX31: 9 | BF31: Observações | BG31: 9
A32: Porcentagem em relação ao caixa do periódo t-1 | B32: =-(B29/B17) -> 0.1244558 | C32: =-(C29/C17) -> 0.067898474 | D32: =-(D29/D17) -> 0.078701504 | E32: =-(E29/E17) -> 0.075259516 | F32: =-(F29/F17) -> 0.027113207 | G32: =-(G29/G17) -> 0.030055433 | H32: =-(H29/H17) -> 0.16504909 | I32: =-(I29/I17) -> 0.067226103 | J32: =-(J29/J17) -> 0.55858311 | W32: Observações | X32: 9 | AF32: Observações | AG32: 9 | BU32: ANOVA | CD32: ANOVA
A33: Porcentagem em relação ao caixa do periódo t | B33: =-(B29/B16) -> 0.14703416 | C33: =-(C29/C16) -> 0.12821325 | D33: =-(D29/D16) -> 0.047770088 | E33: =-(E29/E16) -> 0.045394813 | F33: =-(F29/F16) -> 0.044954981 | G33: =-(G29/G16) -> 0.053237982 | H33: =-(H29/H16) -> 0.13632741 | I33: =-(I29/I16) -> 0.48841962 | J33: =-(J29/J16) -> 0.22401311 | AW33: ANOVA | BF33: ANOVA | BV33: gl | BW33: SQ | BX33: MQ | BY33: F | BZ33: F de significação | CE33: gl | CF33: SQ | CG33: MQ | CH33: F | CI33: F de significação
A34: Média ponderada dos rendimentos t (dívida) | B34: =-SUM(B29:J29)/SUM(B8:J9) -> 1.3107956 | W34: ANOVA | AF34: ANOVA | AX34: gl | AY34: SQ | AZ34: MQ | BA34: F | BB34: F de significação | BG34: gl | BH34: SQ | BI34: MQ | BJ34: F | BK34: F de significação | BU34: Regressão | BV34: 2 | BW34: 0.046227637 | BX34: 0.023113818 | BY34: 1.3132309 | BZ34: 0.33647721 | CD34: Regressão | CE34: 1 | CF34: 0.051568017 | CG34: 0.051568017 | CH34: 3.6002571 | CI34: 0.099581
A35: Média ponderada dos rendimentos t-1 (dívida) | B35: =-SUM(B29:J29)/SUM(B7:J7,B10:J10) -> 0.47376083 | X35: gl | Y35: SQ | Z35: MQ | AA35: F | AB35: F de significação | AG35: gl | AH35: SQ | AI35: MQ | AJ35: F | AK35: F de significação | AW35: Regressão | AX35: 1 | AY35: 0.012097661 | AZ35: 0.012097661 | BA35: 4.6704238 | BB35: 0.06749659 | BF35: Regressão | BG35: 1 | BH35: 0.0011204451 | BI35: 0.0011204451 | BJ35: 0.26943852 | BK35: 0.6197111 | BU35: Resíduo | BV35: 6 | BW35: 0.10560436 | BX35: 0.017600727 | CD35: Resíduo | CE35: 7 | CF35: 0.10026398 | CG35: 0.014323426
A36: Média ponderada dos rendimentos t-1 (caixa) | B36: =-SUM(B29:J29)/SUM(B17:J17) -> 0.07845524 | W36: Regressão | X36: 1 | Y36: 0.1320847 | Z36: 0.1320847 | AA36: 0.068804299 | AB36: 0.80063753 | AF36: Regressão | AG36: 1 | AH36: 3.7102196 | AI36: 3.7102196 | AJ36: 2.6340633 | AK36: 0.1486232 | AW36: Resíduo | AX36: 7 | AY36: 0.018131894 | AZ36: 0.0025902706 | BF36: Resíduo | BG36: 7 | BH36: 0.02910911 | BI36: 0.0041584444 | BU36: Total | BV36: 8 | BW36: 0.151832 | CD36: Total | CE36: 8 | CF36: 0.151832
A37: Média ponderada dos rendimentos t (caixa) | B37: =-SUM(B29:J29)/SUM(B16:J16) -> 0.091025388 | W37: Resíduo | X37: 7 | Y37: 13.438011 | Z37: 1.9197158 | AF37: Resíduo | AG37: 7 | AH37: 9.8598759 | AI37: 1.4085537 | AW37: Total | AX37: 8 | AY37: 0.030229556 | BF37: Total | BG37: 8 | BH37: 0.030229556
W38: Total | X38: 8 | Y38: 13.570096 | AF38: Total | AG38: 8 | AH38: 13.570096 | BV38: Coeficientes | BW38: Erro padrão | BX38: Stat t | BY38: valor-P | BZ38: 95% inferiores | CA38: 95% superiores | CB38: Inferior 99,0% | CC38: Superior 99,0% | CE38: Coeficientes | CF38: Erro padrão | CG38: Stat t | CH38: valor-P | CI38: 95% inferiores | CJ38: 95% superiores | CK38: Inferior 99,0% | CL38: Superior 99,0%
AX39: Coeficientes | AY39: Erro padrão | AZ39: Stat t | BA39: valor-P | BB39: 95% inferiores | BC39: 95% superiores | BD39: Inferior 99,0% | BE39: Superior 99,0% | BG39: Coeficientes | BH39: Erro padrão | BI39: Stat t | BJ39: valor-P | BK39: 95% inferiores | BL39: 95% superiores | BM39: Inferior 99,0% | BN39: Superior 99,0% | BU39: Interseção | BV39: 0.011964691 | BW39: 0.12260163 | BX39: 0.097589981 | BY39: 0.92543627 | BZ39: -0.2880307 | CA39: 0.31196008 | CB39: -0.44257204 | CC39: 0.46650142 | CD39: Interseção | CE39: 59.221667 | CF39: 31.210416 | CG39: 1.8974969 | CH39: 0.099571844 | CI39: -14.57924 | CJ39: 133.02257 | CK39: -49.998663 | CL39: 168.442
A40: {=TRANSPOSE(A1:J15)} -> Ano | B40: Receita | C40: Capital Investido (T-1) | D40: Lucro (Prejuízo) operacional (EBIT/LAJIR) | E40: Capital Investido | F40: Capital Investido (T-1) | G40: Dívida LP | H40: Dívida LP (t-1) | I40: Dívida CP (t-1) | J40: Dívida CP | K40: Despesa de juros, líq | L40: Despesa com juros | M40: Despesa de juros, líq (t-1) | N40: Despesa com juros (t-1) | O40: Outros Prejuízos (Lucros) não op | X40: Coeficientes | Y40: Erro padrão | Z40: Stat t | AA40: valor-P | AB40: 95% inferiores | AC40: 95% superiores | AD40: Inferior 99,0% | AE40: Superior 99,0% | AG40: Coeficientes | AH40: Erro padrão | AI40: Stat t | AJ40: valor-P | AK40: 95% inferiores | AL40: 95% superiores | AM40: Inferior 99,0% | AN40: Superior 99,0% | AW40: Interseção | AX40: 0.021917886 | AY40: 0.034878788 | AZ40: 0.62840158 | BA40: 0.54968664 | BB40: -0.060557343 | BC40: 0.10439311 | BD40: -0.10013985 | BE40: 0.14397562 | BF40: Interseção | BG40: 0.082710935 | BH40: 0.023607887 | BI40: 3.5035298 | BJ40: 0.0099456406 | BK40: 0.026887153 | BL40: 0.13853472 | BM40: 9.5528436e-05 | BN40: 0.16532634 | BU40: Receita | BV40: -0.0014930332 | BW40: 0.0014734342 | BX40: -1.0133015 | BY40: 0.35002084 | BZ40: -0.0050983968 | CA40: 0.0021123305 | CB40: -0.0069556844 | CC40: 0.0039696181 | CD40: Ano | CE40: -0.029316667 | CF40: 0.015450688 | CG40: -1.8974343 | CH40: 0.099581 | CI40: -0.065851739 | CJ40: 0.0072184057 | CK40: -0.083386092 | CL40: 0.024752759
A41: 2016 | B41: 31.353 | C41: 48.617 | D41: 16.399 | E41: 48.617 | F41: 7.45 | G41: 2.699 | H41: 3.426 | I41: 0.61 | J41: 0.735 | K41: -5.26 | L41: 0.192 | M41: 0 | N41: 0 | O41: 0 | W41: Interseção | X41: -2.2607912 | Y41: 0.50723609 | Z41: -4.4570787 | AA41: 0.0029464012 | AB41: -3.4602139 | AC41: -1.0613684 | AD41: -4.0358554 | AE41: -0.48572695 | AF41: Interseção | AG41: -1.2514398 | AH41: 0.7087092 | AI41: -1.7658015 | AJ41: 0.12077479 | AK41: -2.9272707 | AL41: 0.42439116 | AM41: -3.7315558 | AN41: 1.2286762 | AW41: Despesa de juros, líq | AX41: -0.0298579 | AY41: 0.013815962 | AZ41: -2.1611163 | BA41: 0.06749659 | BB41: -0.062527458 | BC41: 0.0028116577 | BD41: -0.078206627 | BE41: 0.018490827 | BF41: Dívida LP | BG41: 0.0011886557 | BH41: 0.0022899513 | BI41: 0.51907468 | BJ41: 0.6197111 | BK41: -0.0042262186 | BL41: 0.00660353 | BM41: -0.0068249905 | BN41: 0.0092023019 | BU41: Capital Investido (T-1) | BV41: -0.0032439165 | BW41: 0.0029314301 | BX41: -1.1065986 | BY41: 0.31085007 | BZ41: -0.010416868 | CA41: 0.0039290346 | CB41: -0.014111983 | CC41: 0.0076241497
A42: 2017 | B42: 23.646 | C42: 34.12 | D42: 12.666 | E42: 34.12 | F42: 48.617 | G42: 1.972 | H42: 2.699 | I42: 0.735 | J42: 0.733 | K42: -2.429 | L42: 0.157 | M42: -5.26 | N42: 0.192 | O42: 0.151 | W42: Dívida LP | X42: 0.012905863 | Y42: 0.049201604 | Z42: 0.26230574 | AA42: 0.80063753 | AB42: -0.10343744 | AC42: 0.12924917 | AD42: -0.15927433 | AE42: 0.18508606 | AF42: Dívida CP | AG42: -2.4269686 | AH42: 1.4953782 | AI42: -1.6229798 | AJ42: 0.1486232 | AK42: -5.9629762 | AL42: 1.109039 | AM42: -7.6600197 | AN42: 2.8060825 | BU42: "Causas X": Despesa de juros, líq (t-1) e Despesa com juros (t-1) | CD42: "Causas X": Despesa com juros (t-1)
A43: 2018 | B43: 33.684 | C43: 173.063 | D43: 22.903 | E43: 173.063 | F43: 34.12 | G43: 1.245 | H43: 1.972 | I43: 0.733 | J43: 0.731 | K43: -1.491 | L43: 0.121 | M43: -2.429 | N43: 0.157 | O43: 0.089 | W43: "Causas X": RECEITA E ANO | AF43: "Causas X": ANO | BU43: RESUMO DOS RESULTADOS | CD43: RESUMO DOS RESULTADOS
A44: 2019 | B44: 38.621 | C44: 170.254 | D44: 24.961 | E44: 170.254 | F44: 173.063 | G44: 0.737 | H44: 1.245 | I44: 0.731 | J44: 0.511 | K44: -2.349 | L44: 0.086 | M44: -1.491 | N44: 0.121 | O44: -0.044 | W44: RESUMO DOS RESULTADOS | AF44: RESUMO DOS RESULTADOS
A45: 2020 | B45: 35.93 | C45: 169.813 | D45: 19.171 | E45: 169.813 | F45: 170.254 | G45: 0.536 | H45: 0.737 | I45: 0.511 | J45: 0.203 | K45: -1.403 | L45: 0.053 | M45: -2.349 | N45: 0.086 | O45: 0.139 | BU45: Estatística de regressão | CD45: Estatística de regressão
A46: 2021 | B46: 120.319 | C46: 248.141 | D46: 103.23 | E46: 248.141 | F46: 169.813 | G46: 0.335 | H46: 0.536 | I46: 0.203 | J46: 0.202 | K46: -0.938 | L46: 0.037 | M46: -1.403 | N46: 0.053 | O46: 0.004 | W46: Estatística de regressão | AF46: Estatística de regressão | BU46: R múltiplo | BV46: 0.66033802 | CD46: R múltiplo | CE46: 0.57614275
A47: 2022 | B47: 72.058 | C47: 259.026 | D47: 38.323 | E47: 259.026 | F47: 248.141 | G47: 0.134 | H47: 0.335 | I47: 0.202 | J47: 0.202 | K47: -2.908 | L47: 0.025 | M47: -0.938 | N47: 0.037 | O47: 0.084 | W47: R múltiplo | X47: 0.56500774 | AF47: R múltiplo | AG47: 0.56220077 | BU47: R-Quadrado | BV47: 0.4360463 | CD47: R-Quadrado | CE47: 0.33194047
A48: 2023 | B48: 67.307 | C48: 270.264 | D48: 30.123 | E48: 270.264 | F48: 259.026 | G48: 0 | H48: 0.134 | I48: 0.202 | J48: 0.134 | K48: -1.434 | L48: 0.014 | M48: -2.908 | N48: 0.025 | O48: -0.276 | W48: R-Quadrado | X48: 0.31923375 | AF48: R-Quadrado | AG48: 0.3160697 | BU48: R-quadrado ajustado | BV48: 0.24806173 | CD48: R-quadrado ajustado | CE48: 0.23650339
A49: 2024 | B49: 85.999 | C49: 317.531 | D49: 43.628 | E49: 317.531 | F49: 270.264 | G49: 30.706 | H49: 0 | I49: 0.134 | J49: 0.088 | K49: -1.64 | L49: 0.105 | M49: -1.434 | N49: 0.014 | O49: -0.129 | W49: R-quadrado ajustado | X49: 0.092311661 | AF49: R-quadrado ajustado | AG49: 0.21836537 | BU49: Erro padrão | BV49: 0.11946144 | CD49: Erro padrão | CE49: 0.12037609
W50: Erro padrão | X50: 1.2408373 | AF50: Erro padrão | AG50: 1.1514587 | BU50: Observações | BV50: 9 | CD50: Observações | CE50: 9
W51: Observações | X51: 9 | AF51: Observações | AG51: 9
BU52: ANOVA | CD52: ANOVA
W53: ANOVA | AF53: ANOVA | BV53: gl | BW53: SQ | BX53: MQ | BY53: F | BZ53: F de significação | CE53: gl | CF53: SQ | CG53: MQ | CH53: F | CI53: F de significação
A54: PROJEÇÃO (ESPERADO) | X54: gl | Y54: SQ | Z54: MQ | AA54: F | AB54: F de significação | AG54: gl | AH54: SQ | AI54: MQ | AJ54: F | AK54: F de significação | BU54: Regressão | BV54: 2 | BW54: 0.066205782 | BX54: 0.033102891 | BY54: 2.3195856 | BZ54: 0.17936197 | CD54: Regressão | CE54: 1 | CF54: 0.050399185 | CG54: 0.050399185 | CH54: 3.4781081 | CI54: 0.10444673
A55: Ano | B55: 2025 | C55: 2026 | D55: 2027 | E55: 2028 | F55: 2029 | G55: 2030 | H55: 2031 | I55: 2032 | J55: 2033 | K55: 2034 | W55: Regressão | X55: 2 | Y55: 4.3320324 | Z55: 2.1660162 | AA55: 1.4067989 | AB55: 0.31549615 | AF55: Regressão | AG55: 1 | AH55: 4.2890961 | AI55: 4.2890961 | AJ55: 3.2349611 | AK55: 0.11512012 | BU55: Resíduo | BV55: 6 | BW55: 0.085626218 | BX55: 0.014271036 | CD55: Resíduo | CE55: 7 | CF55: 0.10143282 | CG55: 0.014490402
A56: Despesa de juros, líq | W56: Resíduo | X56: 6 | Y56: 9.2380631 | Z56: 1.5396772 | AF56: Resíduo | AG56: 7 | AH56: 9.2809995 | AI56: 1.3258571 | BU56: Total | BV56: 8 | BW56: 0.151832 | CD56: Total | CE56: 8 | CF56: 0.151832
A57: Despesa de juros, líq | B57: =$AG$118+($AG$119*K8) -> -23.979668 | C57: =$AG$118+($AG$119*L8) -> -20.778716 | D57: =$AG$118+($AG$119*M8) -> -17.207592 | E57: =$AG$118+($AG$119*N8) -> -14.291044 | F57: =$AG$118+($AG$119*O8) -> -11.90909 | G57: =$AG$118+($AG$119*P8) -> -9.9637409 | H57: =$AG$118+($AG$119*Q8) -> -8.3749679 | I57: =$AG$118+($AG$119*R8) -> -7.0774119 | ... K57: =$AG$118+($AG$119*T8) -> -5.1522188 | W57: Total | X57: 8 | Y57: 13.570096 | AF57: Total | AG57: 8 | AH57: 13.570096
A58: Despesa com juros | B58: =$AX$20+($AX$21*K8) -> 1.3984489 | C58: =$AX$20+($AX$21*L8) -> 1.2057688 | D58: =$AX$20+($AX$21*M8) -> 0.99080637 | E58: =$AX$20+($AX$21*N8) -> 0.81524585 | F58: =$AX$20+($AX$21*O8) -> 0.67186502 | G58: =$AX$20+($AX$21*P8) -> 0.55476545 | H58: =$AX$20+($AX$21*Q8) -> 0.45912986 | I58: =$AX$20+($AX$21*R8) -> 0.38102396 | ... K58: =$AX$20+($AX$21*T8) -> 0.26513769 | BV58: Coeficientes | BW58: Erro padrão | BX58: Stat t | BY58: valor-P | BZ58: 95% inferiores | CA58: 95% superiores | CB58: Inferior 99,0% | CC58: Superior 99,0% | CE58: Coeficientes | CF58: Erro padrão | CG58: Stat t | CH58: valor-P | CI58: 95% inferiores | CJ58: 95% superiores | CK58: Inferior 99,0% | CL58: Superior 99,0%
A59: Outros Prejuízos (Lucros) não op | B59: =(SUM($B$15:$J$15)/(SUM($B$4:$J$4))) -> 5.7802726e-05 | C59: =(SUM($B$15:$J$15)/(SUM($B$4:$J$4))) -> 5.7802726e-05 | D59: =(SUM($B$15:$J$15)/(SUM($B$4:$J$4))) -> 5.7802726e-05 | E59: =(SUM($B$15:$J$15)/(SUM($B$4:$J$4))) -> 5.7802726e-05 | F59: =(SUM($B$15:$J$15)/(SUM($B$4:$J$4))) -> 5.7802726e-05 | G59: =(SUM($B$15:$J$15)/(SUM($B$4:$J$4))) -> 5.7802726e-05 | H59: =(SUM($B$15:$J$15)/(SUM($B$4:$J$4))) -> 5.7802726e-05 | I59: =(SUM($B$15:$J$15)/(SUM($B$4:$J$4))) -> 5.7802726e-05 | ... K59: =(SUM($B$15:$J$15)/(SUM($B$4:$J$4))) -> 5.7802726e-05 | X59: Coeficientes | Y59: Erro padrão | Z59: Stat t | AA59: valor-P | AB59: 95% inferiores | AC59: 95% superiores | AD59: Inferior 99,0% | AE59: Superior 99,0% | AG59: Coeficientes | AH59: Erro padrão | AI59: Stat t | AJ59: valor-P | AK59: 95% inferiores | AL59: 95% superiores | AM59: Inferior 99,0% | AN59: Superior 99,0% | BU59: Interseção | BV59: -0.05294958 | BW59: 0.070260206 | BX59: -0.75362118 | BY59: 0.47959511 | BZ59: -0.22487011 | CA59: 0.11897095 | CB59: -0.31343424 | CC59: 0.20753508 | CD59: Interseção | CE59: -0.087543126 | CF59: 0.06257246 | CG59: -1.399068 | CH59: 0.20450853 | CI59: -0.23550348 | CJ59: 0.06041723 | CK59: -0.3065144 | CL59: 0.13142815
W60: Interseção | X60: -486.26654 | Y60: 466.0943 | Z60: -1.0432793 | AA60: 0.33701892 | AB60: -1626.7582 | AC60: 654.22512 | AD60: -2214.2776 | AE60: 1241.7445 | AF60: Interseção | AG60: -542.28644 | AH60: 300.27865 | AI60: -1.8059441 | AJ60: 0.11388918 | AK60: -1252.3326 | AL60: 167.75973 | AM60: -1593.1066 | AN60: 508.53367 | BU60: Despesa de juros, líq (t-1) | BV60: 0.043702444 | BW60: 0.041525445 | BX60: 1.0524257 | BY60: 0.3331309 | BZ60: -0.05790666 | CA60: 0.14531155 | CB60: -0.11025015 | CC60: 0.19765504 | CD60: Despesa com juros (t-1) | CE60: 1.176479 | CF60: 0.63083045 | CG60: 1.8649687 | CH60: 0.10444673 | CI60: -0.31519797 | CJ60: 2.668156 | CK60: -1.0311016 | CL60: 3.3840597
W61: Ano | X61: 0.23954204 | Y61: 0.23113647 | Z61: 1.0363663 | AA61: 0.33998199 | AB61: -0.32602851 | AC61: 0.8051126 | AD61: -0.61737976 | AE61: 1.0964639 | AF61: Ano | AG61: 0.26736667 | AH61: 0.14865268 | AI61: 1.7985998 | AJ61: 0.11512012 | AK61: -0.084141054 | AL61: 0.61887439 | AM61: -0.25284089 | AN61: 0.78757422 | BU61: Despesa com juros (t-1) | BV61: 1.8838761 | BW61: 0.91854232 | BX61: 2.050941 | BY61: 0.086129754 | BZ61: -0.36371599 | CA61: 4.1314682 | CB61: -1.5215534 | CC61: 5.2893056
W62: Receita | X62: 0.0032862886 | Y62: 0.019679221 | Z62: 0.16699282 | AA62: 0.87286156 | AB62: -0.04486703 | AC62: 0.051439607 | AD62: -0.069673005 | AE62: 0.076245582 | BU62: "Causas X": Despesa de juros, líq e Despesa com juros | CD62: "Causas X": Despesa com juros
W63: "Causas X": RECEITA | AF63: "Causas X": Capital Investido (t-1) | BU63: RESUMO DOS RESULTADOS | CD63: RESUMO DOS RESULTADOS
W64: RESUMO DOS RESULTADOS | AF64: RESUMO DOS RESULTADOS
BU65: Estatística de regressão | CD65: Estatística de regressão
W66: Estatística de regressão | AF66: Estatística de regressão | BU66: R múltiplo | BV66: 0.32573886 | CD66: R múltiplo | CE66: 0.31466535
W67: R múltiplo | X67: 0.44426381 | AF67: R múltiplo | AG67: 0.47290049 | BU67: R-Quadrado | BV67: 0.1061058 | CD67: R-Quadrado | CE67: 0.099014282
W68: R-Quadrado | X68: 0.19737033 | AF68: R-Quadrado | AG68: 0.22363487 | BU68: R-quadrado ajustado | BV68: -0.19185893 | CD68: R-quadrado ajustado | CE68: -0.029697964
W69: R-quadrado ajustado | X69: 0.082708951 | AF69: R-quadrado ajustado | AG69: 0.11272557 | BU69: Erro padrão | BV69: 0.15040043 | CD69: Erro padrão | CE69: 0.13979498
W70: Erro padrão | X70: 1.2473836 | AF70: Erro padrão | AG70: 1.2268047 | BU70: Observações | BV70: 9 | CD70: Observações | CE70: 9
W71: Observações | X71: 9 | AF71: Observações | AG71: 9
BU72: ANOVA | CD72: ANOVA
W73: ANOVA | AF73: ANOVA | BV73: gl | BW73: SQ | BX73: MQ | BY73: F | BZ73: F de significação | CE73: gl | CF73: SQ | CG73: MQ | CH73: F | CI73: F de significação
X74: gl | Y74: SQ | Z74: MQ | AA74: F | AB74: F de significação | AG74: gl | AH74: SQ | AI74: MQ | AJ74: F | AK74: F de significação | BU74: Regressão | BV74: 2 | BW74: 0.016110256 | BX74: 0.0080551282 | BY74: 0.35610189 | BZ74: 0.71426333 | CD74: Regressão | CE74: 1 | CF74: 0.015033536 | CG74: 0.015033536 | CH74: 0.76926854 | CI74: 0.40953305
W75: Regressão | X75: 1 | Y75: 2.6783343 | Z75: 2.6783343 | AA75: 1.7213322 | AB75: 0.23090689 | AF75: Regressão | AG75: 1 | AH75: 3.0347466 | AI75: 3.0347466 | AJ75: 2.0163761 | AK75: 0.19857787 | BU75: Resíduo | BV75: 6 | BW75: 0.13572174 | BX75: 0.022620291 | CD75: Resíduo | CE75: 7 | CF75: 0.13679846 | CG75: 0.019542638
W76: Resíduo | X76: 7 | Y76: 10.891761 | Z76: 1.5559659 | AF76: Resíduo | AG76: 7 | AH76: 10.535349 | AI76: 1.5050499 | BU76: Total | BV76: 8 | BW76: 0.151832 | CD76: Total | CE76: 8 | CF76: 0.151832
W77: Total | X77: 8 | Y77: 13.570096 | AF77: Total | AG77: 8 | AH77: 13.570096
BV78: Coeficientes | BW78: Erro padrão | BX78: Stat t | BY78: valor-P | BZ78: 95% inferiores | CA78: 95% superiores | CB78: Inferior 99,0% | CC78: Superior 99,0% | CE78: Coeficientes | CF78: Erro padrão | CG78: Stat t | CH78: valor-P | CI78: 95% inferiores | CJ78: 95% superiores | CK78: Inferior 99,0% | CL78: Superior 99,0%
X79: Coeficientes | Y79: Erro padrão | Z79: Stat t | AA79: valor-P | AB79: 95% inferiores | AC79: 95% superiores | AD79: Inferior 99,0% | AE79: Superior 99,0% | AG79: Coeficientes | AH79: Erro padrão | AI79: Stat t | AJ79: valor-P | AK79: 95% inferiores | AL79: 95% superiores | AM79: Inferior 99,0% | AN79: Superior 99,0% | BU79: Interseção | BV79: -0.048063093 | BW79: 0.10593872 | BX79: -0.45368771 | BY79: 0.66600098 | BZ79: -0.30728579 | CA79: 0.21115961 | CB79: -0.44082326 | CC79: 0.34469707 | CD79: Interseção | CE79: -0.05990123 | CF79: 0.084572162 | CG79: -0.70828543 | CH79: 0.50166565 | CI79: -0.25988261 | CJ79: 0.14008015 | CK79: -0.3558601 | CL79: 0.23605764
W80: Interseção | X80: -3.2229644 | Y80: 0.87975624 | Z80: -3.6634743 | AA80: 0.0080332931 | AB80: -5.3032573 | AC80: -1.1426715 | AD80: -6.3016567 | AE80: -0.14427212 | AF80: Interseção | AG80: -3.143452 | AH80: 0.77670706 | AI80: -4.0471526 | AJ80: 0.0048883898 | AK80: -4.9800724 | AL80: -1.3068316 | AM80: -5.8615254 | AN80: -0.4253786 | BU80: Despesa de juros, líq | BV80: 0.011501493 | BW80: 0.052717151 | BX80: 0.21817365 | BY80: 0.83452491 | BZ80: -0.11749273 | CA80: 0.14049571 | CB80: -0.18394355 | CC80: 0.20694654 | CD80: Despesa com juros | CE80: 0.70520388 | CF80: 0.8040364 | CG80: 0.87707955 | CH80: 0.40953305 | CI80: -1.1960401 | CJ80: 2.6064478 | CK80: -2.1085081 | CL80: 3.5189158
W81: Receita | X81: 0.017988551 | Y81: 0.013710833 | Z81: 1.3119955 | AA81: 0.23090689 | AB81: -0.014432417 | AC81: 0.050409519 | AD81: -0.029992279 | AE81: 0.065969382 | AF81: Capital Investido (T-1) | AG81: 0.0061119538 | AH81: 0.0043042183 | AI81: 1.4199916 | AJ81: 0.19857787 | AK81: -0.0040659052 | AL81: 0.016289813 | AM81: -0.0089505863 | AN81: 0.021174494 | BU81: Despesa com juros | BV81: 0.85936138 | BW81: 1.116934 | BX81: 0.76939317 | BY81: 0.47085384 | BZ81: -1.8736776 | CA81: 3.5924004 | CB81: -3.2815909 | CC81: 5.0003137
W82: "Causas X": LAJIR | AF82: "Causas X": DÍVIDA LP (t-1) | BU82: "Causas X": Despesa de juros, líq | CD82: "Causas X": Despesa de juros, líq (t-1)
W83: RESUMO DOS RESULTADOS | AF83: RESUMO DOS RESULTADOS | BU83: RESUMO DOS RESULTADOS | CD83: RESUMO DOS RESULTADOS
W85: Estatística de regressão | AF85: Estatística de regressão | BU85: Estatística de regressão | CD85: Estatística de regressão
W86: R múltiplo | X86: 0.4417863 | AF86: R múltiplo | AG86: 0.68802635 | BU86: R múltiplo | BV86: 0.13384069 | CD86: R múltiplo | CE86: 0.20169535
W87: R-Quadrado | X87: 0.19517513 | AF87: R-Quadrado | AG87: 0.47338026 | BU87: R-Quadrado | BV87: 0.01791333 | CD87: R-Quadrado | CE87: 0.040681014
W88: R-quadrado ajustado | X88: 0.080200152 | AF88: R-quadrado ajustado | AG88: 0.39814887 | BU88: R-quadrado ajustado | BV88: -0.12238477 | CD88: R-quadrado ajustado | CE88: -0.096364555
W89: Erro padrão | X89: 1.2490883 | AF89: Erro padrão | AG89: 1.0103946 | BU89: Erro padrão | BV89: 0.14595116 | CD89: Erro padrão | CE89: 0.14424945
W90: Observações | X90: 9 | AF90: Observações | AG90: 9 | BU90: Observações | BV90: 9 | CD90: Observações | CE90: 9
W92: ANOVA | AF92: ANOVA | BU92: ANOVA | CD92: ANOVA
X93: gl | Y93: SQ | Z93: MQ | AA93: F | AB93: F de significação | AG93: gl | AH93: SQ | AI93: MQ | AJ93: F | AK93: F de significação | BV93: gl | BW93: SQ | BX93: MQ | BY93: F | BZ93: F de significação | CE93: gl | CF93: SQ | CG93: MQ | CH93: F | CI93: F de significação
W94: Regressão | X94: 1 | Y94: 2.6485452 | Z94: 2.6485452 | AA94: 1.6975444 | AB94: 0.23382983 | AF94: Regressão | AG94: 1 | AH94: 6.4238154 | AI94: 6.4238154 | AJ94: 6.2923236 | AK94: 0.040488576 | BU94: Regressão | BV94: 1 | BW94: 0.0027198168 | BX94: 0.0027198168 | BY94: 0.12768049 | BZ94: 0.73137942 | CD94: Regressão | CE94: 1 | CF94: 0.0061766798 | CG94: 0.0061766798 | CH94: 0.29684297 | CI94: 0.60278538
W95: Resíduo | X95: 7 | Y95: 10.92155 | Z95: 1.5602215 | AF95: Resíduo | AG95: 7 | AH95: 7.1462802 | AI95: 1.0208972 | BU95: Resíduo | BV95: 7 | BW95: 0.14911218 | BX95: 0.02130174 | CD95: Resíduo | CE95: 7 | CF95: 0.14565532 | CG95: 0.020807903
W96: Total | X96: 8 | Y96: 13.570096 | AF96: Total | AG96: 8 | AH96: 13.570096 | BU96: Total | BV96: 8 | BW96: 0.151832 | CD96: Total | CE96: 8 | CF96: 0.151832
X98: Coeficientes | Y98: Erro padrão | Z98: Stat t | AA98: valor-P | AB98: 95% inferiores | AC98: 95% superiores | AD98: Inferior 99,0% | AE98: Superior 99,0% | AG98: Coeficientes | AH98: Erro padrão | AI98: Stat t | AJ98: valor-P | AK98: 95% inferiores | AL98: 95% superiores | AM98: Inferior 99,0% | AN98: Superior 99,0% | BV98: Coeficientes | BW98: Erro padrão | BX98: Stat t | BY98: valor-P | BZ98: 95% inferiores | CA98: 95% superiores | CB98: Inferior 99,0% | CC98: Superior 99,0% | CE98: Coeficientes | CF98: Erro padrão | CG98: Stat t | CH98: valor-P | CI98: 95% inferiores | CJ98: 95% superiores | CK98: Inferior 99,0% | CL98: Superior 99,0%
W99: Interseção | X99: -2.9264197 | Y99: 0.69230414 | Z99: -4.2270724 | AA99: 0.0039022531 | AB99: -4.5634589 | AC99: -1.2893806 | AD99: -5.3491265 | AE99: -0.50371293 | AF99: Interseção | AG99: -1.295981 | AH99: 0.49495358 | AI99: -2.6183889 | AJ99: 0.034489902 | AK99: -2.4663602 | AL99: -0.12560173 | AM99: -3.0280628 | AN99: 0.43610082 | BU99: Interseção | BV99: -0.029227709 | BW99: 0.10002219 | BX99: -0.29221225 | BY99: 0.77859522 | BZ99: -0.26574261 | CA99: 0.20728719 | CB99: -0.3792537 | CC99: 0.32079828 | CD99: Interseção | CE99: -0.03567734 | CF99: 0.084227399 | CG99: -0.42358354 | CH99: 0.68458103 | CI99: -0.23484349 | CJ99: 0.16348881 | CK99: -0.33042972 | CL99: 0.25907504
W100: Lucro (Prejuízo) operacional (EBIT/LAJIR) | X100: 0.020827534 | Y100: 0.015985539 | Z100: 1.3028985 | AA100: 0.23382983 | AB100: -0.016972259 | AC100: 0.058627327 | AD100: -0.035113593 | AE100: 0.076768661 | AF100: Dívida LP (t-1) | AG100: -0.73873792 | AH100: 0.29449971 | AI100: -2.5084504 | AJ100: 0.040488576 | AK100: -1.4351191 | AL100: -0.042356772 | AM100: -1.7693347 | AN100: 0.29185889 | BU100: Despesa de juros, líq | BV100: -0.014157233 | BW100: 0.039620148 | BX100: -0.35732407 | BY100: 0.73137942 | BZ100: -0.107844 | CA100: 0.07952953 | CB100: -0.15280728 | CC100: 0.12449281 | CD100: Despesa com juros | CE100: -0.018619375 | CF100: 0.034174464 | CG100: -0.54483298 | CH100: 0.60278538 | CI100: -0.099429142 | CJ100: 0.062190392 | CK100: -0.13821234 | CL100: 0.10097359
W101: "Causas X": DÍVIDA LP (t-1) e DÍVIDA CP (t-1) | AF101: "Causas X": DÍVIDA LP (t-1) | BU101: "Causas X": Capital Investido (t-1) | CD101: "Causas X": Capital Investido
W102: RESUMO DOS RESULTADOS | AF102: RESUMO DOS RESULTADOS | AH102: MODELO A SER UTILIZADO PARA A PROJEÇÃO | BU102: RESUMO DOS RESULTADOS | CD102: RESUMO DOS RESULTADOS
W104: Estatística de regressão | AF104: Estatística de regressão | BU104: Estatística de regressão | CD104: Estatística de regressão
W105: R múltiplo | X105: 0.78316321 | AF105: R múltiplo | AG105: 0.68802635 | BU105: R múltiplo | BV105: 0.55073408 | CD105: R múltiplo | CE105: 0.55339686
...

Sheet Proj. Imposto de Renda
A1: Ano | B1: 2016 | C1: 2017 | D1: 2018 | E1: 2019 | F1: 2020 | G1: 2021 | H1: 2022 | I1: 2023 | J1: 2024 | K1: 2025 | L1: 2026 | M1: 2027 | N1: 2028 | O1: 2029 | P1: 2030 | Q1: 2031 | R1: 2032 | S1: 2033 | T1: 2034 | W1: Imposto de renda
A2: Receita | B2: 31.353 | C2: 23.646 | D2: 33.684 | E2: 38.621 | F2: 35.93 | G2: 120.319 | H2: 72.058 | I2: 67.307 | J2: 85.999 | W2: "Causas X": ANO, RECEITA, LAJIR, LAIR | AF2: "Causas X": LAIR
A3: LAJIR (Lucro antes do Juros e IR) | B3: 16.399 | C3: 12.666 | D3: 22.903 | E3: 24.961 | F3: 19.171 | G3: 103.23 | H3: 38.323 | I3: 30.123 | J3: 43.628 | W3: RESUMO DOS RESULTADOS | AF3: RESUMO DOS RESULTADOS
A4: LAIR (Lucro antes do IR) | B4: 21.237 | C4: 14.944 | D4: 24.305 | E4: 27.354 | F4: 20.435 | G4: 104.164 | H4: 41.147 | I4: 31.833 | J4: 45.526
A5: Dívida LP | B5: ='Proj. Despesa não operacional'!B7 -> 2.699 | C5: ='Proj. Despesa não operacional'!C7 -> 1.972 | D5: ='Proj. Despesa não operacional'!D7 -> 1.245 | E5: ='Proj. Despesa não operacional'!E7 -> 0.737 | F5: ='Proj. Despesa não operacional'!F7 -> 0.536 | G5: ='Proj. Despesa não operacional'!G7 -> 0.335 | H5: ='Proj. Despesa não operacional'!H7 -> 0.134 | I5: ='Proj. Despesa não operacional'!I7 -> 0 | ... T5: ='Proj. Despesa não operacional'!T7 -> 4.2632191 | W5: Estatística de regressão | AF5: Estatística de regressão
A6: Dívida CP | B6: 0.735 | C6: 0.733 | D6: 0.731 | E6: 0.511 | F6: 0.203 | G6: 0.202 | H6: 0.202 | I6: 0.134 | J6: 0.088 | W6: R múltiplo | X6: 0.78474858 | AF6: R múltiplo | AG6: 0.24422995
A7: Imposto de renda | B7: 6.949 | C7: 2.427 | D7: 1.689 | E7: 2.097 | F7: 1.726 | G7: 4.356 | H7: 3.657 | I7: 3.121 | J7: 10.662 | W7: R-Quadrado | X7: 0.61583033 | AF7: R-Quadrado | AG7: 0.05964827
A8: Alíquota do IR (Sobre o LAIR) | B8: =B7/B4 -> 0.32721194 | C8: =C7/C4 -> 0.16240632 | D8: =D7/D4 -> 0.069491874 | E8: =E7/E4 -> 0.076661549 | F8: =F7/F4 -> 0.084462931 | G8: =G7/G4 -> 0.041818671 | H8: =H7/H4 -> 0.088876467 | I8: =I7/I4 -> 0.098042911 | J8: =J7/J4 -> 0.23419584 | W8: R-quadrado ajustado | X8: 0.23166067 | AF8: R-quadrado ajustado | AG8: -0.074687692
W9: Erro padrão | X9: 2.6049056 | AF9: Erro padrão | AG9: 3.080751
A10: Média ponderada das alíquotas de IR | B10: =SUM(B7:J7)/SUM(B4:J4) -> 0.11084621 | W10: Observações | X10: 9 | AF10: Observações | AG10: 9
A12: {=TRANSPOSE(A1:J8)} -> Ano | B12: Receita | C12: LAJIR (Lucro antes do Juros e IR) | D12: LAIR (Lucro antes do IR) | E12: Dívida LP | F12: Dívida CP | G12: Imposto de renda | H12: Alíquota do IR (Sobre o LAIR) | W12: ANOVA | AF12: ANOVA
A13: 2016 | B13: 31.353 | C13: 16.399 | D13: 21.237 | E13: 2.699 | F13: 0.735 | G13: 6.949 | H13: 0.32721194 | X13: gl | Y13: SQ | Z13: MQ | AA13: F | AB13: F de significação | AG13: gl | AH13: SQ | AI13: MQ | AJ13: F | AK13: F de significação
A14: 2017 | B14: 23.646 | C14: 12.666 | D14: 14.944 | E14: 1.972 | F14: 0.733 | G14: 2.427 | H14: 0.16240632 | W14: Regressão | X14: 4 | Y14: 43.509289 | Z14: 10.877322 | AA14: 1.6030166 | AB14: 0.32936261 | AF14: Regressão | AG14: 1 | AH14: 4.2142351 | AI14: 4.2142351 | AJ14: 0.4440231 | AK14: 0.52653096
A15: 2018 | B15: 33.684 | C15: 22.903 | D15: 24.305 | E15: 1.245 | F15: 0.731 | G15: 1.689 | H15: 0.069491874 | W15: Resíduo | X15: 4 | Y15: 27.142133 | Z15: 6.7855333 | AF15: Resíduo | AG15: 7 | AH15: 66.437187 | AI15: 9.4910267
A16: 2019 | B16: 38.621 | C16: 24.961 | D16: 27.354 | E16: 0.737 | F16: 0.511 | G16: 2.097 | H16: 0.076661549 | W16: Total | X16: 8 | Y16: 70.651422 | AF16: Total | AG16: 8 | AH16: 70.651422
A17: 2020 | B17: 35.93 | C17: 19.171 | D17: 20.435 | E17: 0.536 | F17: 0.203 | G17: 1.726 | H17: 0.084462931
A18: 2021 | B18: 120.319 | C18: 103.23 | D18: 104.164 | E18: 0.335 | F18: 0.202 | G18: 4.356 | H18: 0.041818671 | X18: Coeficientes | Y18: Erro padrão | Z18: Stat t | AA18: valor-P | AB18: 95% inferiores | AC18: 95% superiores | AD18: Inferior 99,0% | AE18: Superior 99,0% | AG18: Coeficientes | AH18: Erro padrão | AI18: Stat t | AJ18: valor-P | AK18: 95% inferiores | AL18: 95% superiores | AM18: Inferior 99,0% | AN18: Superior 99,0%
A19: 2022 | B19: 72.058 | C19: 38.323 | D19: 41.147 | E19: 0.134 | F19: 0.202 | G19: 3.657 | H19: 0.088876467 | W19: Interseção | X19: 3167.348 | Y19: 4164.5092 | Z19: 0.76055734 | AA19: 0.4892857 | AB19: -8395.1831 | AC19: 14729.879 | AD19: -16006.447 | AE19: 22341.143 | AF19: Interseção | AG19: 3.0924637 | AH19: 1.7980954 | AI19: 1.7198552 | AJ19: 0.12914415 | AK19: -1.1593563 | AL19: 7.3442837 | AM19: -3.1999412 | AN19: 9.3848686
A20: 2023 | B20: 67.307 | C20: 30.123 | D20: 31.833 | E20: 0 | F20: 0.134 | G20: 3.121 | H20: 0.098042911 | W20: Ano | X20: -1.5716183 | Y20: 2.0644441 | Z20: -0.76127919 | AA20: 0.48889957 | AB20: -7.3034341 | AC20: 4.1601974 | AD20: -11.076515 | AE20: 7.9332782 | AF20: LAIR (Lucro antes do IR) | AG20: 0.026747123 | AH20: 0.040139716 | AI20: 0.66635058 | AJ20: 0.52653096 | AK20: -0.068168223 | AL20: 0.12166247 | AM20: -0.11372114 | AN20: 0.16721539
A21: 2024 | B21: 85.999 | C21: 43.628 | D21: 45.526 | E21: 30.706 | F21: 0.088 | G21: 10.662 | H21: 0.23419584 | W21: Receita | X21: 0.42553247 | Y21: 0.39378164 | Z21: 1.0806305 | AA21: 0.34066363 | AB21: -0.66778065 | AC21: 1.5188456 | AD21: -1.3874756 | AE21: 2.2385405
W22: LAJIR (Lucro antes do Juros e IR) | X22: -0.35774804 | Y22: 1.6377696 | Z22: -0.21843613 | AA22: 0.83778129 | AB22: -4.9049253 | AC22: 4.1894293 | AD22: -7.8981945 | AE22: 7.1826984
W23: LAIR (Lucro antes do IR) | X23: -0.0078054715 | Y23: 1.9563561 | Z23: -0.003989801 | AA23: 0.99700766 | AB23: -5.4395207 | AC23: 5.4239098 | AD23: -9.0150544 | AE23: 8.9994435
W24: "Causas X": Dívida LP e Dívida CP | AF24: "Causas X": Dívida LP
W25: RESUMO DOS RESULTADOS | AF25: RESUMO DOS RESULTADOS
A26: PROJEÇÃO (ESPERADO)
A27: Ano | B27: 2025 | C27: 2026 | D27: 2027 | E27: 2028 | F27: 2029 | G27: 2030 | H27: 2031 | I27: 2032 | J27: 2033 | K27: 2034 | W27: Estatística de regressão | AF27: Estatística de regressão | AJ27: MODELO A SER UTILIZADO PARA A PROJEÇÃO
A28: Imposto de renda | B28: =$AG$41+($AG$42*K5) -> 9.6824168 | C28: =$AG$41+($AG$42*L5) -> 8.4566592 | D28: =$AG$41+($AG$42*M5) -> 7.4555791 | E28: =$AG$41+($AG$42*N5) -> 6.6379938 | F28: =$AG$41+($AG$42*O5) -> 5.9702692 | G28: =$AG$41+($AG$42*P5) -> 5.4249365 | H28: =$AG$41+($AG$42*Q5) -> 4.9795616 | I28: =$AG$41+($AG$42*R5) -> 4.6158225 | ... K28: =$AG$41+($AG$42*T5) -> 4.0761401 | W28: R múltiplo | X28: 0.84951368 | AF28: R múltiplo | AG28: 0.84951069
W29: R-Quadrado | X29: 0.72167348 | AF29: R-Quadrado | AG29: 0.72166842
W30: R-quadrado ajustado | X30: 0.62889798 | AF30: R-quadrado ajustado | AG30: 0.68190676
W31: Erro padrão | X31: 1.8103482 | AF31: Erro padrão | AG31: 1.676072
W32: Observações | X32: 9 | AF32: Observações | AG32: 9
W34: ANOVA | AF34: ANOVA
X35: gl | Y35: SQ | Z35: MQ | AA35: F | AB35: F de significação | AG35: gl | AH35: SQ | AI35: MQ | AJ35: F | AK35: F de significação
W36: Regressão | X36: 2 | Y36: 50.987258 | Z36: 25.493629 | AA36: 7.7787072 | AB36: 0.021560744 | AF36: Regressão | AG36: 1 | AH36: 50.9869 | AI36: 50.9869 | AJ36: 18.149859 | AK36: 0.0037453651
W37: Resíduo | X37: 6 | Y37: 19.664164 | Z37: 3.2773607 | AF37: Resíduo | AG37: 7 | AH37: 19.664522 | AI37: 2.8092174
W38: Total | X38: 8 | Y38: 70.651422 | AF38: Total | AG38: 8 | AH38: 70.651422
X40: Coeficientes | Y40: Erro padrão | Z40: Stat t | AA40: valor-P | AB40: 95% inferiores | AC40: 95% superiores | AD40: Inferior 99,0% | AE40: Superior 99,0% | AG40: Coeficientes | AH40: Erro padrão | AI40: Stat t | AJ40: valor-P | AK40: 95% inferiores | AL40: 95% superiores | AM40: Inferior 99,0% | AN40: Superior 99,0%
W41: Interseção | X41: 3.0060958 | Y41: 1.2405422 | Z41: 2.4232111 | AA41: 0.051637028 | AB41: -0.029401737 | AC41: 6.0415932 | AD41: -1.5931253 | AE41: 7.6053168 | AF41: Interseção | AG41: 2.995135 | AH41: 0.61359858 | AI41: 4.8812612 | AJ41: 0.0017910361 | AK41: 1.5442049 | AL41: 4.4460651 | AM41: 0.84785697 | AN41: 5.142413
W42: Dívida LP | X42: 0.25332739 | Y42: 0.068202666 | Z42: 3.7143327 | AA42: 0.0099186182 | AB42: 0.08644148 | AC42: 0.4202133 | AD42: 0.00047091642 | AE42: 0.50618387 | AF42: Dívida LP | AG42: 0.25356546 | AH42: 0.059518705 | AI42: 4.2602651 | AJ42: 0.0037453651 | AK42: 0.11282609 | AL42: 0.39430483 | AM42: 0.045280748 | AN42: 0.46185017
W43: Dívida CP | X43: -0.025293543 | Y43: 2.4199417 | Z43: -0.010452129 | AA43: 0.99199943 | AB43: -5.9466777 | AC43: 5.8960906 | AD43: -8.9970534 | AE43: 8.9464663

Sheet DRE - Ajustado 3º TRI 2025
A2: (AFLT3 BZ) - Ajustado
A4: Em Milhões de BRL exceto Por ação | C4: FY 2016 | D4: FY 2017 | E4: FY 2018 | F4: FY 2019 | G4: FY 2020 | H4: FY 2021 | I4: FY 2022 | J4: FY 2023 | K4: FY 2024 | L4: Últ 12M
A5: Término de 12 meses | C5: 12/31/2016 | D5: 12/31/2017 | E5: 12/31/2018 | F5: 12/31/2019 | G5: 12/31/2020 | H5: 12/31/2021 | I5: 12/31/2022 | J5: 12/31/2023 | K5: 12/31/2024 | L5: 09/30/2025
A6: Receita | B6: SALES_REV_TURN | C6: 31.353 | D6: 23.646 | E6: 33.684 | F6: 38.621 | G6: 35.93 | H6: 120.319 | I6: 72.058 | J6: 67.307 | K6: 85.999 | L6: 81.447
A7: + Receita de vendas e serviços | B7: IS_SALES_AND_SERVICES_REVENUES | C7: — | D7: 23.646 | E7: 33.684 | F7: 38.621 | G7: 35.93 | H7: 120.319 | I7: 72.058 | J7: 67.307 | K7: 85.999 | L7: 81.447
A8: - Custo da receita | B8: IS_COGS_TO_FE_AND_PP_AND_G | C8: 14.175 | D8: 10.425 | E8: 10.028 | F8: 13.006 | G8: 12.631 | H8: 13.665 | I8: 27.51 | J8: 32.318 | K8: 38.091 | L8: 26.314
A9: + Custo de bens e serviços | B9: IS_COG_AND_SERVICES_SOLD | C9: — | D9: 10.425 | E9: 10.028 | F9: 13.006 | G9: 12.631 | H9: 13.665 | I9: 27.45 | J9: 32.273 | K9: 38.034 | L9: 26.273
A10: + Depreciação e amortização: | B10: IS_DA_COST_OF_REVENUE_GAAP | C10: — | D10: — | E10: — | F10: — | G10: — | H10: — | I10: 0.06 | J10: 0.045 | K10: 0.057 | L10: 0.041
A11: Lucro bruto | B11: GROSS_PROFIT | C11: 17.178 | D11: 13.221 | E11: 23.656 | F11: 25.615 | G11: 23.299 | H11: 106.654 | I11: 44.548 | J11: 34.989 | K11: 47.908 | L11: 55.133
A12: + Outros lucros operacionais | B12: IS_OTHER_OPER_INC | C12: — | D12: 0 | E12: 0 | F12: 0 | G12: 0 | H12: 0.005 | I12: 0 | J12: 0 | K12: 0.109
A13: - Despesas operacionais | B13: IS_OPERATING_EXPN | C13: 0.779 | D13: 0.555 | E13: 0.753 | F13: 0.654 | G13: 4.128 | H13: 3.429 | I13: 6.225 | J13: 4.866 | K13: 4.389 | L13: 5.036
A14: + Vendas, geral e admin | B14: IS_SGA_EXPENSE | C14: — | D14: 0.555 | E14: 0.753 | F14: 0.654 | G14: 4.202 | H14: 3.365 | I14: 6.112 | J14: 4.713 | K14: 4.253 | L14: 4.9
A15: + Venda e marketing | B15: IS_SELLING_EXPENSES | C15: — | D15: — | E15: 0.074 | F15: 0.095 | G15: — | H15: — | I15: 0.018 | J15: 0.185 | K15: — | L15: 0.067
A16: + Geral e administrativas | B16: IS_GENERAL_AND_ADMINISTRATIVE | C16: — | D16: 0.555 | E16: 0.679 | F16: 0.559 | G16: 4.202 | H16: 3.365 | I16: 6.094 | J16: 4.528 | K16: 4.253 | L16: 4.833
A17: + Pesquisa e desenvolvimento | B17: IS_OPERATING_EXPENSES_RD | C17: — | D17: 0.334 | E17: 0.355 | F17: 0.393 | G17: 0.38 | H17: 0.449 | I17: 0.539 | J17: 0.657 | K17: 0.604
A18: + Depreciação e amortização: | B18: IS_DEPRECIATION_AND_AMORTIZATION | C18: — | D18: — | E18: — | F18: — | G18: — | H18: 0.064 | I18: 0.113 | J18: 0.153 | K18: 0.136 | L18: 0.125
A19: + Outras desp operacionais | B19: IS_OTHER_OPERATING_EXPENSES | C19: — | D19: -0.334 | E19: -0.355 | F19: -0.393 | G19: -0.454 | H19: -0.449 | I19: -0.539 | J19: -0.657 | K19: -0.604 | L19: 0.011
A20: Lucro (Prejuízo) operacional | B20: IS_OPER_INC | C20: 16.399 | D20: 12.666 | E20: 22.903 | F20: 24.961 | G20: 19.171 | H20: 103.23 | I20: 38.323 | J20: 30.123 | K20: 43.628 | L20: 50.097 | M20: LAJIR
A21: - Perdas (lucros) não operacionais | B21: IS_NONOP_INCOME_LOSS | C21: — | D21: -2.278 | E21: -1.402 | F21: -2.393 | G21: -1.264 | H21: -0.934 | I21: -2.824 | J21: -1.71 | K21: -1.063 | L21: 0.73
A22: + Despesa de juros, líq | B22: IS_NET_INTEREST_EXPENSE | C22: -5.26 | D22: -2.429 | E22: -1.491 | F22: -2.349 | G22: -1.403 | H22: -0.938 | I22: -2.908 | J22: -1.434 | K22: -1.64 | L22: -1.101 | M22: Receitas de aplicações financeiras realizadas pela empresa
A23: + Despesa com juros | B23: IS_INT_EXPENSE | C23: 0.192 | D23: 0.157 | E23: 0.121 | F23: 0.086 | G23: 0.053 | H23: 0.037 | I23: 0.025 | J23: 0.014 | K23: 0.105 | L23: 1.313 | M23: Interests expenses -> Despesas com as dívidas adquiridas pela empresa (custo da dívida)
A24: - Lucro com juros | B24: IS_INT_INC | C24: 5.452 | D24: 2.586 | E24: 1.612 | F24: 2.435 | G24: 1.456 | H24: 0.975 | I24: 2.933 | J24: 1.448 | K24: 1.745 | L24: 2.414 | M24: A empresa tem receita de juros/capital investido fora das operações
A25: + Prejuízo (Lucro) câmbio | B25: IS_FOREIGN_EXCH_LOSS | C25: — | D25: 0 | E25: 0 | F25: 0 | G25: 0 | H25: 0 | I25: 0 | J25: 0 | K25: 0.706
A26: + Perda (Lucro) de afiliados | B26: INCOME_LOSS_FROM_AFFILIATES | C26: — | D26: 0 | E26: 0 | F26: 0 | G26: 0 | H26: 0 | I26: 0 | J26: 0 | K26: 0
A27: + Outros Prejuízos (Lucros) não op | B27: IS_OTHER_NON_OPERATING_INC_LOSS | C27: — | D27: 0.151 | E27: 0.089 | F27: -0.044 | G27: 0.139 | H27: 0.004 | I27: 0.084 | J27: -0.276 | K27: -0.129 | L27: 6.483
A28: Lucro (Prejuízo) antes de impostos, ajustado | B28: PRETAX_INC | C28: 21.237 | D28: 14.944 | E28: 24.305 | F28: 27.354 | G28: 20.435 | H28: 104.164 | I28: 41.147 | J28: 31.833 | K28: 44.691 | L28: 49.367
A29: - Lucros(Prejuízos) extraordinários | B29: IS_ABNORMAL_ITEM | C29: 21.386 | D29: 0 | E29: 0 | F29: 0 | G29: 0 | H29: 0 | I29: 0 | J29: 0 | K29: 0 | L29: 0.029
A30: Lucro (Prejuízo) líquido antes de impostos, GAAP | B30: PRETAX_INC | C30: 21.237 | D30: 14.944 | E30: 24.305 | F30: 27.354 | G30: 20.435 | H30: 104.164 | I30: 41.147 | J30: 31.833 | K30: 44.691 | L30: 49.338
A31: - Desp c/imposto renda (Benefício) | B31: IS_INC_TAX_EXP | C31: 6.949 | D31: 2.427 | E31: 1.689 | F31: 2.097 | G31: 1.726 | H31: 4.356 | I31: 3.657 | J31: 3.121 | K31: 10.662 | L31: 14.478 | M31: IMPOSTO DE RENDA
A32: + Imposto de renda atual | B32: IS_CURRENT_INCOME_TAX_BENEFIT | C32: — | D32: 2.014 | E32: 1.735 | F32: 2.199 | G32: 1.859 | H32: 2.033 | I32: 3.099 | J32: 3.074 | K32: 7.947 | L32: -0.489
A33: + Imposto de renda diferido | B33: IS_DEFERRED_INCOME_TAX_BENEFIT | C33: — | D33: 0.413 | E33: -0.046 | F33: -0.102 | G33: -0.133 | H33: 2.323 | I33: 0.558 | J33: 0.047 | K33: 2.715 | L33: 14.967
A34: Lucro (Prejuízo) de op cont | B34: IS_INC_BEF_XO_ITEM | C34: 14.288 | D34: 12.517 | E34: 22.616 | F34: 25.257 | G34: 18.709 | H34: 99.808 | I34: 37.49 | J34: 28.712 | K34: 34.029 | L34: 34.86
A35: - Perdas (ganhos) extraordinários líquidos | B35: XO_GL_NET_OF_TAX | C35: 0 | D35: 0 | E35: 0 | F35: 0 | G35: 0 | H35: 0 | I35: 0 | J35: 0 | K35: 0 | L35: 0
A36: + Operações descontinuadas | B36: IS_DISCONTINUED_OPERATIONS | C36: — | D36: 0 | E36: 0 | F36: 0 | G36: 0 | H36: 0 | I36: 0 | J36: 0 | K36: 0 | L36: 0
A37: + Itens ext e mudanças contábeis | B37: EXTRAORD_ITEMS_ACCOUNTING_CHANGS | C37: — | D37: 0 | E37: 0 | F37: 0 | G37: 0 | H37: 0 | I37: 0 | J37: 0 | K37: 0 | L37: 0
A38: Lucro (Prejuízo) inc MI | B38: NI_INCLUDING_MINORITY_INT_RATIO | C38: 14.288 | D38: 12.517 | E38: 22.616 | F38: 25.257 | G38: 18.709 | H38: 99.808 | I38: 37.49 | J38: 28.712 | K38: 34.029 | L38: 34.86
A39: - Part minoritária | B39: MIN_NONCONTROL_INTEREST_CREDITS | C39: 0 | D39: 0 | E39: 0 | F39: 0 | G39: 0 | H39: 0 | I39: 0 | J39: 0 | K39: 0 | L39: 0
A40: Lucro líquido, GAAP | B40: NET_INCOME | C40: 14.288 | D40: 12.517 | E40: 22.616 | F40: 25.257 | G40: 18.709 | H40: 99.808 | I40: 37.49 | J40: 28.712 | K40: 34.029 | L40: 34.86
A41: - Dividendos em preferred | B41: IS_TOT_CASH_PFD_DVD | C41: 0 | D41: 0 | E41: 0 | F41: 0 | G41: 0 | H41: 0 | I41: 0 | J41: 0 | K41: 0 | L41: 0
A42: - Outros ajustes | B42: OTHER_ADJUSTMENTS | C42: 0 | D42: 0 | E42: 0 | F42: 0 | G42: 0 | H42: 0 | I42: 0 | J42: 0 | K42: 0 | L42: 0
A43: Lucro líquido disp a ações ordinárias, GAAP | B43: EARN_FOR_COMMON | C43: 14.288 | D43: 12.517 | E43: 22.616 | F43: 25.257 | G43: 18.709 | H43: 99.808 | I43: 37.49 | J43: 28.712 | K43: 34.029 | L43: 34.86
A45: Lucro líquido disp aos acionistas, ajst | B45: EARN_FOR_COMMON | C45: 14.288 | D45: 12.517 | E45: 22.616 | F45: 25.257 | G45: 18.709 | H45: 99.808 | I45: 37.49 | J45: 28.712 | K45: 34.029 | L45: 34.87914
A46: Perdas (ganhos) líquidos extraordinários | B46: IS_NET_ABNORMAL_ITEMS | C46: 14.1148 | D46: 0 | E46: 0 | F46: 0 | G46: 0 | H46: 0 | I46: 0 | J46: 0 | K46: 0 | L46: 0.01914
A47: Perdas (ganhos) extraordinários líquidos | B47: XO_GL_NET_OF_TAX | C47: 0 | D47: 0 | E47: 0 | F47: 0 | G47: 0 | H47: 0 | I47: 0 | J47: 0 | K47: 0 | L47: 0
A49: Méd pond de ações básicas | B49: IS_AVG_NUM_SH_FOR_EPS | C49: 63.085 | D49: 33.085 | E49: 63.085 | F49: 63.085 | G49: 63.085 | H49: 63.085 | I49: 63.085 | J49: 63.085 | K49: 63.085 | L49: 63.085
A50: LPA básico, GAAP | B50: IS_EPS | C50: 0.2265 | D50: 0.3783 | E50: 0.36 | F50: 0.4004 | G50: 0.3 | H50: 1.5821 | I50: 0.5943 | J50: 0.4551 | K50: 0.54 | L50: 0.552592
A51: LPA básico de op cont, GAAP | B51: IS_EARN_BEF_XO_ITEMS_PER_SH | C51: 0.2265 | D51: 0.3783 | E51: 0.36 | F51: 0.4004 | G51: 0.3 | H51: 1.5821 | I51: 0.5943 | J51: 0.4551 | K51: 0.54 | L51: 0.552592
... A57: Lucro por ação diluído de op cont, ajustado | B57: IS_DIL_EPS_CONT_OPS | C57: 0.4502 | D57: 0.3783 | E57: 0.36 | F57: 0.4004 | G57: 0.3 | H57: 1.5821 | I57: 0.5943 | J57: 0.4551 | K57: 0.54 | L57: 0.552896
A59: Itens de referência
A60: Normas contábeis | B60: ACCOUNTING_STANDARD | C60: IAS/IFRS | D60: IAS/IFRS | E60: IAS/IFRS | F60: IAS/IFRS | G60: IAS/IFRS | H60: IAS/IFRS | I60: IAS/IFRS | J60: IAS/IFRS | K60: IAS/IFRS
A61: EBITDA | B61: EBITDA | C61: — | D61: 12.666 | E61: 22.903 | F61: 24.961 | G61: 19.302 | H61: 103.307 | I61: 38.496 | J61: 30.321 | K61: 43.821
A62: Margem EBITDA (Últ12M) | B62: EBITDA_MARGIN | C62: — | D62: 53.5651 | E62: 67.9937 | F62: 64.6306 | G62: 53.7211 | H62: 85.8609 | I62: 53.4236 | J62: 45.0488 | K62: 50.9552
A63: EBITA | B63: EBITA | C63: — | D63: 12.666 | E63: 22.903 | F63: 24.961 | G63: — | H63: — | I63: — | J63: — | K63: —
A64: EBIT | B64: EBIT | C64: 16.399 | D64: 12.666 | E64: 22.903 | F64: 24.961 | G64: 19.171 | H64: 103.23 | I64: 38.323 | J64: 30.123 | K64: 43.628 | L64: 50.097
A65: Margem bruta | B65: GROSS_MARGIN | C65: 54.789 | D65: 55.9122 | E65: 70.2292 | F65: 66.324 | G65: 64.8455 | H65: 88.6427 | I65: 61.8224 | J65: 51.9842 | K65: 55.7076 | L65: 67.691873
A66: Margem operacional | B66: OPER_MARGIN | C66: 52.3044 | D66: 53.5651 | E66: 67.9937 | F66: 64.6306 | G66: 53.3565 | H66: 85.7969 | I66: 53.1835 | J66: 44.7546 | K66: 50.7308 | L66: 61.508711
A67: Margem de lucro | B67: PROF_MARGIN | C67: 45.5714 | D67: 52.935 | E67: 67.1417 | F67: 65.3971 | G67: 52.0707 | H67: 82.9528 | I67: 52.0275 | J67: 42.6583 | K67: 39.5691 | L67: 42.82434
A68: Dividendos por ação | B68: EQY_DPS | C68: — | D68: 0.1452 | E68: — | F68: 0.2947 | G68: 0.1226 | H68: 0.2362 | I68: 0.2362 | J68: 0.45 | K68: 0.6692
A69: Dividendos pagos em caixa | B69: IS_TOT_CASH_COM_DVD | C69: 6.074 | D69: 4.803 | E69: 4.803 | F69: 18.592 | G69: 7.735 | H69: 14.903 | I69: 14.903 | J69: 28.712 | K69: 42.215
A70: Despesas com pessoal | B70: IS_PERSONNEL_EXP | C70: — | D70: — | E70: — | F70: — | G70: — | H70: 2.948 | I70: 3.296 | J70: 2.399 | K70: 2.7 | L70: 4.689
A71: Despesas depreciação | B71: IS_DEPR_EXP | C71: 0 | D71: 0 | E71: 0 | F71: 0 | G71: — | H71: — | I71: — | J71: — | K71: —
A72: Fonte: Bloomberg | C72: Clique botão direito p/exibir a transp de dados (não suportado p/tds valores)

Sheet Fluxo de caixa 3º TRI 2025
A2: (AFLT3 BZ) - Padronizado
A4: Em Milhões de BRL exceto Por ação | C4: FY 2016 | D4: FY 2017 | E4: FY 2018 | F4: FY 2019 | G4: FY 2020 | H4: FY 2021 | I4: FY 2022 | J4: FY 2023 | K4: FY 2024 | L4: Últ 12M
A5: Término de 12 meses | C5: 12/31/2016 | D5: 12/31/2017 | E5: 12/31/2018 | F5: 12/31/2019 | G5: 12/31/2020 | H5: 12/31/2021 | I5: 12/31/2022 | J5: 12/31/2023 | K5: 12/31/2024 | L5: 09/30/2025
A6: Caixa de atividades operacionais
A7: + Lucro líquido | B7: CF_NET_INC | C7: 14.288 | D7: 12.517 | E7: 22.616 | F7: 25.257 | G7: 18.709 | H7: 99.808 | I7: 37.49 | J7: 28.712 | K7: 34.029 | L7: 34.861
A8: + Depreciação e amortização: | B8: CF_DEPR_AMORT | C8: — | D8: 0 | E8: 0 | F8: 0 | G8: 0.131 | H8: 0.077 | I8: 0.173 | J8: 0.198 | K8: 0.193
A9: + Itens não em dinheiro | B9: NON_CASH_ITEMS_DETAILED | C9: -15.652 | D9: 8.802 | E9: 2.902 | F9: 5.591 | G9: -0.48 | H9: -76.755 | I9: -17.997 | J9: -4.556 | K9: -44.172 | L9: -8.013
A10: + Outros ajustes não caixa | B10: OTHER_NON_CASH_ADJ_LESS_DETAILED | C10: -15.652 | D10: 8.802 | E10: 2.902 | F10: 5.591 | G10: -0.48 | H10: -76.755 | I10: -17.997 | J10: -4.556 | K10: -44.172 | L10: -8.013
A11: + Var capital de giro não em caixa | B11: CF_CHNG_NON_CASH_WORK_CAP | C11: -1.811 | D11: -0.942 | E11: -1.134 | F11: -2.487 | G11: 8.188 | H11: 4.397 | I11: 1.037 | J11: -4.753 | K11: 21.368 | L11: -3.088 | M11: Negativo: Liberação da necessidade de dinheiro da operação / Positivo: A operação precisa de mais dinheiro para se manter ativa
A12: + Aum (red) em contas a rec | B12: CF_ACCT_RCV_UNBILLED_REV | C12: -0.047 | D12: 0.707 | E12: 0.102 | F12: -1.377 | G12: 0.616 | H12: -2.274 | I12: 0.024 | J12: -2.849 | K12: 2.23 | L12: -17.32
A13: + Aum (red) em contas a pg | B13: CF_CHANGE_IN_ACCOUNTS_PAYABLE | C13: -0.452 | D13: -0.93 | E13: 0.264 | F13: 1.526 | G13: 0.701 | H13: 3.71 | I13: -0.996 | J13: -0.983 | K13: 1.186 | L13: -2.833
A14: + Aum (red) em outros | B14: INC_DEC_IN_OT_OP_AST_LIAB_DETAIL | C14: -1.312 | D14: -0.719 | E14: -1.5 | F14: -2.636 | G14: 6.871 | H14: 2.961 | I14: 2.009 | J14: -0.921 | K14: 17.952 | L14: 17.065
A15: + Caixa líquido de op desc | B15: CF_NET_CASH_DISCONT_OPS_OPER | C15: — | D15: — | E15: — | F15: — | G15: — | H15: 0 | I15: 0 | J15: 0 | K15: 0
A16: Caixa de atividades operacionais | B16: CF_CASH_FROM_OPER | C16: -3.175 | D16: 20.377 | E16: 24.384 | F16: 28.361 | G16: 26.548 | H16: 27.527 | I16: 20.703 | J16: 19.601 | K16: 11.418 | L16: 23.872
A18: Cash de atividades de investimentos
A19: + Mudança em fixos e intangíveis | B19: FIXED_INTANG_ASST_CHANGE | C19: 0 | D19: 0 | E19: 0 | F19: -0.442 | G19: -1.1 | H19: -1.248 | I19: -1.911 | J19: -0.375 | K19: -1.434 | L19: -1.449
A20: + Vnd de fixos e intang | B20: DISPOSAL_OF_FIXED_INTANG | C20: 0 | D20: 0 | E20: 0 | F20: 0 | G20: 0 | H20: 0 | I20: 0 | J20: 0 | K20: 0 | L20: 0.111
A21: + Redução de ativos imobilizados | B21: CF_DISPOSAL_OF_FIXED_PROD_ASSETS | C21: — | D21: — | E21: 0 | F21: 0 | G21: 0 | H21: 0 | I21: 0 | J21: 0 | K21: 0
A22: + Venda de ativos intangíveis | B22: CF_DISPOSAL_OF_INTANGIBLE_ASSETS | C22: — | D22: — | E22: 0 | F22: 0 | G22: 0 | H22: 0 | I22: 0 | J22: 0 | K22: 0
A23: + Aquis de fixos e intang | B23: ACQUIS_OF_FIXED_INTANG | C23: 0 | D23: 0 | E23: 0 | F23: -0.442 | G23: -1.1 | H23: -1.248 | I23: -1.911 | J23: -0.375 | K23: -1.434
A24: + Aquisição de ativos imobilizados | B24: CF_PURCHASE_OF_FIXED_PROD_ASSETS | C24: — | D24: — | E24: 0 | F24: -0.093 | G24: 0 | H24: — | I24: 0 | J24: 0 | K24: -1.434
A25: + Aquis de ativos intangíveis | B25: CF_ACQUISITION_OF_INTANG_ASSETS | C25: — | D25: — | E25: 0 | F25: -0.349 | G25: -1.1 | H25: — | I25: -1.911 | J25: -0.375 | K25: 0
A26: + Var líq em investimentos LP | B26: NET_CHG_IN_LT_INVEST_DETAILED | C26: -5.454 | D26: 43.532 | E26: 0 | F26: 0 | G26: 0 | H26: 0 | I26: 0 | J26: 0 | K26: 0 | L26: 0
A27: + Red em investimento LP | B27: CF_DECR_INVEST | C27: 0 | D27: — | E27: 0 | F27: 0 | G27: 0 | H27: 0 | I27: 0 | J27: 0 | K27: 0 | L27: 0
A28: + Aum em investimento LP | B28: CF_INCR_INVEST | C28: -5.454 | D28: — | E28: 0 | F28: 0 | G28: 0 | H28: 0 | I28: 0 | J28: 0 | K28: 0 | L28: 0
A29: + Caixa líquido da aquis e div | B29: CF_NT_CSH_RCVD_PD_FOR_ACQUIS_DIV | C29: — | D29: 0 | E29: 0 | F29: 0 | G29: 0 | H29: 0 | I29: 0 | J29: 0 | K29: 0 | L29: 0
A30: + Caixa de alienações | B30: CF_CASH_FOR_DIVESTITURES | C30: — | D30: 0 | E30: 0 | F30: 0 | G30: 0 | H30: 0 | I30: 0 | J30: 0 | K30: 0 | L30: 0
A31: + Caixa da aquis de subs | B31: CF_CASH_FOR_ACQUIS_SUBSIDIARIES | C31: — | D31: 0 | E31: 0 | F31: 0 | G31: 0 | H31: 0 | I31: 0 | J31: 0 | K31: 0 | L31: 0
A32: + Caixa de JVs | B32: CF_CASH_FOR_JOINT_VENTURES_ASSOC | C32: — | D32: 0 | E32: 0 | F32: 0 | G32: 0 | H32: 0 | I32: 0 | J32: 0 | K32: 0 | L32: 0
A33: + Outras atividades de investimentos | B33: OTHER_INVESTING_ACT_DETAILED | C33: 21.754 | D33: -0.512 | E33: -0.014 | F33: 0 | G33: 0 | H33: 0 | I33: 0 | J33: 0 | K33: 0 | L33: 0
A34: + Caixa líquido de op desc | B34: CF_NET_CASH_DISCONTINUED_OPS_INV | C34: — | D34: — | E34: 0 | F34: 0 | G34: 0 | H34: 0 | I34: 0 | J34: 0 | K34: 0 | L34: 0
A35: Cash de atividades de investimentos | B35: CF_CASH_FROM_INV_ACT | C35: 16.3 | D35: 43.02 | E35: -0.014 | F35: -0.442 | G35: -1.1 | H35: -1.248 | I35: -1.911 | J35: -0.375 | K35: -1.434 | L35: -1.448
A37: Caixa de atividades financeiras
A38: + Dividendos pagos | B38: CF_DVD_PAID | C38: -19.48 | D38: -13.774 | E38: -11.376 | F38: -6.658 | G38: -45.477 | H38: -39.668 | I38: -14.879 | J38: -37.42 | K38: -35.465 | L38: -35.473
A39: + Caixa de (reembolso) dívida | B39: PROC_FR_REPAYMNTS_BOR_DETAILED | C39: -0.602 | D39: -0.729 | E39: -0.727 | F39: -0.727 | G39: -0.508 | H39: -0.201 | I39: -0.201 | J39: -0.201 | K39: 29.866 | L39: 30
A40: + Caixa de (reembolso) dívida CP | B40: CF_NET_CHG_ST_DEBT_CPTL_LEAS | C40: — | D40: — | E40: — | F40: — | G40: 0 | H40: — | I40: — | J40: — | K40: —
A41: + Caixa de dívida LP | B41: CF_LT_DEBT_CAP_LEAS_PROCEEDS | C41: — | D41: — | E41: — | F41: — | G41: 0 | H41: — | I41: — | J41: — | K41: —
A42: + Reembolso de dívida LP | B42: CF_LT_DEBT_CAP_LEAS_PAYMENT | C42: — | D42: — | E42: — | F42: — | G42: -0.508 | H42: — | I42: — | J42: — | K42: —
A43: + Caixa (recompra) de capital | B43: PROC_FR_REPURCH_EQTY_DETAILED | C43: 0 | D43: 0 | E43: 0 | F43: 0 | G43: 0 | H43: 0 | I43: 0 | J43: 0 | K43: 0 | L43: 0
A44: + Aumento no capital social | B44: CF_INCR_CAP_STOCK | C44: 0 | D44: 0 | E44: 0 | F44: 0 | G44: 0 | H44: 0 | I44: 0 | J44: 0 | K44: 0 | L44: 0
A45: + Redução no capital social | B45: CF_DECR_CAP_STOCK | C45: 0 | D45: 0 | E45: 0 | F45: 0 | G45: 0 | H45: 0 | I45: 0 | J45: 0 | K45: 0 | L45: 0
A46: + Outras atividades financeiras | B46: OTHER_FIN_AND_DEC_CAP | C46: 0 | D46: -30 | E46: 0 | F46: 0 | G46: 0 | H46: 0 | I46: 0 | J46: 0 | K46: 0 | L46: 0
A47: + Caixa líquido de op desc | B47: CF_NET_CASH_DISCONTINUED_OPS_FIN | C47: — | D47: — | E47: 0 | F47: 0 | G47: 0 | H47: 0 | I47: 0 | J47: 0 | K47: 0 | L47: 0
A48: Caixa de atividades financeiras | B48: CFF_ACTIVITIES_DETAILED | C48: -20.082 | D48: -44.503 | E48: -12.103 | F48: -7.385 | G48: -45.985 | H48: -39.869 | I48: -15.08 | J48: -37.621 | K48: -5.599 | L48: -5.473
A50: Effect of Foreign Exchange Rates | B50: CF_EFFECT_FOREIGN_EXCHANGES | C50: — | D50: 0 | E50: 0 | F50: 0 | G50: 0 | H50: 0 | I50: 0 | J50: 0 | K50: 0 | L50: 0
A52: Var. líquidas no caixa | B52: CF_NET_CHNG_CASH | C52: -6.957 | D52: 18.894 | E52: 12.267 | F52: 20.534 | G52: -20.537 | H52: -13.59 | I52: 3.712 | J52: -18.395 | K52: 4.385 | L52: 16.951
A54: Impostos pagos em cash | B54: CF_CASH_PAID_FOR_TAX | C54: 1.874 | D54: 1.475 | E54: -1.689 | F54: -2.097 | G54: 0.402 | H54: 0.336 | I54: 1.567 | J54: 0.393 | K54: 12.309 | L54: 8.493
A55: Juros pagos | B55: CF_ACT_CASH_PAID_FOR_INT_DEBT | C55: 0.192 | D55: 0.157 | E55: 0.123 | F55: 0.087 | G55: 0.054 | H55: 0.038 | I55: 0.025 | J55: 0.015 | K55: 0.002 | L55: 0
A57: Itens de referência
A58: EBITDA | B58: EBITDA | C58: — | D58: 12.666 | E58: 22.903 | F58: 24.961 | G58: 19.302 | H58: 103.307 | I58: 38.496 | J58: 30.321 | K58: 43.821
A59: Margem EBITDA últimos 12M | B59: EBITDA_MARGIN | C59: — | D59: 53.5651 | E59: 67.9937 | F59: 64.6306 | G59: 53.7211 | H59: 85.8609 | I59: 53.4236 | J59: 45.0488 | K59: 50.9552
A60: Juros recebidos | B60: CF_INTEREST_RECEIVED | C60: — | D60: — | E60: — | F60: — | G60: — | H60: 0.975 | I60: 2.933 | J60: 1.448 | K60: 1.745
A61: Fluxo de caixa livre | B61: CF_FREE_CASH_FLOW | C61: -3.175 | D61: 20.377 | E61: 24.384 | F61: 28.268 | G61: 26.548 | H61: 26.279 | I61: 20.703 | J61: 19.601 | K61: 9.984 | L61: 22.216
A62: Fluxo de caixa livre a Empresa | B62: CF_FREE_CASH_FLOW_FIRM | C62: -3.0458 | D62: 20.5085 | E62: 24.4966 | F62: 28.3474 | G62: 26.5965 | H62: 26.3145 | I62: 20.7258 | J62: 19.6136 | K62: 10.0639 | L62: 23.119781
A63: Fluxo caixa livre p/ ação | B63: FREE_CASH_FLOW_EQUITY | C63: -3.777 | D63: 19.648 | E63: 23.657 | F63: 27.541 | G63: 26.04 | H63: 26.078 | I63: 20.502 | J63: 19.4 | K63: 39.85 | L63: 52.438
A64: Fluxo de caixa livre/Ação básica | B64: FREE_CASH_FLOW_PER_SH | C64: -0.0503 | D64: 0.6159 | E64: 0.3865 | F64: 0.4481 | G64: 0.4208 | H64: 0.4166 | I64: 0.3282 | J64: 0.3107 | K64: 0.1583 | L64: 0.35215978
A65: Preço/Fluxo de caixa livre | B65: PX_TO_FREE_CASH_FLOW | C65: — | D65: 8.0695 | E65: 14.3587 | F65: 24.727 | G65: 23.4299 | H65: 21.2932 | I65: 28.247 | J65: 27.6466 | K65: 45.1781 | L65: 20.502056
A66: Fluxo de caixa/Lucro líquido | B66: CASH_FLOW_TO_NET_INC | C66: -0.2222 | D66: 1.6279 | E66: 1.0782 | F66: 1.1229 | G66: 1.419 | H66: 0.2758 | I66: 0.5522 | J66: 0.6827 | K66: 0.3355 | L66: 1.0049986
A67: Fonte: Bloomberg | C67: Clique botão direito p/exibir a transp de dados (não suportado p/tds valores)

Sheet Bal patrim - Padronizado
A2: (AFLT3 BZ) - Padronizado
A4: Em Milhões de BRL exceto Por ação | C4: FY 2015 | D4: FY 2016 | E4: FY 2017 | F4: FY 2018 | G4: FY 2019 | H4: FY 2020 | I4: FY 2021 | J4: FY 2022 | K4: FY 2023 | L4: FY 2024
A5: Término de 12 meses | C5: 12/31/2015 | D5: 12/31/2016 | E5: 12/31/2017 | F5: 12/31/2018 | G5: 12/31/2019 | H5: 12/31/2020 | I5: 12/31/2021 | J5: 12/31/2022 | K5: 12/31/2023 | L5: 12/31/2024
A6: Ativo total
A7: + Caixa, equivalentes a caixa e STI | B7: CASH_CASH_EQTY_STI_DETAILED | C7: 42.264 | D7: 35.774 | E7: 18.945 | F7: 31.212 | G7: 51.746 | H7: 31.209 | I7: 17.619 | J7: 21.331 | K7: 2.936 | L7: 7.321 | M7: FINANCEIRO
A8: + Caixa e bancos | B8: BS_CASH_NEAR_CASH_ITEM | C8: 42.264 | D8: 35.307 | E8: 18.945 | F8: 31.212 | G8: 51.746 | H8: 31.209 | I8: 17.619 | J8: 21.331 | K8: 2.936 | L8: 7.321
A9: + Investimentos CP | B9: BS_MKT_SEC_OTHER_ST_INVEST | C9: 0 | D9: 0.467 | E9: 0 | F9: 0 | G9: 0 | H9: 0 | I9: 0 | J9: 0 | K9: 0 | L9: 0
A10: + Accounts & Notes Receiv | B10: BS_ACCT_NOTE_RCV | C10: 4.186 | D10: 4.47 | E10: 3.647 | F10: 3.424 | G10: 4.706 | H10: 4.14 | I10: 6.467 | J10: 6.446 | K10: 9.563 | L10: 7.345 | M10: OPERACIONAL
A11: + Contas a receber, líquido | B11: BS_ACCTS_REC_EXCL_NOTES_REC | C11: 4.186 | D11: 4.47 | E11: 3.647 | F11: 3.424 | G11: 4.706 | H11: 4.14 | I11: 6.467 | J11: 6.446 | K11: 9.563 | L11: 7.345
A12: + Notas a receber, líq | B12: NOTES_RECEIVABLE | C12: — | D12: — | E12: — | F12: 0 | G12: 0 | H12: 0 | I12: 0 | J12: 0 | K12: 0 | L12: 0
A13: + Estoques | B13: BS_INVENTORIES | C13: 0 | D13: 0 | E13: 0 | F13: 0 | G13: 0 | H13: 0 | I13: 0 | J13: 0 | K13: 0 | L13: 0 | M13: OPERACIONAL
A14: + Matéria prima | B14: INVTRY_RAW_MATERIALS | C14: — | D14: — | E14: — | F14: 0 | G14: 0 | H14: 0 | I14: 0 | J14: 0 | K14: 0 | L14: 0
A15: + Trabalhos em processo | B15: INVTRY_IN_PROGRESS | C15: — | D15: — | E15: — | F15: 0 | G15: 0 | H15: 0 | I15: 0 | J15: 0 | K15: 0 | L15: 0
A16: + Prods acabados | B16: INVTRY_FINISHED_GOODS | C16: — | D16: — | E16: — | F16: 0 | G16: 0 | H16: 0 | I16: 0 | J16: 0 | K16: 0 | L16: 0
A17: + Outros estoques | B17: BS_OTHER_INV | C17: — | D17: — | E17: — | F17: 0 | G17: 0 | H17: 0 | I17: 0 | J17: 0 | K17: 0 | L17: 0
A18: + Outros ativos CP | B18: OTHER_CURRENT_ASSETS_DETAILED | C18: 27.554 | D18: 28.637 | E18: 30.494 | F18: 17.715 | G18: 18.904 | H18: 19.748 | I18: 36.748 | J18: 40.851 | K18: 42.612 | L18: 55.775 | M18: OPERACIONAL | N18: AUMENTO SIGNIFICATIVO DA CONTA AO LONGO DOS ANOS
A19: + Desp paGás antecipadamente | B19: BS_PREPAY | C19: — | D19: — | E19: 0.004 | F19: — | G19: 0.183 | H19: 0.142 | I19: 0.198 | J19: 0.22 | K19: 0.223 | L19: 0.054
A20: + Derivativos e ativos de hedging | B20: BS_DERIV_HEDGING_ASST_ST | C20: — | D20: — | E20: — | F20: — | G20: — | H20: — | I20: — | J20: — | K20: — | L20: 0
A21: + Impostos a receber | B21: BS_TAXES_RECEIVABLE_SHORT_TERM | C21: — | D21: — | E21: 0.233 | F21: 0.011 | G21: 0.06 | H21: 0.002 | I21: 0.002 | J21: 0.015 | K21: 0.038 | L21: 3.658
A22: + Ativos CP div | B22: BS_OTHER_CUR_ASSET_LESS_PREPAY | C22: — | D22: — | E22: 30.257 | F22: 17.704 | G22: 18.661 | H22: 19.604 | I22: 36.548 | J22: 40.616 | K22: 42.351 | L22: 52.063 | M22: AUMENTO SIGNIFICATIVO DA CONTA AO LONGO DOS ANOS
A23: Ativo circulante | B23: BS_CUR_ASSET_REPORT | C23: 74.004 | D23: 68.881 | E23: 53.086 | F23: 52.351 | G23: 75.356 | H23: 55.097 | I23: 60.834 | J23: 68.628 | K23: 55.111 | L23: 70.441
A24: + Property, Plant & Equip, Net | B24: BS_NET_FIX_ASSET | C24: 0 | D24: — | E24: 0 | F24: 0 | G24: 0.093 | H24: 1.129 | I24: 1.785 | J24: 3.611 | K24: 3.856 | L24: 3.939
A25: + Investimentos LP e recebíveis | B25: BS_LT_INVEST | C25: 0.237 | D25: 5.224 | E25: 0 | F25: 0 | G25: 0 | H25: 0 | I25: 0 | J25: 0 | K25: 0 | L25: 0
A26: + Ativos negociáveis LP | B26: BS_LT_MARKETABLE_SECURITIES | C26: 0.237 | D26: 5.224 | E26: — | F26: — | G26: — | H26: — | I26: — | J26: — | K26: — | L26: —
A27: + Outros ativos LP | B27: BS_OTHER_ASSETS_DEF_CHRG_OTHER | C27: 15.133 | D27: 13.511 | E27: 1.705 | F27: 153.849 | G27: 150.206 | H27: 151.557 | I27: 213.326 | J27: 228.48 | K27: 230.819 | L27: 268.377 | M27: AUMENTO SIGNIFICATIVO DA CONTA AO LONGO DOS ANOS
A28: + Total de ativos intangíveis | B28: BS_DISCLOSED_INTANGIBLES | C28: 0 | D28: 0 | E28: 0 | F28: 0 | G28: 0.349 | H28: 0.282 | I28: 0.797 | J28: 0.677 | K28: 0.597 | L28: 1.209
A29: + Goodwill | B29: BS_GOODWILL | C29: 0 | D29: 0 | E29: 0 | F29: 0 | G29: 0 | H29: 0 | I29: 0 | J29: 0 | K29: 0 | L29: 0
A30: + Outros ativos intangíveis | B30: OTHER_INTANGIBLE_ASSETS_DETAILED | C30: 0 | D30: 0 | E30: 0 | F30: 0 | G30: 0.349 | H30: 0.282 | I30: 0.797 | J30: 0.677 | K30: 0.597 | L30: 1.209
A31: + Derivativos e ativos de hedging | B31: BS_DERIV_HEDGING_ASST_LT | C31: — | D31: — | E31: — | F31: — | G31: — | H31: — | I31: — | J31: — | K31: — | L31: 0.359
A32: + Investimentos em afiliadas | B32: BS_INVEST_IN_ASSOC_CO | C32: 0 | D32: 0 | E32: 0 | F32: 0 | G32: 0 | H32: 0 | I32: 0 | J32: 0 | K32: 0 | L32: 0
A33: + Ativos LP div | B33: OTHER_NONCURRENT_ASSETS_DETAILED | C33: 15.133 | D33: 13.511 | E33: 1.705 | F33: 153.849 | G33: 149.857 | H33: 151.275 | I33: 212.529 | J33: 227.803 | K33: 230.222 | L33: 266.809 | M33: AUMENTO SIGNIFICATIVO DA CONTA AO LONGO DOS ANOS
A34: Total Noncurrent Assets | B34: BS_TOT_NON_CUR_ASSET | C34: 15.37 | D34: 18.735 | E34: 1.705 | F34: 153.849 | G34: 150.299 | H34: 152.686 | I34: 215.111 | J34: 232.091 | K34: 234.675 | L34: 272.316
A35: Ativo total | B35: BS_TOT_ASSET | C35: 89.374 | D35: 87.616 | E35: 54.791 | F35: 206.2 | G35: 225.655 | H35: 207.783 | I35: 275.945 | J35: 300.719 | K35: 289.786 | L35: 342.757
A37: Passivo e patrimônio líquido
A38: + A pagar e acúmulos | B38: ACCT_PAYABLE_ACCRUALS_DETAILED | C38: 2.011 | D38: 1.559 | E38: 1.499 | F38: 1.777 | G38: 3.323 | H38: 4.772 | I38: 8.944 | J38: 18.111 | K38: 14.386 | L38: 13.035 | M38: OPERACIONAL
A39: + Contas a pagar | B39: BS_ACCT_PAYABLE | C39: 2.011 | D39: 1.559 | E39: 0.629 | F39: 0.893 | G39: 2.419 | H39: 3.124 | I39: 6.867 | J39: 5.929 | K39: 5.004 | L39: 6.244
A40: + Impostos acumulados | B40: BS_TAXES_PAYABLE | C40: — | D40: — | E40: 0.764 | F40: 0.766 | G40: 0.759 | H40: 0.841 | I40: 1.299 | J40: 1.533 | K40: 1.26 | L40: 0.982
A41: + Juros e dividendos a pagar | B41: INTEREST_DIVIDENDS_PAYABLE | C41: — | D41: — | E41: 0.106 | F41: 0.118 | G41: 0.125 | H41: 0.244 | I41: 0.325 | J41: 9.721 | K41: 7.596 | L41: 5.144 | M41: JUROS A PAGAR
A42: + Outros a pagar e acúmulos | B42: BS_ACCRUAL | C42: — | D42: — | E42: — | F42: — | G42: 0.02 | H42: 0.563 | I42: 0.453 | J42: 0.928 | K42: 0.526 | L42: 0.665
A43: + Dívida CP | B43: BS_ST_BORROW | C43: 0.61 | D43: 0.735 | E43: 0.733 | F43: 0.731 | G43: 0.511 | H43: 0.203 | I43: 0.202 | J43: 0.202 | K43: 0.134 | L43: 0.088 | M43: FINANCEIRO
A44: + Tomada de empréstimos CP | B44: SHORT_TERM_DEBT_DETAILED | C44: 0.61 | D44: 0.735 | E44: 0.733 | F44: 0.731 | G44: 0.511 | H44: 0.203 | I44: 0.202 | J44: 0.202 | K44: 0.134 | L44: 0.088
A45: + Passivos de lease CP | B45: ST_CAPITALIZED_LEASE_LIABILITIES | C45: 0 | D45: 0 | E45: 0 | F45: 0 | G45: 0 | H45: 0 | I45: 0 | J45: 0 | K45: 0 | L45: 0
A46: + Leases financeiros CP | B46: ST_CAPITAL_LEASE_OBLIGATIONS | C46: 0 | D46: 0 | E46: 0 | F46: 0 | G46: 0 | H46: 0 | I46: 0 | J46: 0 | K46: 0 | L46: 0
A47: + Outros passivos de curto prazo | B47: OTHER_CURRENT_LIABS_SUB_DETAILED | C47: 4.444 | D47: 1.666 | E47: 0.227 | F47: 0.148 | G47: 0.332 | H47: 1.989 | I47: 1.241 | J47: 2.251 | K47: 2.2 | L47: 4.87 | M47: OPERACIONAL | N47: AUMENTO SIGNIFICATIVO DA CONTA AO LONGO DOS ANOS
A48: + Deferred Revenue | B48: ST_DEFERRED_REVENUE | C48: — | D48: — | E48: 0 | F48: 0 | G48: 0 | H48: 0 | I48: 0 | J48: 0 | K48: 0 | L48: —
A49: + Derivativos e hedging | B49: BS_DERIV_HEDGING_LIAB_ST | C49: — | D49: — | E49: — | F49: — | G49: — | H49: — | I49: — | J49: — | K49: — | L49: 0.088
A50: + Passivos CP div | B50: OTHER_CURRENT_LIABS_DETAILED | C50: 4.444 | D50: 1.666 | E50: 0.227 | F50: 0.148 | G50: 0.332 | H50: 1.989 | I50: 1.241 | J50: 2.251 | K50: 2.2 | L50: 4.782 | M50: AUMENTO SIGNIFICATIVO DA CONTA AO LONGO DOS ANOS
A51: Passivo circulante | B51: BS_CUR_LIAB | C51: 7.065 | D51: 3.96 | E51: 2.459 | F51: 2.656 | G51: 4.166 | H51: 6.964 | I51: 10.387 | J51: 20.564 | K51: 16.72 | L51: 17.993
A52: + Dívida LP | B52: BS_LT_BORROW | C52: 3.426 | D52: 2.699 | E52: 1.972 | F52: 1.245 | G52: 0.737 | H52: 0.536 | I52: 0.335 | J52: 0.134 | K52: 0 | L52: 30.706 | M52: FINANCEIRO
A53: + Empréstimos LP | B53: LONG_TERM_BORROWINGS_DETAILED | C53: 3.426 | D53: 2.699 | E53: 1.972 | F53: 1.245 | G53: 0.737 | H53: 0.536 | I53: 0.335 | J53: 0.134 | K53: 0 | L53: 30.706
A54: + Passivos de lease LP | B54: LT_CAPITALIZED_LEASE_LIABILITIES | C54: 0 | D54: 0 | E54: 0 | F54: 0 | G54: 0 | H54: 0 | I54: 0 | J54: 0 | K54: 0 | L54: 0
A55: + Leases financeiros LP | B55: LT_CAPITAL_LEASE_OBLIGATIONS | C55: 0 | D55: 0 | E55: 0 | F55: 0 | G55: 0 | H55: 0 | I55: 0 | J55: 0 | K55: 0 | L55: 0
A56: + Outros passivos LP | B56: OTHER_NONCUR_LIABS_SUB_DETAILED | C56: 0.465 | D56: 4.751 | E56: 5.425 | F56: 6.545 | G56: 6.406 | H56: 12.824 | I56: 17.705 | J56: 19.289 | K56: 18.917 | L56: 41.146 | M56: AUMENTO SIGNIFICATIVO DA CONTA AO LONGO DOS ANOS
A57: + Passivos acumulados | B57: BS_ACCRUED_LIABILITIES | C57: — | D57: — | E57: 0 | F57: 0 | G57: 0 | H57: 0 | I57: 0 | J57: 0 | K57: 0 | L57: —
A58: + Deferred Revenue | B58: LT_DEFERRED_REVENUE | C58: — | D58: — | E58: 0 | F58: 0 | G58: 0 | H58: 0 | I58: 0 | J58: 0 | K58: 0 | L58: —
A59: + Passivo de imposto diferido | B59: BS_DEFERRED_TAX_LIABILITIES_LT | C59: — | D59: — | E59: 4.407 | F59: 5.253 | G59: 5.151 | H59: 5.018 | I59: 7.341 | J59: 7.899 | K59: 7.946 | L59: 10.543
A60: + Derivativos e hedging | B60: BS_DERIV_HEDGING_LIAB_LT | C60: — | D60: — | E60: — | F60: — | G60: — | H60: — | I60: — | J60: — | K60: — | L60: 0
A61: + Passivos LP div | B61: OTHER_NONCURRENT_LIABS_DETAILED | C61: 0.465 | D61: 4.751 | E61: 1.018 | F61: 1.292 | G61: 1.255 | H61: 7.806 | I61: 10.364 | J61: 11.39 | K61: 10.971 | L61: 30.603 | M61: AUMENTO SIGNIFICATIVO DA CONTA AO LONGO DOS ANOS
A62: Total passivo não-circulante | B62: NON_CUR_LIAB | C62: 3.891 | D62: 7.45 | E62: 7.397 | F62: 7.79 | G62: 7.143 | H62: 13.36 | I62: 18.04 | J62: 19.423 | K62: 18.917 | L62: 71.852
A63: Passivos totais | B63: BS_TOT_LIAB2 | C63: 10.956 | D63: 11.41 | E63: 9.856 | F63: 10.446 | G63: 11.309 | H63: 20.324 | I63: 28.427 | J63: 39.987 | K63: 35.637 | L63: 89.845
A64: + Ações em preferreds e capital híbrido | B64: PFD_EQTY_HYBRID_CAPITAL | C64: 0 | D64: 0 | E64: 0 | F64: 0 | G64: 0 | H64: 0 | I64: 0 | J64: 0 | K64: 0 | L64: 0
A65: + Capital social e APIC | B65: BS_SH_CAP_AND_APIC | C65: 63.085 | D65: 63.085 | E65: 33.085 | F65: 33.085 | G65: 33.085 | H65: 33.085 | I65: 33.085 | J65: 33.085 | K65: 33.085 | L65: 33.085
A66: + Ação ordinária | B66: BS_COMMON_STOCK | C66: — | D66: — | E66: 33.085 | F66: 33.085 | G66: 33.085 | H66: 33.085 | I66: 33.085 | J66: 33.085 | K66: 33.085 | L66: 33.085
A67: - Ações do Tesouro | B67: BS_AMT_OF_TSY_STOCK | C67: 0 | D67: 0 | E67: 0 | F67: 0 | G67: 0 | H67: 0 | I67: 0 | J67: 0 | K67: 0 | L67: 0
A68: + Lucros retidos | B68: BS_PURE_RETAINED_EARNINGS | C68: 15.333 | D68: 13.121 | E68: 7.047 | F68: 0 | G68: 25.209 | H68: 14.352 | I68: 21.52 | J68: 34.734 | K68: 28.151 | L68: 27.143
A69: + Outros ativos | B69: OTHER_EQUITY_RATIO | C69: 0 | D69: 0 | E69: 4.803 | F69: 162.669 | G69: 156.052 | H69: 140.022 | I69: 192.913 | J69: 192.913 | K69: 192.913 | L69: 192.684 | M69: AUMENTO SIGNIFICATIVO DA CONTA AO LONGO DOS ANOS
A70: Ações antes de participação minoritária | B70: EQTY_BEF_MINORITY_INT_DETAILED | C70: 78.418 | D70: 76.206 | E70: 44.935 | F70: 195.754 | G70: 214.346 | H70: 187.459 | I70: 247.518 | J70: 260.732 | K70: 254.149 | L70: 252.912
A71: + Minoridade/juros não controlados | B71: MINORITY_NONCONTROLLING_INTEREST | C71: 0 | D71: 0 | E71: 0 | F71: 0 | G71: 0 | H71: 0 | I71: 0 | J71: 0 | K71: 0 | L71: 0
A72: Patrimônio | B72: TOTAL_EQUITY | C72: 78.418 | D72: 76.206 | E72: 44.935 | F72: 195.754 | G72: 214.346 | H72: 187.459 | I72: 247.518 | J72: 260.732 | K72: 254.149 | L72: 252.912 | M72: EQUITY ou P/L
A73: Passivo total e patrimônio | B73: TOT_LIAB_AND_EQY | C73: 89.374 | D73: 87.616 | E73: 54.791 | F73: 206.2 | G73: 225.655 | H73: 207.783 | I73: 275.945 | J73: 300.719 | K73: 289.786 | L73: 342.757
A75: Itens de referência
A76: Normas contábeis | B76: ACCOUNTING_STANDARD | C76: IAS/IFRS | D76: IAS/IFRS | E76: IAS/IFRS | F76: IAS/IFRS | G76: IAS/IFRS | H76: IAS/IFRS | I76: IAS/IFRS | J76: IAS/IFRS | K76: IAS/IFRS | L76: IAS/IFRS
A77: Ações em circulação | B77: BS_SH_OUT | C77: 63.085 | D77: 63.085 | E77: 63.085 | F77: 63.085 | G77: 63.085 | H77: 63.085 | I77: 63.085 | J77: 63.085 | K77: 63.085 | L77: 63.085
A78: Número de ações do Tesouro | B78: BS_NUM_OF_TSY_SH | C78: 0 | D78: 0 | E78: 0 | F78: 0 | G78: 0 | H78: 0 | I78: 0 | J78: 0 | K78: 0 | L78: 0
A79: Orbigações de pensões | B79: BS_PENSION_RSRV | C79: 0 | D79: 0 | E79: 0 | F79: 0 | G79: 0 | H79: 0 | I79: 0 | J79: 0 | K79: 0 | L79: 0
A80: Obrigações de leasing operacional mínimo futuro | B80: BS_FUTURE_MIN_OPER_LEASE_OBLIG | C80: 0 | D80: 0 | E80: 0 | F80: 0 | G80: 0 | H80: 0 | I80: 0 | J80: 0 | K80: 0 | L80: 0
A81: Arrendamento capital - Total | B81: BS_TOTAL_CAPITAL_LEASES | C81: 0 | D81: 0 | E81: 0 | F81: 0 | G81: 0 | H81: 0 | I81: 0 | J81: 0 | K81: 0 | L81: 0
A82: Opções concedidas durante o período | B82: BS_OPTIONS_GRANTED | C82: — | D82: — | E82: — | F82: — | G82: — | H82: — | I82: — | J82: — | K82: — | L82: —
A83: Opções em aberto no fim do período | B83: BS_OPTIONS_OUTSTANDING | C83: — | D83: — | E83: — | F83: — | G83: — | H83: — | I83: — | J83: — | K83: — | L83: —
A84: Dívida líquida | B84: NET_DEBT | C84: -38.465 | D84: -37.564 | E84: -16.24 | F84: -29.236 | G84: -50.498 | H84: -30.47 | I84: -17.082 | J84: -20.995 | K84: -2.802 | L84: 23.473
A85: Dívida líq/Ação | B85: NET_DEBT_TO_SHRHLDR_EQTY | C85: -49.0512 | D85: -49.2927 | E85: -36.1411 | F85: -14.9351 | G85: -23.5591 | H85: -16.2542 | I85: -6.9013 | J85: -8.0523 | K85: -1.1025 | L85: 9.2811
A86: Ratio capital ordinário tangível | B86: TCE_RATIO | C86: 87.7414 | D86: 86.9773 | E86: 82.0116 | F86: 94.934 | G86: 94.9806 | H86: 90.2053 | I86: 89.6685 | J86: 86.6729 | K86: 87.6769 | L86: 73.6948
A87: Ratio de circulante | B87: CUR_RATIO | C87: 10.4747 | D87: 17.3942 | E87: 21.5885 | F87: 19.7105 | G87: 18.0883 | H87: 7.9117 | I87: 5.8567 | J87: 3.3373 | K87: 3.2961 | L87: 3.9149
A88: Ciclo de conversão de caixa | B88: CASH_CONVERSION_CYCLE | C88: 26.554 | D88: — | E88: — | F88: — | G88: — | H88: — | I88: — | J88: — | K88: — | L88: —
A89: Fonte: Bloomberg | C89: Clique botão direito p/exibir a transp de dados (não suportado p/tds valores)

Sheet Bal patrim B3 - 3º TRI 2025
A1: 45930
A2: AFLUENTE TRANSMISSÃO DE ENERGIA ELÉTRICA S/A - Balanço Patrimonial Passivo - (Reais Mil)
A4: Conta | B4: Descrição | C4: 30/09/2025 | D4: 31/12/2024
A5: 2 | B5: Passivo Total | C5: 376.972 | D5: 342.757
A6: 2.01 | B6: Passivo Circulante | C6: 41.450 | D6: 17.993
A7: 2.01.01 | B7: Obrigações Sociais e Trabalhistas | C7: 593 | D7: 665
A8: 2.01.01.01 | B8: Obrigações Sociais | C8: 593 | D8: 665
A9: 2.01.01.01.01 | B9: Salários e encargos a pagar | C9: 593 | D9: 665
A10: 2.01.01.02 | B10: Obrigações Trabalhistas
A11: 2.01.02 | B11: Fornecedores | C11: 2.343 | D11: 6.244
A12: 2.01.02.01 | B12: Fornecedores Nacionais | C12: 2.343 | D12: 6.244
A13: 2.01.02.02 | B13: Fornecedores Estrangeiros
A14: 2.01.03 | B14: Obrigações Fiscais | C14: 2.022 | D14: 982
A15: 2.01.03.01 | B15: Obrigações Fiscais Federais | C15: 1.899 | D15: 790
A16: 2.01.03.01.01 | B16: Imposto de Renda e Contribuição Social a Pagar | C16: 761 | D16: 0
A17: 2.01.03.01.02 | B17: Programa de Integração Social - PIS | C17: 131 | D17: 98
A18: 2.01.03.01.03 | B18: Contribuição para o Financiamento da Seguridade Social - COFINS | C18: 609 | D18: 455
A19: 2.01.03.01.04 | B19: Instituto Nacional da Seguridade Social - INSS | C19: 114 | D19: 91
A20: 2.01.03.01.05 | B20: Outros | C20: 284 | D20: 146
A21: 2.01.03.02 | B21: Obrigações Fiscais Estaduais | C21: 81 | D21: 146
A22: 2.01.03.03 | B22: Obrigações Fiscais Municipais | C22: 42 | D22: 46
A23: 2.01.04 | B23: Empréstimos e Financiamentos | C23: 1.049 | D23: 88
A24: 2.01.04.01 | B24: Empréstimos e Financiamentos | C24: 1.049 | D24: 88
A25: 2.01.04.01.01 | B25: Em Moeda Nacional
A26: 2.01.04.01.02 | B26: Em Moeda Estrangeira | C26: 1.049 | D26: 88
A27: 2.01.04.02 | B27: Debêntures
A28: 2.01.04.03 | B28: Financiamento por Arrendamento
A29: 2.01.05 | B29: Outras Obrigações | C29: 35.443 | D29: 10.014
A30: 2.01.05.01 | B30: Passivos com Partes Relacionadas
A31: 2.01.05.01.01 | B31: Débitos com Coligadas
A32: 2.01.05.01.02 | B32: Débitos com Controladas
A33: 2.01.05.01.03 | B33: Débitos com Controladores
A34: 2.01.05.01.04 | B34: Débitos com Outras Partes Relacionadas
A35: 2.01.05.02 | B35: Outros | C35: 35.443 | D35: 10.014
A36: 2.01.05.02.01 | B36: Dividendos e JCP a Pagar
A37: 2.01.05.02.02 | B37: Dividendo Mínimo Obrigatório a Pagar
A38: 2.01.05.02.03 | B38: Obrigações por Pagamentos Baseados em Ações
A39: 2.01.05.02.04 | B39: Taxas regulamentares | C39: 1.655 | D39: 807
A40: 2.01.05.02.05 | B40: Outros passivos circulantes | C40: 5.119 | D40: 3.975
A41: 2.01.05.02.06 | B41: Dividendos e Juros Sobre Capital Pr¢prio | C41: 26.577 | D41: 5.144
A42: 2.01.05.02.07 | B42: Instrumento financeiro derivativo | C42: 2.092 | D42: 88
A43: 2.01.06 | B43: Provisões
A44: 2.01.06.01 | B44: Provisões Fiscais Previdenciárias Trabalhistas e Cíveis
A45: 2.01.06.01.01 | B45: Provisões Fiscais
A46: 2.01.06.01.02 | B46: Provisões Previdenciárias e Trabalhistas
A47: 2.01.06.01.03 | B47: Provisões para Benefícios a Empregados
A48: 2.01.06.01.04 | B48: Provisões Cíveis
A49: 2.01.06.02 | B49: Outras Provisões
A50: 2.01.06.02.01 | B50: Provisões para Garantias
A51: 2.01.06.02.02 | B51: Provisões para Reestruturação
A52: 2.01.06.02.03 | B52: Provisões para Passivos Ambientais e de Desativação
A53: 2.01.07 | B53: Passivos sobre Ativos Não-Correntes a Venda e Descontinuados
A54: 2.01.07.01 | B54: Passivos sobre Ativos Não-Correntes a Venda
A55: 2.01.07.02 | B55: Passivos sobre Ativos de Operações Descontinuadas
A56: 2.02 | B56: Passivo Não Circulante | C56: 80.129 | D56: 71.852
A57: 2.02.01 | B57: Empréstimos e Financiamentos | C57: 26.373 | D57: 30.706
A58: 2.02.01.01 | B58: Empréstimos e Financiamentos | C58: 26.373 | K58: 26.373
A59: 2.02.01.01.01 | B59: Em Moeda Nacional | K59: 1.049
A60: 2.02.01.01.02 | B60: Em Moeda Estrangeira | C60: 26.373 | D60: 30.706 | K60: =K58+K59 -> 27.422
A61: 2.02.01.02 | B61: Debêntures
A62: 2.02.01.03 | B62: Financiamento por Arrendamento
A63: 2.02.02 | B63: Outras Obrigações | C63: 32.301 | D63: 30.603
A64: 2.02.02.01 | B64: Passivos com Partes Relacionadas
A65: 2.02.02.01.01 | B65: Débitos com Coligadas
A66: 2.02.02.01.02 | B66: Débitos com Controladas
A67: 2.02.02.01.03 | B67: Débitos com Controladores
A68: 2.02.02.01.04 | B68: Débitos com Outras Partes Relacionadas
A69: 2.02.02.02 | B69: Outros | C69: 32.301 | D69: 30.603
A70: 2.02.02.02.01 | B70: Obrigações por Pagamentos Baseados em Ações
A71: 2.02.02.02.02 | B71: Adiantamento para Futuro Aumento de Capital
A72: 2.02.02.02.03 | B72: Taxas regulamentares | C72: 28.377 | D72: 29.995
A73: 2.02.02.02.04 | B73: Outros passivos não circulantes | C73: 49 | D73: 150
A74: 2.02.02.02.05 | B74: Provisões | C74: 476 | D74: 458
A75: 2.02.02.02.06 | B75: Instrumento financeiros derivativos | C75: 3.399 | D75: 0
A76: 2.02.03 | B76: Tributos Diferidos | C76: 21.455 | D76: 10.543
A77: 2.02.03.01 | B77: Imposto de Renda e Contribuição Social Diferidos | C77: 21.455 | D77: 10.543
A78: 2.02.04 | B78: Provisões
A79: 2.02.04.01 | B79: Provisões Fiscais Previdenciárias Trabalhistas e Cíveis
A80: 2.02.04.01.01 | B80: Provisões Fiscais
A81: 2.02.04.01.02 | B81: Provisões Previdenciárias e Trabalhistas
A82: 2.02.04.01.03 | B82: Provisões para Benefícios a Empregados
A83: 2.02.04.01.04 | B83: Provisões Cíveis
A84: 2.02.04.02 | B84: Outras Provisões
A85: 2.02.04.02.01 | B85: Provisões para Garantias
A86: 2.02.04.02.02 | B86: Provisões para Reestruturação
A87: 2.02.04.02.03 | B87: Provisões para Passivos Ambientais e de Desativação
A88: 2.02.05 | B88: Passivos sobre Ativos Não-Correntes a Venda e Descontinuados
A89: 2.02.05.01 | B89: Passivos sobre Ativos Não-Correntes a Venda
... A94: 2.02.06.03 | B94: Subvenções de Investimento a Apropriar
A95: 2.03 | B95: Patrimônio Líquido | C95: 255.393 | D95: 252.912
A96: 2.03.01 | B96: Capital Social Realizado | C96: 33.085 | D96: 33.085
A97: 2.03.02 | B97: Reservas de Capital
A98: 2.03.02.01 | B98: Ágio na Emissão de Ações
A99: 2.03.02.02 | B99: Reserva Especial de Ágio na Incorporação
A100: 2.03.02.03 | B100: Alienação de Bônus de Subscrição
A101: 2.03.02.04 | B101: Opções Outorgadas
A102: 2.03.02.05 | B102: Ações em Tesouraria
A103: 2.03.02.06 | B103: Adiantamento para Futuro Aumento de Capital
A104: 2.03.03 | B104: Reservas de Reavaliação
A105: 2.03.04 | B105: Reservas de Lucros | C105: 199.530 | D105: 220.056
...

Sheet Bal patrim B3 - 3º TRI 2025 Atv
A1: 45930
A2: AFLUENTE TRANSMISSÃO DE ENERGIA ELÉTRICA S/A - Balanço Patrimonial Ativo - (Reais Mil)
A4: Conta | B4: Descrição | C4: 30/09/2025 | D4: 31/12/2024
A5: 1 | B5: Ativo Total | C5: 376.972 | D5: 342.757
A6: 1.01 | B6: Ativo Circulante | C6: 120.228 | D6: 70.441
A7: 1.01.01 | B7: Caixa e Equivalentes de Caixa | C7: 38.090 | D7: 7.321 | E7: 38.09
A8: 1.01.02 | B8: Aplicações Financeiras
A9: 1.01.02.01 | B9: Aplicações Financeiras Avaliadas a Valor Justo através do Resultado
A10: 1.01.02.01.01 | B10: Títulos para Negociação
A11: 1.01.02.01.02 | B11: Títulos Designados a Valor Justo
A12: 1.01.02.02 | B12: Aplicações Financeiras Avaliadas a Valor Justo através de Outros Resultados Abrangentes
A13: 1.01.02.03 | B13: Aplicações Financeiras Avaliadas ao Custo Amortizado
A14: 1.01.03 | B14: Contas a Receber | C14: 24.251 | D14: 7.345
A15: 1.01.03.01 | B15: Clientes | C15: 24.251 | D15: 7.345
A16: 1.01.03.02 | B16: Outras Contas a Receber
A17: 1.01.04 | B17: Estoques
A18: 1.01.05 | B18: Ativos Biológicos
A19: 1.01.06 | B19: Tributos a Recuperar | C19: 3.014 | D19: 3.658
A20: 1.01.06.01 | B20: Tributos Correntes a Recuperar | C20: 3.014 | D20: 3.658
A21: 1.01.07 | B21: Despesas Antecipadas | C21: 360 | D21: 54
A22: 1.01.08 | B22: Outros Ativos Circulantes | C22: 54.513 | D22: 52.063
A23: 1.01.08.01 | B23: Ativos Não-Correntes a Venda
A24: 1.01.08.02 | B24: Ativos de Operações Descontinuadas
A25: 1.01.08.03 | B25: Outros | C25: 54.513 | D25: 52.063
A26: 1.01.08.03.01 | B26: Concessão do serviço público (ativo financeiro)
A27: 1.01.08.03.02 | B27: Concessão do serviço público (ativo contratual) | C27: 48.998 | D27: 48.132
A28: 1.01.08.03.03 | B28: Outros | C28: 5.515 | D28: 3.931
A29: 1.02 | B29: Ativo Não Circulante | C29: 256.744 | D29: 272.316
A30: 1.02.01 | B30: Ativo Realizável a Longo Prazo | C30: 252.115 | D30: 267.168
A31: 1.02.01.01 | B31: Aplicações Financeiras Avaliadas a Valor Justo através do Resultado
A32: 1.02.01.01.01 | B32: Títulos Designados a Valor Justo
A33: 1.02.01.02 | B33: Aplicações Financeiras Avaliadas a Valor Justo através de Outros Resultados Abrangentes
A34: 1.02.01.03 | B34: Aplicações Financeiras Avaliadas ao Custo Amortizado
A35: 1.02.01.04 | B35: Contas a Receber
A36: 1.02.01.04.01 | B36: Clientes
A37: 1.02.01.04.02 | B37: Outras Contas a Receber
A38: 1.02.01.05 | B38: Estoques
A39: 1.02.01.06 | B39: Ativos Biológicos
A40: 1.02.01.07 | B40: Tributos Diferidos
A41: 1.02.01.07.01 | B41: Imposto de Renda e Contribuição Social Diferidos
A42: 1.02.01.08 | B42: Despesas Antecipadas
... A47: 1.02.01.09.04 | B47: Créditos com Outras Partes Relacionadas
A48: 1.02.01.10 | B48: Outros Ativos Não Circulantes | C48: 252.115 | D48: 267.168
A49: 1.02.01.10.01 | B49: Ativos Não-Correntes a Venda
A50: 1.02.01.10.02 | B50: Ativos de Operações Descontinuadas
A51: 1.02.01.10.03 | B51: Depósitos judiciais | C51: 2.156 | D51: 2.032
A52: 1.02.01.10.04 | B52: Concessão do serviço público (ativo financeiro)
A53: 1.02.01.10.05 | B53: Concessão do serviço público (ativo contratual) | C53: 249.624 | D53: 264.442
A54: 1.02.01.10.06 | B54: Impostos e contribuições a recuperar | C54: 335 | D54: 335
A55: 1.02.01.10.07 | B55: Outros
A56: 1.02.01.10.08 | B56: Instrumentos financeiros derivativos | C56: 0 | D56: 359
A57: 1.02.02 | B57: Investimentos
A58: 1.02.02.01 | B58: Participações Societárias
A59: 1.02.02.01.01 | B59: Participações em Coligadas
A60: 1.02.02.01.02 | B60: Participações em Controladas
A61: 1.02.02.01.03 | B61: Participações em Controladas em Conjunto
A62: 1.02.02.01.04 | B62: Outros Investimentos
A63: 1.02.02.02 | B63: Propriedades para Investimento
A64: 1.02.03 | B64: Imobilizado | C64: 3.437 | D64: 3.939
A65: 1.02.03.01 | B65: Imobilizado em Operação | C65: 2.489 | D65: 2.746
A66: 1.02.03.02 | B66: Direito de Uso em Arrendamento
A67: 1.02.03.03 | B67: Imobilizado em Andamento | C67: 948 | D67: 1.193
A68: 1.02.04 | B68: Intangível | C68: 1.192 | D68: 1.209
A69: 1.02.04.01 | B69: Intangíveis | C69: 1.192 | D69: 1.209
A70: 1.02.04.01.01 | B70: Contrato de Concessão
A71: 1.02.04.01.02 | B71: Intangível | C71: 1.192 | D71: 1.209
A73: Fonte: B3
